{
  "type": "Feature",
  "properties": {
    "gn:admin1_code":"02",
    "gn:asciiname":"Djangatebe",
    "gn:country_code":"GA",
    "gn:dem":552,
    "gn:feature_class":"P",
    "gn:feature_code":"PPL",
    "gn:name":"Djangat\u00e9b\u00e9",
    "gn:population":0,
    "gn:timezone":"Africa/Libreville",
    "iso:country":"GA",
    "wof:name":"Djangatebe",
    "wof:placetype":"locality"
},
  "geometry": {"coordinates":[13.08998,-1.69027],"type":"Point"}
}