{
  "type": "Feature",
  "properties": {
    "gn:admin1_code":"04",
    "gn:asciiname":"Ndoubi",
    "gn:country_code":"GA",
    "gn:dem":525,
    "gn:feature_class":"P",
    "gn:feature_code":"PPL",
    "gn:name":"Ndoubi",
    "gn:population":0,
    "gn:timezone":"Africa/Libreville",
    "iso:country":"GA",
    "wof:name":"Ndoubi",
    "wof:placetype":"locality"
},
  "geometry": {"coordinates":[11.60189,-2.0797],"type":"Point"}
}