{
  "type": "Feature",
  "properties": {
    "gn:admin1_code":"01",
    "gn:asciiname":"Monda",
    "gn:country_code":"GA",
    "gn:dem":45,
    "gn:feature_class":"P",
    "gn:feature_code":"PPL",
    "gn:name":"Monda",
    "gn:population":0,
    "gn:timezone":"Africa/Libreville",
    "iso:country":"GA",
    "name:ara_x_preferred":[
        "\u0645\u0648\u0646\u062f\u0627"
    ],
    "name:arg_x_preferred":[
        "Monda"
    ],
    "name:ast_x_preferred":[
        "Monda"
    ],
    "name:bre_x_preferred":[
        "Monda"
    ],
    "name:cat_x_preferred":[
        "Monda"
    ],
    "name:ceb_x_preferred":[
        "Monda"
    ],
    "name:eus_x_preferred":[
        "Monda"
    ],
    "name:fra_x_preferred":[
        "Monda"
    ],
    "name:hat_x_preferred":[
        "Monda"
    ],
    "name:hun_x_preferred":[
        "Monda"
    ],
    "name:hye_x_preferred":[
        "\u0544\u0578\u0576\u0564\u0561"
    ],
    "name:ita_x_preferred":[
        "Monda"
    ],
    "name:kaz_x_preferred":[
        "\u041c\u043e\u043d\u0434\u0430"
    ],
    "name:kon_x_preferred":[
        "Monda"
    ],
    "name:msa_x_preferred":[
        "Monda"
    ],
    "name:nld_x_preferred":[
        "Monda"
    ],
    "name:oci_x_preferred":[
        "Monda"
    ],
    "name:pol_x_preferred":[
        "Monda"
    ],
    "name:por_x_preferred":[
        "Monda"
    ],
    "name:rus_x_preferred":[
        "\u041c\u043e\u043d\u0434\u0430"
    ],
    "name:spa_x_preferred":[
        "Monda"
    ],
    "name:swe_x_preferred":[
        "Monda"
    ],
    "name:ukr_x_preferred":[
        "\u041c\u043e\u043d\u0434\u0430"
    ],
    "name:uzb_x_preferred":[
        "Monda"
    ],
    "name:vie_x_preferred":[
        "Monda"
    ],
    "name:war_x_preferred":[
        "Monda"
    ],
    "wof:name":"Monda",
    "wof:placetype":"locality"
},
  "geometry": {"coordinates":[9.83333,0.28333],"type":"Point"}
}