{
  "type": "Feature",
  "properties": {
    "gn:admin1_code":"04",
    "gn:asciiname":"Lebagny",
    "gn:country_code":"GA",
    "gn:dem":788,
    "gn:feature_class":"P",
    "gn:feature_code":"PPL",
    "gn:name":"Lebagny",
    "gn:population":0,
    "gn:timezone":"Africa/Libreville",
    "iso:country":"GA",
    "wof:name":"Lebagny",
    "wof:placetype":"locality"
},
  "geometry": {"coordinates":[12.16667,-1.88333],"type":"Point"}
}