{
  "type": "Feature",
  "properties": {
    "gn:admin1_code":"07",
    "gn:asciiname":"Mopoumba",
    "gn:country_code":"GA",
    "gn:dem":467,
    "gn:feature_class":"P",
    "gn:feature_code":"PPL",
    "gn:name":"Mopoumba",
    "gn:population":0,
    "gn:timezone":"Africa/Libreville",
    "iso:country":"GA",
    "wof:name":"Mopoumba",
    "wof:placetype":"locality"
},
  "geometry": {"coordinates":[12.03333,-1.13333],"type":"Point"}
}