{
  "type": "Feature",
  "properties": {
    "gn:admin1_code":"03",
    "gn:asciiname":"Otanda",
    "gn:country_code":"GA",
    "gn:dem":20,
    "gn:feature_class":"P",
    "gn:feature_code":"PPL",
    "gn:name":"Otanda",
    "gn:population":0,
    "gn:timezone":"Africa/Libreville",
    "iso:country":"GA",
    "wof:name":"Otanda",
    "wof:placetype":"locality"
},
  "geometry": {"coordinates":[10.08333,-0.65],"type":"Point"}
}