{
  "type": "Feature",
  "properties": {
    "gn:admin1_code":"06",
    "gn:asciiname":"Adzo",
    "gn:country_code":"GA",
    "gn:dem":551,
    "gn:feature_class":"P",
    "gn:feature_code":"PPL",
    "gn:name":"Adzo",
    "gn:population":0,
    "gn:timezone":"Africa/Libreville",
    "iso:country":"GA",
    "wof:name":"Adzo",
    "wof:placetype":"locality"
},
  "geometry": {"coordinates":[12.66667,0.58333],"type":"Point"}
}