{
  "type": "Feature",
  "properties": {
    "gn:admin1_code":"07",
    "gn:asciiname":"Oubendji",
    "gn:country_code":"GA",
    "gn:dem":696,
    "gn:feature_class":"P",
    "gn:feature_code":"PPL",
    "gn:name":"Oubendji",
    "gn:population":0,
    "gn:timezone":"Africa/Libreville",
    "iso:country":"GA",
    "wof:name":"Oubendji",
    "wof:placetype":"locality"
},
  "geometry": {"coordinates":[12.15,-1.48333],"type":"Point"}
}