{
  "type": "Feature",
  "properties": {
    "gn:admin1_code":"04",
    "gn:asciiname":"Goulougai",
    "gn:country_code":"GA",
    "gn:dem":259,
    "gn:feature_class":"P",
    "gn:feature_code":"PPL",
    "gn:name":"Goulouga\u00ef",
    "gn:population":0,
    "gn:timezone":"Africa/Libreville",
    "iso:country":"GA",
    "wof:name":"Goulougai",
    "wof:placetype":"locality"
},
  "geometry": {"coordinates":[10.55736,-2.11372],"type":"Point"}
}