{
  "type": "Feature",
  "properties": {
    "gn:admin1_code":"05",
    "gn:asciiname":"Moubou",
    "gn:country_code":"GA",
    "gn:dem":111,
    "gn:feature_class":"P",
    "gn:feature_code":"PPL",
    "gn:name":"Moubou",
    "gn:population":0,
    "gn:timezone":"Africa/Libreville",
    "iso:country":"GA",
    "wof:name":"Moubou",
    "wof:placetype":"locality"
},
  "geometry": {"coordinates":[10.62042,-2.53038],"type":"Point"}
}