{
  "type": "Feature",
  "properties": {
    "gn:admin1_code":"09",
    "gn:asciiname":"Essoun-Alem",
    "gn:country_code":"GA",
    "gn:dem":579,
    "gn:feature_class":"P",
    "gn:feature_code":"PPL",
    "gn:name":"Essoun-Alem",
    "gn:population":0,
    "gn:timezone":"Africa/Libreville",
    "iso:country":"GA",
    "wof:name":"Essoun-Alem",
    "wof:placetype":"locality"
},
  "geometry": {"coordinates":[11.45,0.96667],"type":"Point"}
}