{
  "type": "Feature",
  "properties": {
    "gn:admin1_code":"07",
    "gn:asciiname":"Comi",
    "gn:country_code":"GA",
    "gn:dem":599,
    "gn:feature_class":"P",
    "gn:feature_code":"PPL",
    "gn:name":"Comi",
    "gn:population":0,
    "gn:timezone":"Africa/Libreville",
    "iso:country":"GA",
    "wof:name":"Comi",
    "wof:placetype":"locality"
},
  "geometry": {"coordinates":[12.13333,-1.41667],"type":"Point"}
}