{
  "type": "Feature",
  "properties": {
    "gn:admin1_code":"09",
    "gn:asciiname":"Abame",
    "gn:country_code":"GA",
    "gn:dem":634,
    "gn:feature_class":"P",
    "gn:feature_code":"PPL",
    "gn:name":"Abame",
    "gn:population":0,
    "gn:timezone":"Africa/Libreville",
    "iso:country":"GA",
    "wof:name":"Abame",
    "wof:placetype":"locality"
},
  "geometry": {"coordinates":[11.66874,1.69573],"type":"Point"}
}