{
  "type": "Feature",
  "properties": {
    "gn:gn_country":"GA",
    "gn:gn_fcode":"PPL",
    "gn:gn_pop":7155,
    "gn:population":7155,
    "iso:country":"GA",
    "name:ceb_x_preferred":[
        "Okondja"
    ],
    "name:eng_x_preferred":[
        "Okondja"
    ],
    "name:fra_x_preferred":[
        "Okandja"
    ],
    "name:ita_x_preferred":[
        "Okondja"
    ],
    "name:jpn_x_preferred":[
        "\u30aa\u30b3\u30f3\u30b8\u30e3"
    ],
    "name:nld_x_preferred":[
        "Okondja"
    ],
    "name:pol_x_preferred":[
        "Okandja"
    ],
    "name:por_x_preferred":[
        "Okondja"
    ],
    "name:rus_x_preferred":[
        "\u041e\u043a\u043e\u043d\u0434\u0436\u0430"
    ],
    "name:spa_x_preferred":[
        "Okondja"
    ],
    "name:swe_x_preferred":[
        "Okondja"
    ],
    "name:unk_x_variant":[
        "Okondi"
    ],
    "qs_pg:aaroncc":"GA",
    "qs_pg:gn_country":"GA",
    "qs_pg:gn_fcode":"PPL",
    "qs_pg:gn_pop":7155,
    "qs_pg:name":"Okondja",
    "qs_pg:photos_9r":0,
    "qs_pg:photos_sr":0,
    "qs_pg:pop_sr":5,
    "qs_pg:qs_pg_placetype":"locality",
    "wof:name":"Okondja",
    "wof:placetype":"locality",
    "wof:population":7155
},
  "geometry": {"coordinates":[13.67533,-0.65487],"type":"Point"}
}