{
  "type": "Feature",
  "properties": {
    "gn:admin1_code":"04",
    "gn:asciiname":"Dipouya",
    "gn:country_code":"GA",
    "gn:dem":620,
    "gn:feature_class":"P",
    "gn:feature_code":"PPL",
    "gn:name":"Dipouya",
    "gn:population":0,
    "gn:timezone":"Africa/Libreville",
    "iso:country":"GA",
    "wof:name":"Dipouya",
    "wof:placetype":"locality"
},
  "geometry": {"coordinates":[11.93333,-1.45],"type":"Point"}
}