{
  "type": "Feature",
  "properties": {
    "gn:admin1_code":"09",
    "gn:asciiname":"Assengama",
    "gn:country_code":"GA",
    "gn:dem":674,
    "gn:feature_class":"P",
    "gn:feature_code":"PPL",
    "gn:name":"Assengama",
    "gn:population":0,
    "gn:timezone":"Africa/Libreville",
    "iso:country":"GA",
    "wof:name":"Assengama",
    "wof:placetype":"locality"
},
  "geometry": {"coordinates":[11.63372,1.37794],"type":"Point"}
}