{
  "type": "Feature",
  "properties": {
    "gn:admin1_code":"05",
    "gn:asciiname":"Tono",
    "gn:country_code":"GA",
    "gn:dem":96,
    "gn:feature_class":"P",
    "gn:feature_code":"PPL",
    "gn:name":"Tono",
    "gn:population":0,
    "gn:timezone":"Africa/Libreville",
    "iso:country":"GA",
    "wof:name":"Tono",
    "wof:placetype":"locality"
},
  "geometry": {"coordinates":[10.8265,-3.07484],"type":"Point"}
}