{
  "type": "Feature",
  "properties": {
    "gn:admin1_code":"08",
    "gn:asciiname":"Boka",
    "gn:country_code":"GA",
    "gn:dem":30,
    "gn:feature_class":"P",
    "gn:feature_code":"PPL",
    "gn:name":"Boka",
    "gn:population":0,
    "gn:timezone":"Africa/Libreville",
    "iso:country":"GA",
    "name:ceb_x_preferred":[
        "Boka"
    ],
    "name:deu_x_preferred":[
        "Boka"
    ],
    "name:fra_x_preferred":[
        "Boka"
    ],
    "name:hun_x_preferred":[
        "Boka"
    ],
    "name:rus_x_preferred":[
        "\u0411\u043e\u043a\u0430"
    ],
    "name:slv_x_preferred":[
        "Boka"
    ],
    "name:srp_x_preferred":[
        "\u0411\u043e\u043a\u0430"
    ],
    "name:swe_x_preferred":[
        "Boka"
    ],
    "wof:name":"Boka",
    "wof:placetype":"locality"
},
  "geometry": {"coordinates":[9.43333,-1.71667],"type":"Point"}
}