{
  "type": "Feature",
  "properties": {
    "gn:admin1_code":"04",
    "gn:asciiname":"Lekimbou",
    "gn:country_code":"GA",
    "gn:dem":262,
    "gn:feature_class":"P",
    "gn:feature_code":"PPL",
    "gn:name":"Lekimbou",
    "gn:population":0,
    "gn:timezone":"Africa/Libreville",
    "iso:country":"GA",
    "wof:name":"Lekimbou",
    "wof:placetype":"locality"
},
  "geometry": {"coordinates":[11.63333,-2.31667],"type":"Point"}
}