{
  "type": "Feature",
  "properties": {
    "gn:admin1_code":"03",
    "gn:asciiname":"Mimbal Mibe",
    "gn:country_code":"GA",
    "gn:dem":45,
    "gn:feature_class":"P",
    "gn:feature_code":"PPL",
    "gn:name":"Mimbal Mib\u00e9",
    "gn:population":0,
    "gn:timezone":"Africa/Libreville",
    "iso:country":"GA",
    "name:und_x_variant":[
        "Mimbal Mib\u00e9",
        "Mimbal\u00e9-Mib\u00e9"
    ],
    "wof:name":"Mimbal Mibe",
    "wof:placetype":"locality"
},
  "geometry": {"coordinates":[10.53008,-0.2234],"type":"Point"}
}