{
  "type": "Feature",
  "properties": {
    "gn:admin1_code":"04",
    "gn:asciiname":"Degueli",
    "gn:country_code":"GA",
    "gn:dem":103,
    "gn:feature_class":"P",
    "gn:feature_code":"PPL",
    "gn:name":"D\u00e9gueli",
    "gn:population":0,
    "gn:timezone":"Africa/Libreville",
    "iso:country":"GA",
    "wof:name":"Degueli",
    "wof:placetype":"locality"
},
  "geometry": {"coordinates":[10.76095,-1.69755],"type":"Point"}
}