{
  "type": "Feature",
  "properties": {
    "gn:admin1_code":"02",
    "gn:asciiname":"Etchougou",
    "gn:country_code":"GA",
    "gn:dem":323,
    "gn:feature_class":"P",
    "gn:feature_code":"PPL",
    "gn:name":"Etchougou",
    "gn:population":0,
    "gn:timezone":"Africa/Libreville",
    "iso:country":"GA",
    "wof:name":"Etchougou",
    "wof:placetype":"locality"
},
  "geometry": {"coordinates":[13.53333,-1.18333],"type":"Point"}
}