{
  "type": "Feature",
  "properties": {
    "gn:admin1_code":"03",
    "gn:asciiname":"Anonebere",
    "gn:country_code":"GA",
    "gn:dem":59,
    "gn:feature_class":"P",
    "gn:feature_code":"PPL",
    "gn:name":"Anon\u00e9b\u00e9r\u00e9",
    "gn:population":0,
    "gn:timezone":"Africa/Libreville",
    "iso:country":"GA",
    "name:und_x_variant":[
        "Anon\u00e9b\u00e9r\u00e9"
    ],
    "wof:name":"Anonebere",
    "wof:placetype":"locality"
},
  "geometry": {"coordinates":[10.51667,-0.26667],"type":"Point"}
}