{
  "type": "Feature",
  "properties": {
    "gn:admin1_code":"01",
    "gn:asciiname":"Mekamenzogh",
    "gn:country_code":"GA",
    "gn:dem":17,
    "gn:feature_class":"P",
    "gn:feature_code":"PPL",
    "gn:name":"Mekamenzogh",
    "gn:population":0,
    "gn:timezone":"Africa/Libreville",
    "iso:country":"GA",
    "wof:name":"Mekamenzogh",
    "wof:placetype":"locality"
},
  "geometry": {"coordinates":[9.60359,0.82269],"type":"Point"}
}