{
  "type": "Feature",
  "properties": {
    "gn:admin1_code":"01",
    "gn:asciiname":"Nzong Bour",
    "gn:country_code":"GA",
    "gn:dem":80,
    "gn:feature_class":"P",
    "gn:feature_code":"PPL",
    "gn:name":"Nzong Bour",
    "gn:population":0,
    "gn:timezone":"Africa/Libreville",
    "iso:country":"GA",
    "wof:name":"Nzong Bour",
    "wof:placetype":"locality"
},
  "geometry": {"coordinates":[9.65,0.36667],"type":"Point"}
}