{
  "type": "Feature",
  "properties": {
    "gn:admin1_code":"04",
    "gn:asciiname":"Egmounga",
    "gn:country_code":"GA",
    "gn:dem":191,
    "gn:feature_class":"P",
    "gn:feature_code":"PPL",
    "gn:name":"Egmounga",
    "gn:population":0,
    "gn:timezone":"Africa/Libreville",
    "iso:country":"GA",
    "wof:name":"Egmounga",
    "wof:placetype":"locality"
},
  "geometry": {"coordinates":[11.25,-1.88333],"type":"Point"}
}