{
  "type": "Feature",
  "properties": {
    "gn:admin1_code":"09",
    "gn:asciiname":"Yoss I",
    "gn:country_code":"GA",
    "gn:dem":631,
    "gn:feature_class":"P",
    "gn:feature_code":"PPL",
    "gn:name":"Yoss I",
    "gn:population":0,
    "gn:timezone":"Africa/Libreville",
    "iso:country":"GA",
    "wof:name":"Yoss I",
    "wof:placetype":"locality"
},
  "geometry": {"coordinates":[11.4819,1.81323],"type":"Point"}
}