{
  "type": "Feature",
  "properties": {
    "gn:admin1_code":"09",
    "gn:asciiname":"Nkolayop",
    "gn:country_code":"GA",
    "gn:dem":676,
    "gn:feature_class":"P",
    "gn:feature_code":"PPL",
    "gn:name":"Nkolayop",
    "gn:population":0,
    "gn:timezone":"Africa/Libreville",
    "iso:country":"GA",
    "wof:name":"Nkolayop",
    "wof:placetype":"locality"
},
  "geometry": {"coordinates":[11.49823,1.51393],"type":"Point"}
}