{
  "type": "Feature",
  "properties": {
    "gn:admin1_code":"09",
    "gn:asciiname":"Bengiaga",
    "gn:country_code":"GA",
    "gn:dem":618,
    "gn:feature_class":"P",
    "gn:feature_code":"PPL",
    "gn:name":"Bengiaga",
    "gn:population":0,
    "gn:timezone":"Africa/Libreville",
    "iso:country":"GA",
    "wof:name":"Bengiaga",
    "wof:placetype":"locality"
},
  "geometry": {"coordinates":[11.98333,2.11667],"type":"Point"}
}