{
  "type": "Feature",
  "properties": {
    "gn:admin1_code":"02",
    "gn:asciiname":"Eleko",
    "gn:country_code":"GA",
    "gn:dem":578,
    "gn:feature_class":"P",
    "gn:feature_code":"PPL",
    "gn:name":"Eleko",
    "gn:population":0,
    "gn:timezone":"Africa/Libreville",
    "iso:country":"GA",
    "wof:name":"Eleko",
    "wof:placetype":"locality"
},
  "geometry": {"coordinates":[13.71667,-0.26667],"type":"Point"}
}