{
  "type": "Feature",
  "properties": {
    "gn:admin1_code":"02",
    "gn:asciiname":"Kabala",
    "gn:country_code":"GA",
    "gn:dem":580,
    "gn:feature_class":"P",
    "gn:feature_code":"PPL",
    "gn:name":"Kabala",
    "gn:population":0,
    "gn:timezone":"Africa/Libreville",
    "iso:country":"GA",
    "name:ceb_x_preferred":[
        "Kabala"
    ],
    "name:est_x_preferred":[
        "Kabala"
    ],
    "name:fra_x_preferred":[
        "Kabala"
    ],
    "name:hye_x_preferred":[
        "\u053f\u0561\u0562\u0561\u056c\u0561"
    ],
    "name:ita_x_preferred":[
        "Kabala"
    ],
    "name:nld_x_preferred":[
        "Kabala"
    ],
    "name:pol_x_preferred":[
        "Kabala"
    ],
    "name:ron_x_preferred":[
        "Kabala"
    ],
    "name:rus_x_preferred":[
        "\u041a\u0430\u0431\u0430\u043b\u0430"
    ],
    "name:slk_x_preferred":[
        "Kabala"
    ],
    "name:swe_x_preferred":[
        "Kabala"
    ],
    "name:ukr_x_preferred":[
        "\u041a\u0430\u0431\u0430\u043b\u0430"
    ],
    "wof:name":"Kabala",
    "wof:placetype":"locality"
},
  "geometry": {"coordinates":[14.42633,-1.67131],"type":"Point"}
}