{
  "type": "Feature",
  "properties": {
    "gn:admin1_code":"05",
    "gn:asciiname":"Moussamo Niambi",
    "gn:country_code":"GA",
    "gn:dem":79,
    "gn:feature_class":"P",
    "gn:feature_code":"PPL",
    "gn:name":"Moussamo Niambi",
    "gn:population":0,
    "gn:timezone":"Africa/Libreville",
    "iso:country":"GA",
    "wof:name":"Moussamo Niambi",
    "wof:placetype":"locality"
},
  "geometry": {"coordinates":[10.07992,-2.78477],"type":"Point"}
}