{
  "type": "Feature",
  "properties": {
    "gn:admin1_code":"07",
    "gn:asciiname":"Boumabango",
    "gn:country_code":"GA",
    "gn:dem":288,
    "gn:feature_class":"P",
    "gn:feature_code":"PPL",
    "gn:name":"Boumabango",
    "gn:population":0,
    "gn:timezone":"Africa/Libreville",
    "iso:country":"GA",
    "wof:name":"Boumabango",
    "wof:placetype":"locality"
},
  "geometry": {"coordinates":[13.03177,-0.91813],"type":"Point"}
}