{
  "type": "Feature",
  "properties": {
    "gn:admin1_code":"02",
    "gn:asciiname":"Mboma",
    "gn:country_code":"GA",
    "gn:dem":421,
    "gn:feature_class":"P",
    "gn:feature_code":"PPL",
    "gn:name":"Mboma",
    "gn:population":0,
    "gn:timezone":"Africa/Libreville",
    "iso:country":"GA",
    "wof:name":"Mboma",
    "wof:placetype":"locality"
},
  "geometry": {"coordinates":[14.08692,-1.78752],"type":"Point"}
}