{
  "type": "Feature",
  "properties": {
    "gn:admin1_code":"05",
    "gn:asciiname":"Gobini",
    "gn:country_code":"GA",
    "gn:dem":15,
    "gn:feature_class":"P",
    "gn:feature_code":"PPL",
    "gn:name":"Gobini",
    "gn:population":0,
    "gn:timezone":"Africa/Libreville",
    "iso:country":"GA",
    "wof:name":"Gobini",
    "wof:placetype":"locality"
},
  "geometry": {"coordinates":[10.45,-3.03333],"type":"Point"}
}