{
  "type": "Feature",
  "properties": {
    "gn:admin1_code":"04",
    "gn:asciiname":"Paga-Dianzi",
    "gn:country_code":"GA",
    "gn:dem":100,
    "gn:feature_class":"P",
    "gn:feature_code":"PPL",
    "gn:name":"Paga-Dianzi",
    "gn:population":0,
    "gn:timezone":"Africa/Libreville",
    "iso:country":"GA",
    "wof:name":"Paga-Dianzi",
    "wof:placetype":"locality"
},
  "geometry": {"coordinates":[10.6177,-1.31353],"type":"Point"}
}