{
  "type": "Feature",
  "properties": {
    "gn:admin1_code":"03",
    "gn:asciiname":"Ngomo",
    "gn:country_code":"GA",
    "gn:dem":17,
    "gn:feature_class":"P",
    "gn:feature_code":"PPL",
    "gn:name":"Ngomo",
    "gn:population":0,
    "gn:timezone":"Africa/Libreville",
    "iso:country":"GA",
    "wof:name":"Ngomo",
    "wof:placetype":"locality"
},
  "geometry": {"coordinates":[9.98192,-0.83926],"type":"Point"}
}