{
  "type": "Feature",
  "properties": {
    "gn:admin1_code":"06",
    "gn:asciiname":"Nzela",
    "gn:country_code":"GA",
    "gn:dem":520,
    "gn:feature_class":"P",
    "gn:feature_code":"PPL",
    "gn:name":"Nz\u00e9la",
    "gn:population":0,
    "gn:timezone":"Africa/Libreville",
    "iso:country":"GA",
    "wof:name":"Nzela",
    "wof:placetype":"locality"
},
  "geometry": {"coordinates":[13.93333,0.76667],"type":"Point"}
}