{
  "type": "Feature",
  "properties": {
    "gn:admin1_code":"03",
    "gn:asciiname":"Benvelle",
    "gn:country_code":"GA",
    "gn:dem":25,
    "gn:feature_class":"P",
    "gn:feature_code":"PPL",
    "gn:name":"Benvelle",
    "gn:population":0,
    "gn:timezone":"Africa/Libreville",
    "iso:country":"GA",
    "wof:name":"Benvelle",
    "wof:placetype":"locality"
},
  "geometry": {"coordinates":[10.78333,-0.15],"type":"Point"}
}