{
  "type": "Feature",
  "properties": {
    "gn:admin1_code":"04",
    "gn:asciiname":"Levinda",
    "gn:country_code":"GA",
    "gn:dem":762,
    "gn:feature_class":"P",
    "gn:feature_code":"PPL",
    "gn:name":"Levinda",
    "gn:population":0,
    "gn:timezone":"Africa/Libreville",
    "iso:country":"GA",
    "name:und_x_variant":[
        "Dyenz\u00e9",
        "Dyenza",
        "Levinda"
    ],
    "wof:name":"Levinda",
    "wof:placetype":"locality"
},
  "geometry": {"coordinates":[12.18824,-1.98327],"type":"Point"}
}