{
  "type": "Feature",
  "properties": {
    "gn:admin1_code":"02",
    "gn:asciiname":"Ngwoni",
    "gn:country_code":"GA",
    "gn:dem":468,
    "gn:feature_class":"P",
    "gn:feature_code":"PPL",
    "gn:name":"Ngwoni",
    "gn:population":0,
    "gn:timezone":"Africa/Libreville",
    "iso:country":"GA",
    "wof:name":"Ngwoni",
    "wof:placetype":"locality"
},
  "geometry": {"coordinates":[13.79245,-1.50021],"type":"Point"}
}