{
  "type": "Feature",
  "properties": {
    "gn:admin1_code":"04",
    "gn:asciiname":"Mingola",
    "gn:country_code":"GA",
    "gn:dem":329,
    "gn:feature_class":"P",
    "gn:feature_code":"PPL",
    "gn:name":"Mingola",
    "gn:population":0,
    "gn:timezone":"Africa/Libreville",
    "iso:country":"GA",
    "wof:name":"Mingola",
    "wof:placetype":"locality"
},
  "geometry": {"coordinates":[10.91975,-2.1304],"type":"Point"}
}