{
  "type": "Feature",
  "properties": {
    "gn:admin1_code":"09",
    "gn:asciiname":"Woumou",
    "gn:country_code":"GA",
    "gn:dem":624,
    "gn:feature_class":"P",
    "gn:feature_code":"PPL",
    "gn:name":"Woumou",
    "gn:population":0,
    "gn:timezone":"Africa/Libreville",
    "iso:country":"GA",
    "wof:name":"Woumou",
    "wof:placetype":"locality"
},
  "geometry": {"coordinates":[11.65,2.16667],"type":"Point"}
}