{
  "type": "Feature",
  "properties": {
    "gn:admin1_code":"02",
    "gn:asciiname":"Kabaga II",
    "gn:country_code":"GA",
    "gn:dem":601,
    "gn:feature_class":"P",
    "gn:feature_code":"PPL",
    "gn:name":"Kabaga II",
    "gn:population":0,
    "gn:timezone":"Africa/Libreville",
    "iso:country":"GA",
    "wof:name":"Kabaga II",
    "wof:placetype":"locality"
},
  "geometry": {"coordinates":[13.91667,-1.38333],"type":"Point"}
}