{
  "type": "Feature",
  "properties": {
    "gn:admin1_code":"02",
    "gn:asciiname":"Bandegue",
    "gn:country_code":"GA",
    "gn:dem":346,
    "gn:feature_class":"P",
    "gn:feature_code":"PPL",
    "gn:name":"Band\u00e9gu\u00e9",
    "gn:population":0,
    "gn:timezone":"Africa/Libreville",
    "iso:country":"GA",
    "wof:name":"Bandegue",
    "wof:placetype":"locality"
},
  "geometry": {"coordinates":[13.55,-1.08333],"type":"Point"}
}