{
  "type": "Feature",
  "properties": {
    "gn:admin1_code":"04",
    "gn:asciiname":"Koumbanou",
    "gn:country_code":"GA",
    "gn:dem":261,
    "gn:feature_class":"P",
    "gn:feature_code":"PPL",
    "gn:name":"Koumbanou",
    "gn:population":0,
    "gn:timezone":"Africa/Libreville",
    "iso:country":"GA",
    "wof:name":"Koumbanou",
    "wof:placetype":"locality"
},
  "geometry": {"coordinates":[10.64008,-2.11072],"type":"Point"}
}