{
  "type": "Feature",
  "properties": {
    "gn:admin1_code":"06",
    "gn:asciiname":"Ovan",
    "gn:country_code":"GA",
    "gn:dem":515,
    "gn:feature_class":"P",
    "gn:feature_code":"PPL",
    "gn:name":"Ovan",
    "gn:population":0,
    "gn:timezone":"Africa/Libreville",
    "iso:country":"GA",
    "name:bos_x_preferred":[
        "Ovan"
    ],
    "name:hrv_x_preferred":[
        "Ovan"
    ],
    "name:srp_x_preferred":[
        "\u041e\u0432\u0430\u043d"
    ],
    "wof:name":"Ovan",
    "wof:placetype":"locality"
},
  "geometry": {"coordinates":[12.95,0.85],"type":"Point"}
}