{
  "type": "Feature",
  "properties": {
    "gn:admin1_code":"05",
    "gn:asciiname":"Yandji",
    "gn:country_code":"GA",
    "gn:dem":312,
    "gn:feature_class":"P",
    "gn:feature_code":"PPL",
    "gn:name":"Yandji",
    "gn:population":0,
    "gn:timezone":"Africa/Libreville",
    "iso:country":"GA",
    "wof:name":"Yandji",
    "wof:placetype":"locality"
},
  "geometry": {"coordinates":[11.23035,-3.08925],"type":"Point"}
}