{
  "type": "Feature",
  "properties": {
    "gn:admin1_code":"07",
    "gn:asciiname":"Doumatsengue",
    "gn:country_code":"GA",
    "gn:dem":358,
    "gn:feature_class":"P",
    "gn:feature_code":"PPL",
    "gn:name":"Doumatsengu\u00e9",
    "gn:population":0,
    "gn:timezone":"Africa/Libreville",
    "iso:country":"GA",
    "wof:name":"Doumatsengue",
    "wof:placetype":"locality"
},
  "geometry": {"coordinates":[12.41667,-1.21667],"type":"Point"}
}