{
  "type": "Feature",
  "properties": {
    "gn:admin1_code":"07",
    "gn:asciiname":"Mikengue",
    "gn:country_code":"GA",
    "gn:dem":252,
    "gn:feature_class":"P",
    "gn:feature_code":"PPL",
    "gn:name":"Mikengu\u00e9",
    "gn:population":0,
    "gn:timezone":"Africa/Libreville",
    "iso:country":"GA",
    "wof:name":"Mikengue",
    "wof:placetype":"locality"
},
  "geometry": {"coordinates":[12.89411,-0.82803],"type":"Point"}
}