{
  "type": "Feature",
  "properties": {
    "gn:admin1_code":"01",
    "gn:asciiname":"Nzing Meyong",
    "gn:country_code":"GA",
    "gn:dem":21,
    "gn:feature_class":"P",
    "gn:feature_code":"PPL",
    "gn:name":"Nzing Meyong",
    "gn:population":0,
    "gn:timezone":"Africa/Libreville",
    "iso:country":"GA",
    "name:und_x_variant":[
        "Nzeng-Meyong"
    ],
    "wof:name":"Nzing Meyong",
    "wof:placetype":"locality"
},
  "geometry": {"coordinates":[10.0463,0.2867],"type":"Point"}
}