{
  "type": "Feature",
  "properties": {
    "gn:admin1_code":"09",
    "gn:asciiname":"Tomassi",
    "gn:country_code":"GA",
    "gn:dem":555,
    "gn:feature_class":"P",
    "gn:feature_code":"PPL",
    "gn:name":"Tomassi",
    "gn:population":0,
    "gn:timezone":"Africa/Libreville",
    "iso:country":"GA",
    "name:deu_x_preferred":[
        "Tomassi"
    ],
    "name:ita_x_preferred":[
        "Tomassi"
    ],
    "name:rus_x_preferred":[
        "\u0422\u043e\u043c\u0430\u0441\u0441\u0438"
    ],
    "name:spa_x_preferred":[
        "Tomassi"
    ],
    "wof:name":"Tomassi",
    "wof:placetype":"locality"
},
  "geometry": {"coordinates":[11.45316,1.0497],"type":"Point"}
}