{
  "type": "Feature",
  "properties": {
    "gn:admin1_code":"06",
    "gn:asciiname":"Allar Mourkevock",
    "gn:country_code":"GA",
    "gn:dem":502,
    "gn:feature_class":"P",
    "gn:feature_code":"PPL",
    "gn:name":"Allar Mourkevock",
    "gn:population":0,
    "gn:timezone":"Africa/Libreville",
    "iso:country":"GA",
    "wof:name":"Allar Mourkevock",
    "wof:placetype":"locality"
},
  "geometry": {"coordinates":[12.11667,0.35],"type":"Point"}
}