{
  "type": "Feature",
  "properties": {
    "gn:admin1_code":"09",
    "gn:asciiname":"Tarangone",
    "gn:country_code":"GA",
    "gn:dem":399,
    "gn:feature_class":"P",
    "gn:feature_code":"PPL",
    "gn:name":"Tarangone",
    "gn:population":0,
    "gn:timezone":"Africa/Libreville",
    "iso:country":"GA",
    "wof:name":"Tarangone",
    "wof:placetype":"locality"
},
  "geometry": {"coordinates":[11.56667,0.43333],"type":"Point"}
}