{
  "type": "Feature",
  "properties": {
    "gn:admin1_code":"02",
    "gn:asciiname":"Mingondza",
    "gn:country_code":"GA",
    "gn:dem":324,
    "gn:feature_class":"P",
    "gn:feature_code":"PPL",
    "gn:name":"Mingondza",
    "gn:population":0,
    "gn:timezone":"Africa/Libreville",
    "iso:country":"GA",
    "wof:name":"Mingondza",
    "wof:placetype":"locality"
},
  "geometry": {"coordinates":[13.42189,-0.72577],"type":"Point"}
}