{
  "type": "Feature",
  "properties": {
    "gn:admin1_code":"09",
    "gn:asciiname":"Minkokmisseng",
    "gn:country_code":"GA",
    "gn:dem":598,
    "gn:feature_class":"P",
    "gn:feature_code":"PPL",
    "gn:name":"Minkokmisseng",
    "gn:population":0,
    "gn:timezone":"Africa/Libreville",
    "iso:country":"GA",
    "wof:name":"Minkokmisseng",
    "wof:placetype":"locality"
},
  "geometry": {"coordinates":[11.73333,2.23333],"type":"Point"}
}