{
  "type": "Feature",
  "properties": {
    "gn:admin1_code":"06",
    "gn:asciiname":"Edabour",
    "gn:country_code":"GA",
    "gn:dem":487,
    "gn:feature_class":"P",
    "gn:feature_code":"PPL",
    "gn:name":"Edabour",
    "gn:population":0,
    "gn:timezone":"Africa/Libreville",
    "iso:country":"GA",
    "wof:name":"Edabour",
    "wof:placetype":"locality"
},
  "geometry": {"coordinates":[11.91516,0.20941],"type":"Point"}
}