{
  "type": "Feature",
  "properties": {
    "gn:admin1_code":"03",
    "gn:asciiname":"Makokoue",
    "gn:country_code":"GA",
    "gn:dem":38,
    "gn:feature_class":"P",
    "gn:feature_code":"PPL",
    "gn:name":"Makokou\u00e9",
    "gn:population":0,
    "gn:timezone":"Africa/Libreville",
    "iso:country":"GA",
    "wof:name":"Makokoue",
    "wof:placetype":"locality"
},
  "geometry": {"coordinates":[10.4055,-0.47721],"type":"Point"}
}