{
  "type": "Feature",
  "properties": {
    "gn:admin1_code":"04",
    "gn:asciiname":"Nganda",
    "gn:country_code":"GA",
    "gn:dem":360,
    "gn:feature_class":"P",
    "gn:feature_code":"PPL",
    "gn:name":"Nganda",
    "gn:population":0,
    "gn:timezone":"Africa/Libreville",
    "iso:country":"GA",
    "name:deu_x_preferred":[
        "Nganda"
    ],
    "name:fra_x_preferred":[
        "Nganda"
    ],
    "wof:name":"Nganda",
    "wof:placetype":"locality"
},
  "geometry": {"coordinates":[10.79601,-2.04947],"type":"Point"}
}