{
  "type": "Feature",
  "properties": {
    "gn:admin1_code":"09",
    "gn:asciiname":"Zorengone",
    "gn:country_code":"GA",
    "gn:dem":580,
    "gn:feature_class":"P",
    "gn:feature_code":"PPL",
    "gn:name":"Zorengone",
    "gn:population":0,
    "gn:timezone":"Africa/Libreville",
    "iso:country":"GA",
    "wof:name":"Zorengone",
    "wof:placetype":"locality"
},
  "geometry": {"coordinates":[10.41295,0.7796],"type":"Point"}
}