{
  "type": "Feature",
  "properties": {
    "gn:admin1_code":"04",
    "gn:asciiname":"Moukouanga",
    "gn:country_code":"GA",
    "gn:dem":637,
    "gn:feature_class":"P",
    "gn:feature_code":"PPL",
    "gn:name":"Moukouanga",
    "gn:population":0,
    "gn:timezone":"Africa/Libreville",
    "iso:country":"GA",
    "name:und_x_variant":[
        "Moucouagna",
        "Moucwagna",
        "Moukouanga"
    ],
    "wof:name":"Moukouanga",
    "wof:placetype":"locality"
},
  "geometry": {"coordinates":[12.31436,-2.29908],"type":"Point"}
}