{
  "type": "Feature",
  "properties": {
    "gn:admin1_code":"09",
    "gn:asciiname":"Ingong",
    "gn:country_code":"GA",
    "gn:dem":663,
    "gn:feature_class":"P",
    "gn:feature_code":"PPL",
    "gn:name":"Ingong",
    "gn:population":0,
    "gn:timezone":"Africa/Libreville",
    "iso:country":"GA",
    "name:und_x_variant":[
        "Okas",
        "Ingong"
    ],
    "wof:name":"Ingong",
    "wof:placetype":"locality"
},
  "geometry": {"coordinates":[11.38269,1.57483],"type":"Point"}
}