{
  "type": "Feature",
  "properties": {
    "gn:admin1_code":"02",
    "gn:asciiname":"Sibbi",
    "gn:country_code":"GA",
    "gn:dem":530,
    "gn:feature_class":"P",
    "gn:feature_code":"PPL",
    "gn:name":"Sibbi",
    "gn:population":0,
    "gn:timezone":"Africa/Libreville",
    "iso:country":"GA",
    "wof:name":"Sibbi",
    "wof:placetype":"locality"
},
  "geometry": {"coordinates":[13.56667,-1.86667],"type":"Point"}
}