{
  "type": "Feature",
  "properties": {
    "gn:admin1_code":"02",
    "gn:asciiname":"Nkiga",
    "gn:country_code":"GA",
    "gn:dem":657,
    "gn:feature_class":"P",
    "gn:feature_code":"PPL",
    "gn:name":"Nkiga",
    "gn:population":0,
    "gn:timezone":"Africa/Libreville",
    "iso:country":"GA",
    "name:und_x_variant":[
        "Kika",
        "Nkiga"
    ],
    "wof:name":"Nkiga",
    "wof:placetype":"locality"
},
  "geometry": {"coordinates":[14.27015,-1.82693],"type":"Point"}
}