{
  "type": "Feature",
  "properties": {
    "gn:admin1_code":"05",
    "gn:asciiname":"Biello",
    "gn:country_code":"GA",
    "gn:dem":57,
    "gn:feature_class":"P",
    "gn:feature_code":"PPL",
    "gn:name":"Biello",
    "gn:population":0,
    "gn:timezone":"Africa/Libreville",
    "iso:country":"GA",
    "wof:name":"Biello",
    "wof:placetype":"locality"
},
  "geometry": {"coordinates":[11.33864,-3.15668],"type":"Point"}
}