{
  "type": "Feature",
  "properties": {
    "gn:admin1_code":"03",
    "gn:asciiname":"Issinga",
    "gn:country_code":"GA",
    "gn:dem":72,
    "gn:feature_class":"P",
    "gn:feature_code":"PPL",
    "gn:name":"Issinga",
    "gn:population":0,
    "gn:timezone":"Africa/Libreville",
    "iso:country":"GA",
    "wof:name":"Issinga",
    "wof:placetype":"locality"
},
  "geometry": {"coordinates":[10.43761,-0.88901],"type":"Point"}
}