{
  "type": "Feature",
  "properties": {
    "gn:admin1_code":"01",
    "gn:asciiname":"Evoredoule",
    "gn:country_code":"GA",
    "gn:dem":18,
    "gn:feature_class":"P",
    "gn:feature_code":"PPL",
    "gn:name":"Evoredoule",
    "gn:population":0,
    "gn:timezone":"Africa/Libreville",
    "iso:country":"GA",
    "wof:name":"Evoredoule",
    "wof:placetype":"locality"
},
  "geometry": {"coordinates":[10.11667,0.16667],"type":"Point"}
}