{
  "type": "Feature",
  "properties": {
    "gn:admin1_code":"01",
    "gn:asciiname":"Nzamanene",
    "gn:country_code":"GA",
    "gn:dem":48,
    "gn:feature_class":"P",
    "gn:feature_code":"PPL",
    "gn:name":"Nzaman\u00e9n\u00e9",
    "gn:population":0,
    "gn:timezone":"Africa/Libreville",
    "iso:country":"GA",
    "wof:name":"Nzamanene",
    "wof:placetype":"locality"
},
  "geometry": {"coordinates":[10.25,0.28333],"type":"Point"}
}