{
  "type": "Feature",
  "properties": {
    "gn:admin1_code":"09",
    "gn:asciiname":"Nko",
    "gn:country_code":"GA",
    "gn:dem":616,
    "gn:feature_class":"P",
    "gn:feature_code":"PPL",
    "gn:name":"Nko",
    "gn:population":0,
    "gn:timezone":"Africa/Libreville",
    "iso:country":"GA",
    "wof:name":"Nko",
    "wof:placetype":"locality"
},
  "geometry": {"coordinates":[11.65,2.03333],"type":"Point"}
}