{
  "type": "Feature",
  "properties": {
    "gn:admin1_code":"09",
    "gn:asciiname":"Andom I",
    "gn:country_code":"GA",
    "gn:dem":597,
    "gn:feature_class":"P",
    "gn:feature_code":"PPL",
    "gn:name":"Andom I",
    "gn:population":0,
    "gn:timezone":"Africa/Libreville",
    "iso:country":"GA",
    "wof:name":"Andom I",
    "wof:placetype":"locality"
},
  "geometry": {"coordinates":[12.11667,2.25],"type":"Point"}
}