{
  "type": "Feature",
  "properties": {
    "gn:admin1_code":"03",
    "gn:asciiname":"Nendja",
    "gn:country_code":"GA",
    "gn:dem":10,
    "gn:feature_class":"P",
    "gn:feature_code":"PPL",
    "gn:name":"Nendja",
    "gn:population":0,
    "gn:timezone":"Africa/Libreville",
    "iso:country":"GA",
    "wof:name":"Nendja",
    "wof:placetype":"locality"
},
  "geometry": {"coordinates":[9.93333,-0.58333],"type":"Point"}
}