{
  "type": "Feature",
  "properties": {
    "gn:admin1_code":"03",
    "gn:asciiname":"Mvoulie",
    "gn:country_code":"GA",
    "gn:dem":104,
    "gn:feature_class":"P",
    "gn:feature_code":"PPL",
    "gn:name":"Mvouli\u00e9",
    "gn:population":0,
    "gn:timezone":"Africa/Libreville",
    "iso:country":"GA",
    "wof:name":"Mvoulie",
    "wof:placetype":"locality"
},
  "geometry": {"coordinates":[10.63333,-0.23333],"type":"Point"}
}