{
  "type": "Feature",
  "properties": {
    "gn:admin1_code":"06",
    "gn:asciiname":"Ibinga",
    "gn:country_code":"GA",
    "gn:dem":515,
    "gn:feature_class":"P",
    "gn:feature_code":"PPL",
    "gn:name":"Ibinga",
    "gn:population":0,
    "gn:timezone":"Africa/Libreville",
    "iso:country":"GA",
    "wof:name":"Ibinga",
    "wof:placetype":"locality"
},
  "geometry": {"coordinates":[13.05034,0.68568],"type":"Point"}
}