{
  "type": "Feature",
  "properties": {
    "gn:admin1_code":"06",
    "gn:asciiname":"Atsombial",
    "gn:country_code":"GA",
    "gn:dem":190,
    "gn:feature_class":"P",
    "gn:feature_code":"PPL",
    "gn:name":"Atsombial",
    "gn:population":0,
    "gn:timezone":"Africa/Libreville",
    "iso:country":"GA",
    "wof:name":"Atsombial",
    "wof:placetype":"locality"
},
  "geometry": {"coordinates":[11.95411,-0.10375],"type":"Point"}
}