{
  "type": "Feature",
  "properties": {
    "gn:admin1_code":"04",
    "gn:asciiname":"Minganga",
    "gn:country_code":"GA",
    "gn:dem":167,
    "gn:feature_class":"P",
    "gn:feature_code":"PPL",
    "gn:name":"Minganga",
    "gn:population":0,
    "gn:timezone":"Africa/Libreville",
    "iso:country":"GA",
    "wof:name":"Minganga",
    "wof:placetype":"locality"
},
  "geometry": {"coordinates":[11.30583,-2.51798],"type":"Point"}
}