{
  "type": "Feature",
  "properties": {
    "gn:admin1_code":"03",
    "gn:asciiname":"Ebel",
    "gn:country_code":"GA",
    "gn:dem":296,
    "gn:feature_class":"P",
    "gn:feature_code":"PPL",
    "gn:name":"Eb\u00e9l",
    "gn:population":0,
    "gn:timezone":"Africa/Libreville",
    "iso:country":"GA",
    "name:und_x_variant":[
        "El\u00e9b\u00e9",
        "Eb\u00e9l\u00e9",
        "Ebel",
        "Eb\u00e9l"
    ],
    "wof:name":"Ebel",
    "wof:placetype":"locality"
},
  "geometry": {"coordinates":[11.10553,0.12051],"type":"Point"}
}