{
  "type": "Feature",
  "properties": {
    "gn:admin1_code":"04",
    "gn:asciiname":"Dissengui",
    "gn:country_code":"GA",
    "gn:dem":297,
    "gn:feature_class":"P",
    "gn:feature_code":"PPL",
    "gn:name":"Dissengui",
    "gn:population":0,
    "gn:timezone":"Africa/Libreville",
    "iso:country":"GA",
    "wof:name":"Dissengui",
    "wof:placetype":"locality"
},
  "geometry": {"coordinates":[10.83333,-1.98333],"type":"Point"}
}