{
  "type": "Feature",
  "properties": {
    "gn:admin1_code":"01",
    "gn:asciiname":"Ayeme",
    "gn:country_code":"GA",
    "gn:dem":24,
    "gn:feature_class":"P",
    "gn:feature_code":"PPL",
    "gn:name":"Ay\u00e9m\u00e9",
    "gn:population":0,
    "gn:timezone":"Africa/Libreville",
    "iso:country":"GA",
    "wof:name":"Ayeme",
    "wof:placetype":"locality"
},
  "geometry": {"coordinates":[10.28333,0.03333],"type":"Point"}
}