{
  "type": "Feature",
  "properties": {
    "gn:admin1_code":"04",
    "gn:asciiname":"Idemba",
    "gn:country_code":"GA",
    "gn:dem":103,
    "gn:feature_class":"P",
    "gn:feature_code":"PPL",
    "gn:name":"Idemba",
    "gn:population":0,
    "gn:timezone":"Africa/Libreville",
    "iso:country":"GA",
    "wof:name":"Idemba",
    "wof:placetype":"locality"
},
  "geometry": {"coordinates":[10.92337,-1.86962],"type":"Point"}
}