{
  "type": "Feature",
  "properties": {
    "gn:admin1_code":"04",
    "gn:asciiname":"Divelo",
    "gn:country_code":"GA",
    "gn:dem":802,
    "gn:feature_class":"P",
    "gn:feature_code":"PPL",
    "gn:name":"Div\u00e9lo",
    "gn:population":0,
    "gn:timezone":"Africa/Libreville",
    "iso:country":"GA",
    "wof:name":"Divelo",
    "wof:placetype":"locality"
},
  "geometry": {"coordinates":[11.81667,-1.65],"type":"Point"}
}