{
  "type": "Feature",
  "properties": {
    "gn:admin1_code":"01",
    "gn:asciiname":"Mafou",
    "gn:country_code":"GA",
    "gn:dem":14,
    "gn:feature_class":"P",
    "gn:feature_code":"PPL",
    "gn:name":"Mafou",
    "gn:population":0,
    "gn:timezone":"Africa/Libreville",
    "iso:country":"GA",
    "name:und_x_variant":[
        "Mafa",
        "Mafu",
        "Mafou"
    ],
    "wof:name":"Mafou",
    "wof:placetype":"locality"
},
  "geometry": {"coordinates":[10.01202,0.19037],"type":"Point"}
}