{
  "type": "Feature",
  "properties": {
    "gn:admin1_code":"03",
    "gn:asciiname":"Akountam",
    "gn:country_code":"GA",
    "gn:dem":23,
    "gn:feature_class":"P",
    "gn:feature_code":"PPL",
    "gn:name":"Akountam",
    "gn:population":0,
    "gn:timezone":"Africa/Libreville",
    "iso:country":"GA",
    "wof:name":"Akountam",
    "wof:placetype":"locality"
},
  "geometry": {"coordinates":[10.04737,-0.93843],"type":"Point"}
}