{
  "type": "Feature",
  "properties": {
    "gn:admin1_code":"09",
    "gn:asciiname":"Abong-Miang II",
    "gn:country_code":"GA",
    "gn:dem":546,
    "gn:feature_class":"P",
    "gn:feature_code":"PPL",
    "gn:name":"Abong-Miang II",
    "gn:population":0,
    "gn:timezone":"Africa/Libreville",
    "iso:country":"GA",
    "wof:name":"Abong-Miang II",
    "wof:placetype":"locality"
},
  "geometry": {"coordinates":[11.56667,0.88333],"type":"Point"}
}