{
  "type": "Feature",
  "properties": {
    "gn:admin1_code":"02",
    "gn:asciiname":"Massengo III",
    "gn:country_code":"GA",
    "gn:dem":383,
    "gn:feature_class":"P",
    "gn:feature_code":"PPL",
    "gn:name":"Massengo III",
    "gn:population":0,
    "gn:timezone":"Africa/Libreville",
    "iso:country":"GA",
    "wof:name":"Massengo III",
    "wof:placetype":"locality"
},
  "geometry": {"coordinates":[13.15,-1.41667],"type":"Point"}
}