{
  "type": "Feature",
  "properties": {
    "gn:admin1_code":"07",
    "gn:asciiname":"Bikouala",
    "gn:country_code":"GA",
    "gn:dem":299,
    "gn:feature_class":"P",
    "gn:feature_code":"PPL",
    "gn:name":"Bikouala",
    "gn:population":0,
    "gn:timezone":"Africa/Libreville",
    "iso:country":"GA",
    "wof:name":"Bikouala",
    "wof:placetype":"locality"
},
  "geometry": {"coordinates":[12.40186,-1.10004],"type":"Point"}
}