{
  "type": "Feature",
  "properties": {
    "gn:admin1_code":"08",
    "gn:asciiname":"Mboumba",
    "gn:country_code":"GA",
    "gn:dem":12,
    "gn:feature_class":"P",
    "gn:feature_code":"PPL",
    "gn:name":"Mboumba",
    "gn:population":0,
    "gn:timezone":"Africa/Libreville",
    "iso:country":"GA",
    "wof:name":"Mboumba",
    "wof:placetype":"locality"
},
  "geometry": {"coordinates":[9.61468,-0.90279],"type":"Point"}
}