{
  "type": "Feature",
  "properties": {
    "gn:admin1_code":"08",
    "gn:asciiname":"Saint-Thomas",
    "gn:country_code":"GA",
    "gn:dem":57,
    "gn:feature_class":"P",
    "gn:feature_code":"PPL",
    "gn:name":"Saint-Thomas",
    "gn:population":0,
    "gn:timezone":"Africa/Libreville",
    "iso:country":"GA",
    "wof:name":"Saint-Thomas",
    "wof:placetype":"locality"
},
  "geometry": {"coordinates":[10.1949,-2.15342],"type":"Point"}
}