{
  "type": "Feature",
  "properties": {
    "gn:admin1_code":"09",
    "gn:asciiname":"Biyen",
    "gn:country_code":"GA",
    "gn:dem":620,
    "gn:feature_class":"P",
    "gn:feature_code":"PPL",
    "gn:name":"Biyen",
    "gn:population":0,
    "gn:timezone":"Africa/Libreville",
    "iso:country":"GA",
    "wof:name":"Biyen",
    "wof:placetype":"locality"
},
  "geometry": {"coordinates":[11.64232,1.86735],"type":"Point"}
}