{
  "type": "Feature",
  "properties": {
    "gn:admin1_code":"05",
    "gn:asciiname":"Tsegnou Bila",
    "gn:country_code":"GA",
    "gn:dem":319,
    "gn:feature_class":"P",
    "gn:feature_code":"PPL",
    "gn:name":"Tsegnou Bila",
    "gn:population":0,
    "gn:timezone":"Africa/Libreville",
    "iso:country":"GA",
    "wof:name":"Tsegnou Bila",
    "wof:placetype":"locality"
},
  "geometry": {"coordinates":[11.11667,-2.76667],"type":"Point"}
}