{
  "type": "Feature",
  "properties": {
    "gn:admin1_code":"05",
    "gn:asciiname":"Pemo",
    "gn:country_code":"GA",
    "gn:dem":227,
    "gn:feature_class":"P",
    "gn:feature_code":"PPL",
    "gn:name":"Pemo",
    "gn:population":0,
    "gn:timezone":"Africa/Libreville",
    "iso:country":"GA",
    "wof:name":"Pemo",
    "wof:placetype":"locality"
},
  "geometry": {"coordinates":[11.26674,-3.10608],"type":"Point"}
}