{
  "type": "Feature",
  "properties": {
    "gn:admin1_code":"02",
    "gn:asciiname":"Lebaladouba",
    "gn:country_code":"GA",
    "gn:dem":480,
    "gn:feature_class":"P",
    "gn:feature_code":"PPL",
    "gn:name":"L\u00e9baladouba",
    "gn:population":0,
    "gn:timezone":"Africa/Libreville",
    "iso:country":"GA",
    "wof:name":"Lebaladouba",
    "wof:placetype":"locality"
},
  "geometry": {"coordinates":[13.76244,-0.72749],"type":"Point"}
}