{
  "type": "Feature",
  "properties": {
    "gn:admin1_code":"06",
    "gn:asciiname":"Katamoba",
    "gn:country_code":"GA",
    "gn:dem":550,
    "gn:feature_class":"P",
    "gn:feature_code":"PPL",
    "gn:name":"Katamoba",
    "gn:population":0,
    "gn:timezone":"Africa/Libreville",
    "iso:country":"GA",
    "wof:name":"Katamoba",
    "wof:placetype":"locality"
},
  "geometry": {"coordinates":[14.04364,0.90316],"type":"Point"}
}