{
  "type": "Feature",
  "properties": {
    "gn:admin1_code":"04",
    "gn:asciiname":"Kiagui",
    "gn:country_code":"GA",
    "gn:dem":59,
    "gn:feature_class":"P",
    "gn:feature_code":"PPL",
    "gn:name":"Kiagui",
    "gn:population":0,
    "gn:timezone":"Africa/Libreville",
    "iso:country":"GA",
    "wof:name":"Kiagui",
    "wof:placetype":"locality"
},
  "geometry": {"coordinates":[10.15,-1.63333],"type":"Point"}
}