{
  "type": "Feature",
  "properties": {
    "gn:admin1_code":"09",
    "gn:asciiname":"Nsak",
    "gn:country_code":"GA",
    "gn:dem":588,
    "gn:feature_class":"P",
    "gn:feature_code":"PPL",
    "gn:name":"Nsak",
    "gn:population":0,
    "gn:timezone":"Africa/Libreville",
    "iso:country":"GA",
    "wof:name":"Nsak",
    "wof:placetype":"locality"
},
  "geometry": {"coordinates":[12.06667,2.28333],"type":"Point"}
}