{
  "type": "Feature",
  "properties": {
    "gn:admin1_code":"04",
    "gn:asciiname":"Pingou",
    "gn:country_code":"GA",
    "gn:dem":292,
    "gn:feature_class":"P",
    "gn:feature_code":"PPL",
    "gn:name":"Pingou",
    "gn:population":0,
    "gn:timezone":"Africa/Libreville",
    "iso:country":"GA",
    "wof:name":"Pingou",
    "wof:placetype":"locality"
},
  "geometry": {"coordinates":[11.1086,-1.26653],"type":"Point"}
}