{
  "type": "Feature",
  "properties": {
    "gn:admin1_code":"01",
    "gn:asciiname":"Masse",
    "gn:country_code":"GA",
    "gn:dem":45,
    "gn:feature_class":"P",
    "gn:feature_code":"PPL",
    "gn:name":"Mass\u00e9",
    "gn:population":0,
    "gn:timezone":"Africa/Libreville",
    "iso:country":"GA",
    "name:ceb_x_preferred":[
        "Masse"
    ],
    "name:dan_x_preferred":[
        "Masse"
    ],
    "name:deu_x_preferred":[
        "Masse"
    ],
    "name:epo_x_preferred":[
        "Maso"
    ],
    "name:fin_x_preferred":[
        "Masse"
    ],
    "name:fra_x_preferred":[
        "Masse"
    ],
    "name:nds_x_preferred":[
        "Masse"
    ],
    "name:swe_x_preferred":[
        "Masse"
    ],
    "wof:name":"Masse",
    "wof:placetype":"locality"
},
  "geometry": {"coordinates":[9.81667,0.93333],"type":"Point"}
}