{
  "type": "Feature",
  "properties": {
    "gn:admin1_code":"06",
    "gn:asciiname":"Etakaniabe",
    "gn:country_code":"GA",
    "gn:dem":515,
    "gn:feature_class":"P",
    "gn:feature_code":"PPL",
    "gn:name":"Etakaniab\u00e9",
    "gn:population":0,
    "gn:timezone":"Africa/Libreville",
    "iso:country":"GA",
    "wof:name":"Etakaniabe",
    "wof:placetype":"locality"
},
  "geometry": {"coordinates":[12.95592,0.53397],"type":"Point"}
}