{
  "type": "Feature",
  "properties": {
    "gn:admin1_code":"04",
    "gn:asciiname":"Boutombi",
    "gn:country_code":"GA",
    "gn:dem":637,
    "gn:feature_class":"P",
    "gn:feature_code":"PPL",
    "gn:name":"Boutombi",
    "gn:population":0,
    "gn:timezone":"Africa/Libreville",
    "iso:country":"GA",
    "name:und_x_variant":[
        "Boutomoi",
        "Boutombi"
    ],
    "wof:name":"Boutombi",
    "wof:placetype":"locality"
},
  "geometry": {"coordinates":[11.96384,-1.44735],"type":"Point"}
}