{
  "type": "Feature",
  "properties": {
    "gn:admin1_code":"06",
    "gn:asciiname":"Cocomacala",
    "gn:country_code":"GA",
    "gn:dem":547,
    "gn:feature_class":"P",
    "gn:feature_code":"PPL",
    "gn:name":"Cocomacala",
    "gn:population":0,
    "gn:timezone":"Africa/Libreville",
    "iso:country":"GA",
    "wof:name":"Cocomacala",
    "wof:placetype":"locality"
},
  "geometry": {"coordinates":[13.58333,0.11667],"type":"Point"}
}