{
  "type": "Feature",
  "properties": {
    "gn:admin1_code":"07",
    "gn:asciiname":"Ndanda",
    "gn:country_code":"GA",
    "gn:dem":472,
    "gn:feature_class":"P",
    "gn:feature_code":"PPL",
    "gn:name":"Ndanda",
    "gn:population":0,
    "gn:timezone":"Africa/Libreville",
    "iso:country":"GA",
    "wof:name":"Ndanda",
    "wof:placetype":"locality"
},
  "geometry": {"coordinates":[12.11595,-1.24487],"type":"Point"}
}