{
  "type": "Feature",
  "properties": {
    "gn:admin1_code":"04",
    "gn:asciiname":"Ivouta",
    "gn:country_code":"GA",
    "gn:dem":400,
    "gn:feature_class":"P",
    "gn:feature_code":"PPL",
    "gn:name":"Ivouta",
    "gn:population":0,
    "gn:timezone":"Africa/Libreville",
    "iso:country":"GA",
    "wof:name":"Ivouta",
    "wof:placetype":"locality"
},
  "geometry": {"coordinates":[11.48333,-1.96667],"type":"Point"}
}