{
  "type": "Feature",
  "properties": {
    "gn:admin1_code":"09",
    "gn:asciiname":"Oveng-Mendong",
    "gn:country_code":"GA",
    "gn:dem":302,
    "gn:feature_class":"P",
    "gn:feature_code":"PPL",
    "gn:name":"Oveng-Mendong",
    "gn:population":0,
    "gn:timezone":"Africa/Libreville",
    "iso:country":"GA",
    "wof:name":"Oveng-Mendong",
    "wof:placetype":"locality"
},
  "geometry": {"coordinates":[11.46745,0.38575],"type":"Point"}
}