{
  "type": "Feature",
  "properties": {
    "gn:admin1_code":"04",
    "gn:asciiname":"Masoui",
    "gn:country_code":"GA",
    "gn:dem":645,
    "gn:feature_class":"P",
    "gn:feature_code":"PPL",
    "gn:name":"Masoui",
    "gn:population":0,
    "gn:timezone":"Africa/Libreville",
    "iso:country":"GA",
    "name:und_x_variant":[
        "Ma\u00e7wi",
        "Masoui"
    ],
    "wof:name":"Masoui",
    "wof:placetype":"locality"
},
  "geometry": {"coordinates":[11.53821,-1.33415],"type":"Point"}
}