{
  "type": "Feature",
  "properties": {
    "gn:admin1_code":"07",
    "gn:asciiname":"Ngueke",
    "gn:country_code":"GA",
    "gn:dem":409,
    "gn:feature_class":"P",
    "gn:feature_code":"PPL",
    "gn:name":"Nguek\u00e9",
    "gn:population":0,
    "gn:timezone":"Africa/Libreville",
    "iso:country":"GA",
    "wof:name":"Ngueke",
    "wof:placetype":"locality"
},
  "geometry": {"coordinates":[12.76667,-0.25],"type":"Point"}
}