{
  "type": "Feature",
  "properties": {
    "gn:admin1_code":"09",
    "gn:asciiname":"Koualessis",
    "gn:country_code":"GA",
    "gn:dem":681,
    "gn:feature_class":"P",
    "gn:feature_code":"PPL",
    "gn:name":"Koualessis",
    "gn:population":0,
    "gn:timezone":"Africa/Libreville",
    "iso:country":"GA",
    "wof:name":"Koualessis",
    "wof:placetype":"locality"
},
  "geometry": {"coordinates":[11.63814,1.39831],"type":"Point"}
}