{
  "type": "Feature",
  "properties": {
    "gn:admin1_code":"08",
    "gn:asciiname":"Nombo",
    "gn:country_code":"GA",
    "gn:dem":9,
    "gn:feature_class":"P",
    "gn:feature_code":"PPL",
    "gn:name":"Nombo",
    "gn:population":0,
    "gn:timezone":"Africa/Libreville",
    "iso:country":"GA",
    "wof:name":"Nombo",
    "wof:placetype":"locality"
},
  "geometry": {"coordinates":[9.51245,-2.15618],"type":"Point"}
}