{
  "type": "Feature",
  "properties": {
    "gn:admin1_code":"03",
    "gn:asciiname":"Paga",
    "gn:country_code":"GA",
    "gn:dem":59,
    "gn:feature_class":"P",
    "gn:feature_code":"PPL",
    "gn:name":"Paga",
    "gn:population":0,
    "gn:timezone":"Africa/Libreville",
    "iso:country":"GA",
    "wof:name":"Paga",
    "wof:placetype":"locality"
},
  "geometry": {"coordinates":[10.36369,-0.74189],"type":"Point"}
}