{
  "type": "Feature",
  "properties": {
    "gn:admin1_code":"05",
    "gn:asciiname":"Yabala",
    "gn:country_code":"GA",
    "gn:dem":351,
    "gn:feature_class":"P",
    "gn:feature_code":"PPL",
    "gn:name":"Yabala",
    "gn:population":0,
    "gn:timezone":"Africa/Libreville",
    "iso:country":"GA",
    "wof:name":"Yabala",
    "wof:placetype":"locality"
},
  "geometry": {"coordinates":[11.26667,-2.85],"type":"Point"}
}