{
  "type": "Feature",
  "properties": {
    "gn:admin1_code":"03",
    "gn:asciiname":"Oberting",
    "gn:country_code":"GA",
    "gn:dem":20,
    "gn:feature_class":"P",
    "gn:feature_code":"PPL",
    "gn:name":"Oberting",
    "gn:population":0,
    "gn:timezone":"Africa/Libreville",
    "iso:country":"GA",
    "wof:name":"Oberting",
    "wof:placetype":"locality"
},
  "geometry": {"coordinates":[9.73333,-0.63333],"type":"Point"}
}