{
  "type": "Feature",
  "properties": {
    "gn:admin1_code":"07",
    "gn:asciiname":"Londo",
    "gn:country_code":"GA",
    "gn:dem":555,
    "gn:feature_class":"P",
    "gn:feature_code":"PPL",
    "gn:name":"Londo",
    "gn:population":0,
    "gn:timezone":"Africa/Libreville",
    "iso:country":"GA",
    "name:ceb_x_preferred":[
        "Londo"
    ],
    "name:fra_x_preferred":[
        "Londo"
    ],
    "name:swe_x_preferred":[
        "Londo"
    ],
    "wof:name":"Londo",
    "wof:placetype":"locality"
},
  "geometry": {"coordinates":[12.80724,-0.93939],"type":"Point"}
}