{
  "type": "Feature",
  "properties": {
    "gn:admin1_code":"05",
    "gn:asciiname":"Maoumba",
    "gn:country_code":"GA",
    "gn:dem":194,
    "gn:feature_class":"P",
    "gn:feature_code":"PPL",
    "gn:name":"Maoumba",
    "gn:population":0,
    "gn:timezone":"Africa/Libreville",
    "iso:country":"GA",
    "wof:name":"Maoumba",
    "wof:placetype":"locality"
},
  "geometry": {"coordinates":[10.8455,-2.56045],"type":"Point"}
}