{
  "type": "Feature",
  "properties": {
    "gn:admin1_code":"09",
    "gn:asciiname":"Sam",
    "gn:country_code":"GA",
    "gn:dem":549,
    "gn:feature_class":"P",
    "gn:feature_code":"PPL",
    "gn:name":"Sam",
    "gn:population":0,
    "gn:timezone":"Africa/Libreville",
    "iso:country":"GA",
    "name:ara_x_preferred":[
        "\u0633\u0627\u0645"
    ],
    "name:bar_x_preferred":[
        "Sam"
    ],
    "name:ceb_x_preferred":[
        "Sam"
    ],
    "name:ces_x_preferred":[
        "Sam"
    ],
    "name:deu_x_preferred":[
        "Sam"
    ],
    "name:fas_x_preferred":[
        "\u0633\u0627\u0645"
    ],
    "name:fra_x_preferred":[
        "Sam"
    ],
    "name:kor_x_preferred":[
        "\uc0d8"
    ],
    "name:nld_x_preferred":[
        "Sam"
    ],
    "name:pol_x_preferred":[
        "Sam"
    ],
    "name:por_x_preferred":[
        "Sam"
    ],
    "name:slv_x_preferred":[
        "Sam"
    ],
    "name:spa_x_preferred":[
        "Sam"
    ],
    "name:swe_x_preferred":[
        "Sam"
    ],
    "name:zho_x_preferred":[
        "Sam"
    ],
    "wof:name":"Sam",
    "wof:placetype":"locality"
},
  "geometry": {"coordinates":[11.56667,0.86667],"type":"Point"}
}