{
  "type": "Feature",
  "properties": {
    "gn:admin1_code":"04",
    "gn:asciiname":"Boussouka",
    "gn:country_code":"GA",
    "gn:dem":186,
    "gn:feature_class":"P",
    "gn:feature_code":"PPL",
    "gn:name":"Boussouka",
    "gn:population":0,
    "gn:timezone":"Africa/Libreville",
    "iso:country":"GA",
    "wof:name":"Boussouka",
    "wof:placetype":"locality"
},
  "geometry": {"coordinates":[11.08333,-1.23333],"type":"Point"}
}