{
  "type": "Feature",
  "properties": {
    "gn:admin1_code":"05",
    "gn:asciiname":"Makaba Ndilo",
    "gn:country_code":"GA",
    "gn:dem":111,
    "gn:feature_class":"P",
    "gn:feature_code":"PPL",
    "gn:name":"Makaba Ndilo",
    "gn:population":0,
    "gn:timezone":"Africa/Libreville",
    "iso:country":"GA",
    "wof:name":"Makaba Ndilo",
    "wof:placetype":"locality"
},
  "geometry": {"coordinates":[10.81667,-3.06667],"type":"Point"}
}