{
  "type": "Feature",
  "properties": {
    "gn:admin1_code":"09",
    "gn:asciiname":"Mbas",
    "gn:country_code":"GA",
    "gn:dem":590,
    "gn:feature_class":"P",
    "gn:feature_code":"PPL",
    "gn:name":"Mbas",
    "gn:population":0,
    "gn:timezone":"Africa/Libreville",
    "iso:country":"GA",
    "wof:name":"Mbas",
    "wof:placetype":"locality"
},
  "geometry": {"coordinates":[12.08333,2.15],"type":"Point"}
}