{
  "type": "Feature",
  "properties": {
    "gn:admin1_code":"07",
    "gn:asciiname":"Bassegua",
    "gn:country_code":"GA",
    "gn:dem":246,
    "gn:feature_class":"P",
    "gn:feature_code":"PPL",
    "gn:name":"Bassegua",
    "gn:population":0,
    "gn:timezone":"Africa/Libreville",
    "iso:country":"GA",
    "wof:name":"Bassegua",
    "wof:placetype":"locality"
},
  "geometry": {"coordinates":[12.81399,-0.81614],"type":"Point"}
}