{
  "type": "Feature",
  "properties": {
    "gn:admin1_code":"04",
    "gn:asciiname":"Moussamou",
    "gn:country_code":"GA",
    "gn:dem":30,
    "gn:feature_class":"P",
    "gn:feature_code":"PPL",
    "gn:name":"Moussamou",
    "gn:population":0,
    "gn:timezone":"Africa/Libreville",
    "iso:country":"GA",
    "wof:name":"Moussamou",
    "wof:placetype":"locality"
},
  "geometry": {"coordinates":[10.15,-1.56667],"type":"Point"}
}