{
  "type": "Feature",
  "properties": {
    "gn:admin1_code":"08",
    "gn:asciiname":"Manzilo",
    "gn:country_code":"GA",
    "gn:dem":37,
    "gn:feature_class":"P",
    "gn:feature_code":"PPL",
    "gn:name":"Manzilo",
    "gn:population":0,
    "gn:timezone":"Africa/Libreville",
    "iso:country":"GA",
    "wof:name":"Manzilo",
    "wof:placetype":"locality"
},
  "geometry": {"coordinates":[9.85092,-1.79439],"type":"Point"}
}