{
  "type": "Feature",
  "properties": {
    "gn:admin1_code":"01",
    "gn:asciiname":"Ex-case Boyer",
    "gn:country_code":"GA",
    "gn:dem":38,
    "gn:feature_class":"P",
    "gn:feature_code":"PPL",
    "gn:name":"Ex-case Boyer",
    "gn:population":0,
    "gn:timezone":"Africa/Libreville",
    "iso:country":"GA",
    "wof:name":"Ex-case Boyer",
    "wof:placetype":"locality"
},
  "geometry": {"coordinates":[9.61667,-0.15],"type":"Point"}
}