{
  "type": "Feature",
  "properties": {
    "gn:admin1_code":"04",
    "gn:asciiname":"Ouaka",
    "gn:country_code":"GA",
    "gn:dem":384,
    "gn:feature_class":"P",
    "gn:feature_code":"PPL",
    "gn:name":"Ouaka",
    "gn:population":0,
    "gn:timezone":"Africa/Libreville",
    "iso:country":"GA",
    "wof:name":"Ouaka",
    "wof:placetype":"locality"
},
  "geometry": {"coordinates":[11.53333,-1.96667],"type":"Point"}
}