{
  "type": "Feature",
  "properties": {
    "gn:admin1_code":"09",
    "gn:asciiname":"Bemve",
    "gn:country_code":"GA",
    "gn:dem":286,
    "gn:feature_class":"P",
    "gn:feature_code":"PPL",
    "gn:name":"Bemv\u00e9",
    "gn:population":0,
    "gn:timezone":"Africa/Libreville",
    "iso:country":"GA",
    "wof:name":"Bemve",
    "wof:placetype":"locality"
},
  "geometry": {"coordinates":[11.45798,0.35131],"type":"Point"}
}