{
  "type": "Feature",
  "properties": {
    "gn:admin1_code":"09",
    "gn:asciiname":"Ngomessi",
    "gn:country_code":"GA",
    "gn:dem":567,
    "gn:feature_class":"P",
    "gn:feature_code":"PPL",
    "gn:name":"Ngomessi",
    "gn:population":0,
    "gn:timezone":"Africa/Libreville",
    "iso:country":"GA",
    "wof:name":"Ngomessi",
    "wof:placetype":"locality"
},
  "geometry": {"coordinates":[11.64075,1.00114],"type":"Point"}
}