{
  "type": "Feature",
  "properties": {
    "gn:admin1_code":"09",
    "gn:asciiname":"Angale",
    "gn:country_code":"GA",
    "gn:dem":517,
    "gn:feature_class":"P",
    "gn:feature_code":"PPL",
    "gn:name":"Angale",
    "gn:population":0,
    "gn:timezone":"Africa/Libreville",
    "iso:country":"GA",
    "wof:name":"Angale",
    "wof:placetype":"locality"
},
  "geometry": {"coordinates":[11.71667,0.98333],"type":"Point"}
}