{
  "type": "Feature",
  "properties": {
    "gn:admin1_code":"06",
    "gn:asciiname":"Cocofili",
    "gn:country_code":"GA",
    "gn:dem":543,
    "gn:feature_class":"P",
    "gn:feature_code":"PPL",
    "gn:name":"Cocofili",
    "gn:population":0,
    "gn:timezone":"Africa/Libreville",
    "iso:country":"GA",
    "wof:name":"Cocofili",
    "wof:placetype":"locality"
},
  "geometry": {"coordinates":[13.76667,0.95],"type":"Point"}
}