{
  "type": "Feature",
  "properties": {
    "gn:admin1_code":"02",
    "gn:asciiname":"Olina",
    "gn:country_code":"GA",
    "gn:dem":545,
    "gn:feature_class":"P",
    "gn:feature_code":"PPL",
    "gn:name":"Olina",
    "gn:population":0,
    "gn:timezone":"Africa/Libreville",
    "iso:country":"GA",
    "name:ita_x_preferred":[
        "Olina"
    ],
    "name:nld_x_preferred":[
        "Olina"
    ],
    "name:srp_x_preferred":[
        "\u041e\u043b\u0438\u043d\u0430"
    ],
    "wof:name":"Olina",
    "wof:placetype":"locality"
},
  "geometry": {"coordinates":[14.29424,-1.6024],"type":"Point"}
}