{
  "type": "Feature",
  "properties": {
    "gn:admin1_code":"02",
    "gn:asciiname":"Olina",
    "gn:country_code":"GA",
    "gn:dem":545,
    "gn:feature_class":"P",
    "gn:feature_code":"PPL",
    "gn:name":"Olina",
    "gn:population":0,
    "gn:timezone":"Africa/Libreville",
    "iso:country":"GA",
    "wof:name":"Olina",
    "wof:placetype":"locality"
},
  "geometry": {"coordinates":[14.29424,-1.6024],"type":"Point"}
}