{
  "type": "Feature",
  "properties": {
    "gn:admin1_code":"01",
    "gn:asciiname":"Bolendjo",
    "gn:country_code":"GA",
    "gn:dem":29,
    "gn:feature_class":"P",
    "gn:feature_code":"PPL",
    "gn:name":"Bolendjo",
    "gn:population":0,
    "gn:timezone":"Africa/Libreville",
    "iso:country":"GA",
    "wof:name":"Bolendjo",
    "wof:placetype":"locality"
},
  "geometry": {"coordinates":[9.76667,0.18333],"type":"Point"}
}