{
  "type": "Feature",
  "properties": {
    "gn:admin1_code":"02",
    "gn:asciiname":"Ossagui",
    "gn:country_code":"GA",
    "gn:dem":506,
    "gn:feature_class":"P",
    "gn:feature_code":"PPL",
    "gn:name":"Ossagui",
    "gn:population":0,
    "gn:timezone":"Africa/Libreville",
    "iso:country":"GA",
    "wof:name":"Ossagui",
    "wof:placetype":"locality"
},
  "geometry": {"coordinates":[14.18333,-1.76667],"type":"Point"}
}