{
  "type": "Feature",
  "properties": {
    "gn:admin1_code":"04",
    "gn:asciiname":"Migola",
    "gn:country_code":"GA",
    "gn:dem":339,
    "gn:feature_class":"P",
    "gn:feature_code":"PPL",
    "gn:name":"Migola",
    "gn:population":0,
    "gn:timezone":"Africa/Libreville",
    "iso:country":"GA",
    "wof:name":"Migola",
    "wof:placetype":"locality"
},
  "geometry": {"coordinates":[10.84456,-2.15267],"type":"Point"}
}