{
  "type": "Feature",
  "properties": {
    "gn:admin1_code":"06",
    "gn:asciiname":"Mbela",
    "gn:country_code":"GA",
    "gn:dem":557,
    "gn:feature_class":"P",
    "gn:feature_code":"PPL",
    "gn:name":"Mb\u00e9la",
    "gn:population":0,
    "gn:timezone":"Africa/Libreville",
    "iso:country":"GA",
    "wof:name":"Mbela",
    "wof:placetype":"locality"
},
  "geometry": {"coordinates":[13.90229,0.98186],"type":"Point"}
}