{
  "type": "Feature",
  "properties": {
    "gn:admin1_code":"01",
    "gn:asciiname":"Kringer",
    "gn:country_code":"GA",
    "gn:dem":-9999,
    "gn:feature_class":"P",
    "gn:feature_code":"PPL",
    "gn:name":"Kringer",
    "gn:population":0,
    "gn:timezone":"Africa/Libreville",
    "iso:country":"GA",
    "wof:name":"Kringer",
    "wof:placetype":"locality"
},
  "geometry": {"coordinates":[9.41667,0.41667],"type":"Point"}
}