{
  "type": "Feature",
  "properties": {
    "gn:admin1_code":"09",
    "gn:asciiname":"Zogogone",
    "gn:country_code":"GA",
    "gn:dem":659,
    "gn:feature_class":"P",
    "gn:feature_code":"PPL",
    "gn:name":"Zogogone",
    "gn:population":0,
    "gn:timezone":"Africa/Libreville",
    "iso:country":"GA",
    "wof:name":"Zogogone",
    "wof:placetype":"locality"
},
  "geometry": {"coordinates":[11.51448,1.56285],"type":"Point"}
}