{
  "type": "Feature",
  "properties": {
    "gn:admin1_code":"05",
    "gn:asciiname":"Makabana",
    "gn:country_code":"GA",
    "gn:dem":211,
    "gn:feature_class":"P",
    "gn:feature_code":"PPL",
    "gn:name":"Makabana",
    "gn:population":0,
    "gn:timezone":"Africa/Libreville",
    "iso:country":"GA",
    "wof:name":"Makabana",
    "wof:placetype":"locality"
},
  "geometry": {"coordinates":[10.92222,-2.51304],"type":"Point"}
}