{
  "type": "Feature",
  "properties": {
    "gn:admin1_code":"05",
    "gn:asciiname":"Makabana",
    "gn:country_code":"GA",
    "gn:dem":211,
    "gn:feature_class":"P",
    "gn:feature_code":"PPL",
    "gn:name":"Makabana",
    "gn:population":0,
    "gn:timezone":"Africa/Libreville",
    "iso:country":"GA",
    "name:fra_x_preferred":[
        "Makabana"
    ],
    "name:pol_x_preferred":[
        "Makabana"
    ],
    "name:urd_x_preferred":[
        "\u0645\u0627\u06a9\u0627\u0628\u0627\u0646\u0627"
    ],
    "name:zho_x_preferred":[
        "\u99ac\u5361\u5df4\u7d0d"
    ],
    "wof:name":"Makabana",
    "wof:placetype":"locality"
},
  "geometry": {"coordinates":[10.92222,-2.51304],"type":"Point"}
}