{
  "type": "Feature",
  "properties": {
    "gn:admin1_code":"04",
    "gn:asciiname":"Lepepe",
    "gn:country_code":"GA",
    "gn:dem":688,
    "gn:feature_class":"P",
    "gn:feature_code":"PPL",
    "gn:name":"L\u00e9p\u00e9p\u00e9",
    "gn:population":0,
    "gn:timezone":"Africa/Libreville",
    "iso:country":"GA",
    "wof:name":"Lepepe",
    "wof:placetype":"locality"
},
  "geometry": {"coordinates":[12.21353,-2.17713],"type":"Point"}
}