{
  "type": "Feature",
  "properties": {
    "gn:admin1_code":"09",
    "gn:asciiname":"Ebang",
    "gn:country_code":"GA",
    "gn:dem":586,
    "gn:feature_class":"P",
    "gn:feature_code":"PPL",
    "gn:name":"Ebang",
    "gn:population":0,
    "gn:timezone":"Africa/Libreville",
    "iso:country":"GA",
    "name:ceb_x_preferred":[
        "Ebang"
    ],
    "name:deu_x_preferred":[
        "Ebang"
    ],
    "name:fra_x_preferred":[
        "Ebang"
    ],
    "name:swe_x_preferred":[
        "Ebang"
    ],
    "wof:name":"Ebang",
    "wof:placetype":"locality"
},
  "geometry": {"coordinates":[11.41926,2.13637],"type":"Point"}
}