{
  "type": "Feature",
  "properties": {
    "gn:admin1_code":"06",
    "gn:asciiname":"Magnimba",
    "gn:country_code":"GA",
    "gn:dem":538,
    "gn:feature_class":"P",
    "gn:feature_code":"PPL",
    "gn:name":"Magnimba",
    "gn:population":0,
    "gn:timezone":"Africa/Libreville",
    "iso:country":"GA",
    "wof:name":"Magnimba",
    "wof:placetype":"locality"
},
  "geometry": {"coordinates":[11.69169,-0.49139],"type":"Point"}
}