{
  "type": "Feature",
  "properties": {
    "gn:admin1_code":"04",
    "gn:asciiname":"Mayengue",
    "gn:country_code":"GA",
    "gn:dem":561,
    "gn:feature_class":"P",
    "gn:feature_code":"PPL",
    "gn:name":"Mayengu\u00e9",
    "gn:population":0,
    "gn:timezone":"Africa/Libreville",
    "iso:country":"GA",
    "wof:name":"Mayengue",
    "wof:placetype":"locality"
},
  "geometry": {"coordinates":[11.81667,-1.28333],"type":"Point"}
}