{
  "type": "Feature",
  "properties": {
    "gn:admin1_code":"09",
    "gn:asciiname":"Essone",
    "gn:country_code":"GA",
    "gn:dem":502,
    "gn:feature_class":"P",
    "gn:feature_code":"PPL",
    "gn:name":"Esson\u00e9",
    "gn:population":0,
    "gn:timezone":"Africa/Libreville",
    "iso:country":"GA",
    "wof:name":"Essone",
    "wof:placetype":"locality"
},
  "geometry": {"coordinates":[11.23333,0.81667],"type":"Point"}
}