{
  "type": "Feature",
  "properties": {
    "gn:admin1_code":"09",
    "gn:asciiname":"Nkolabona",
    "gn:country_code":"GA",
    "gn:dem":574,
    "gn:feature_class":"P",
    "gn:feature_code":"PPL",
    "gn:name":"Nkolabona",
    "gn:population":0,
    "gn:timezone":"Africa/Libreville",
    "iso:country":"GA",
    "wof:name":"Nkolabona",
    "wof:placetype":"locality"
},
  "geometry": {"coordinates":[11.70477,1.21947],"type":"Point"}
}