{
  "type": "Feature",
  "properties": {
    "gn:admin1_code":"07",
    "gn:asciiname":"Kounadembe",
    "gn:cc2":"GA",
    "gn:country_code":"GA",
    "gn:dem":368,
    "gn:feature_class":"P",
    "gn:feature_code":"PPL",
    "gn:name":"Kounademb\u00e9",
    "gn:population":0,
    "gn:timezone":"Africa/Libreville",
    "iso:country":"GA",
    "name:und_x_variant":[
        "Konanademb\u00e9",
        "Kounademb\u00e9"
    ],
    "wof:name":"Kounadembe",
    "wof:placetype":"locality"
},
  "geometry": {"coordinates":[12.38333,-1.43333],"type":"Point"}
}