{
  "type": "Feature",
  "properties": {
    "gn:admin1_code":"01",
    "gn:asciiname":"Kam",
    "gn:country_code":"GA",
    "gn:dem":536,
    "gn:feature_class":"P",
    "gn:feature_code":"PPL",
    "gn:name":"Kam",
    "gn:population":0,
    "gn:timezone":"Africa/Libreville",
    "iso:country":"GA",
    "wof:name":"Kam",
    "wof:placetype":"locality"
},
  "geometry": {"coordinates":[10.61667,0.41667],"type":"Point"}
}