{
  "type": "Feature",
  "properties": {
    "gn:admin1_code":"09",
    "gn:asciiname":"Bissok II",
    "gn:country_code":"GA",
    "gn:dem":662,
    "gn:feature_class":"P",
    "gn:feature_code":"PPL",
    "gn:name":"Bissok II",
    "gn:population":0,
    "gn:timezone":"Africa/Libreville",
    "iso:country":"GA",
    "wof:name":"Bissok II",
    "wof:placetype":"locality"
},
  "geometry": {"coordinates":[11.55382,1.25877],"type":"Point"}
}