{
  "type": "Feature",
  "properties": {
    "gn:admin1_code":"08",
    "gn:asciiname":"Bango",
    "gn:country_code":"GA",
    "gn:dem":28,
    "gn:feature_class":"P",
    "gn:feature_code":"PPL",
    "gn:name":"Bango",
    "gn:population":0,
    "gn:timezone":"Africa/Libreville",
    "iso:country":"GA",
    "wof:name":"Bango",
    "wof:placetype":"locality"
},
  "geometry": {"coordinates":[9.32149,-1.84921],"type":"Point"}
}