{
  "type": "Feature",
  "properties": {
    "gn:admin1_code":"01",
    "gn:asciiname":"Nouako",
    "gn:country_code":"GA",
    "gn:dem":461,
    "gn:feature_class":"P",
    "gn:feature_code":"PPL",
    "gn:name":"Nouako",
    "gn:population":0,
    "gn:timezone":"Africa/Libreville",
    "iso:country":"GA",
    "wof:name":"Nouako",
    "wof:placetype":"locality"
},
  "geometry": {"coordinates":[10.55,0.35],"type":"Point"}
}