{
  "type": "Feature",
  "properties": {
    "gn:admin1_code":"06",
    "gn:asciiname":"Mintoum",
    "gn:country_code":"GA",
    "gn:dem":498,
    "gn:feature_class":"P",
    "gn:feature_code":"PPL",
    "gn:name":"Mintoum",
    "gn:population":0,
    "gn:timezone":"Africa/Libreville",
    "iso:country":"GA",
    "wof:name":"Mintoum",
    "wof:placetype":"locality"
},
  "geometry": {"coordinates":[12.26828,0.41981],"type":"Point"}
}