{
  "type": "Feature",
  "properties": {
    "gn:admin1_code":"09",
    "gn:asciiname":"Azap",
    "gn:country_code":"GA",
    "gn:dem":562,
    "gn:feature_class":"P",
    "gn:feature_code":"PPL",
    "gn:name":"Azap",
    "gn:population":0,
    "gn:timezone":"Africa/Libreville",
    "iso:country":"GA",
    "name:ara_x_preferred":[
        "\u0639\u0632\u0628"
    ],
    "name:bos_x_preferred":[
        "Azap"
    ],
    "name:cat_x_preferred":[
        "Azab"
    ],
    "name:ell_x_preferred":[
        "\u0391\u03b6\u03ac\u03c0\u03b7\u03c2"
    ],
    "name:fra_x_preferred":[
        "Azab"
    ],
    "name:hrv_x_preferred":[
        "Azap"
    ],
    "name:hun_x_preferred":[
        "Aszab"
    ],
    "name:lit_x_preferred":[
        "Azapai"
    ],
    "name:pol_x_preferred":[
        "Azab"
    ],
    "name:rus_x_preferred":[
        "\u0410\u0437\u0430\u043f\u044b"
    ],
    "name:spa_x_preferred":[
        "Azab"
    ],
    "name:srp_x_preferred":[
        "\u0410\u0437\u0430\u043f\u0438"
    ],
    "name:swe_x_preferred":[
        "Azap"
    ],
    "name:tur_x_preferred":[
        "Azab"
    ],
    "name:ukr_x_preferred":[
        "\u0410\u0437\u0430\u043f\u0438"
    ],
    "wof:name":"Azap",
    "wof:placetype":"locality"
},
  "geometry": {"coordinates":[11.55,0.75],"type":"Point"}
}