{
  "type": "Feature",
  "properties": {
    "gn:admin1_code":"07",
    "gn:asciiname":"Dekabalandji",
    "gn:country_code":"GA",
    "gn:dem":281,
    "gn:feature_class":"P",
    "gn:feature_code":"PPL",
    "gn:name":"Dekabalandji",
    "gn:population":0,
    "gn:timezone":"Africa/Libreville",
    "iso:country":"GA",
    "wof:name":"Dekabalandji",
    "wof:placetype":"locality"
},
  "geometry": {"coordinates":[12.90912,-0.7768],"type":"Point"}
}