{
  "type": "Feature",
  "properties": {
    "gn:admin1_code":"09",
    "gn:asciiname":"Mekok",
    "gn:country_code":"GA",
    "gn:dem":643,
    "gn:feature_class":"P",
    "gn:feature_code":"PPL",
    "gn:name":"Mekok",
    "gn:population":0,
    "gn:timezone":"Africa/Libreville",
    "iso:country":"GA",
    "wof:name":"Mekok",
    "wof:placetype":"locality"
},
  "geometry": {"coordinates":[11.50315,1.80247],"type":"Point"}
}