{
  "type": "Feature",
  "properties": {
    "gn:admin1_code":"05",
    "gn:asciiname":"Moabi",
    "gn:country_code":"GA",
    "gn:dem":302,
    "gn:feature_class":"P",
    "gn:feature_code":"PPL",
    "gn:name":"Moabi",
    "gn:population":0,
    "gn:timezone":"Africa/Libreville",
    "iso:country":"GA",
    "name:fra_x_preferred":[
        "Moabi"
    ],
    "wof:name":"Moabi",
    "wof:placetype":"locality"
},
  "geometry": {"coordinates":[11.00068,-2.42245],"type":"Point"}
}