{
  "type": "Feature",
  "properties": {
    "gn:admin1_code":"03",
    "gn:asciiname":"Amboki",
    "gn:country_code":"GA",
    "gn:dem":31,
    "gn:feature_class":"P",
    "gn:feature_code":"PPL",
    "gn:name":"Amboki",
    "gn:population":0,
    "gn:timezone":"Africa/Libreville",
    "iso:country":"GA",
    "wof:name":"Amboki",
    "wof:placetype":"locality"
},
  "geometry": {"coordinates":[9.98917,-0.83968],"type":"Point"}
}