{
  "type": "Feature",
  "properties": {
    "gn:gn_country":"GA",
    "gn:gn_fcode":"PPL",
    "gn:gn_pop":6200,
    "gn:population":6200,
    "iso:country":"GA",
    "name:dut_x_preferred":[
        "Ndend\u00e9"
    ],
    "name:eng_x_preferred":[
        "Ndend\u00e9"
    ],
    "name:fre_x_preferred":[
        "Ndend\u00e9"
    ],
    "name:ita_x_preferred":[
        "Ndend\u00e9"
    ],
    "name:jpn_x_preferred":[
        "\u30c9\u30f3\u30c7"
    ],
    "name:lit_x_preferred":[
        "Ndend\u0117"
    ],
    "name:pol_x_preferred":[
        "Ndend\u00e9"
    ],
    "name:rus_x_preferred":[
        "\u041d\u0434\u0435\u043d\u0434\u0435"
    ],
    "name:swe_x_preferred":[
        "Ndend\u00e9"
    ],
    "qs_pg:aaroncc":"GA",
    "qs_pg:gn_country":"GA",
    "qs_pg:gn_fcode":"PPL",
    "qs_pg:gn_pop":6200,
    "qs_pg:name":"Ndend\u00e9",
    "qs_pg:photos_9r":0,
    "qs_pg:photos_sr":0,
    "qs_pg:pop_sr":5,
    "qs_pg:qs_pg_placetype":"locality",
    "wof:name":"Ndend\u00e9",
    "wof:placetype":"locality",
    "wof:population":6200
},
  "geometry": {"coordinates":[11.35813,-2.40077],"type":"Point"}
}