{
  "type": "Feature",
  "properties": {
    "gn:admin1_code":"09",
    "gn:asciiname":"Alene",
    "gn:country_code":"GA",
    "gn:dem":612,
    "gn:feature_class":"P",
    "gn:feature_code":"PPL",
    "gn:name":"Al\u00e9n\u00e9",
    "gn:population":0,
    "gn:timezone":"Africa/Libreville",
    "iso:country":"GA",
    "name:nor_x_preferred":[
        "Alene"
    ],
    "wof:name":"Alene",
    "wof:placetype":"locality"
},
  "geometry": {"coordinates":[11.98333,2.08333],"type":"Point"}
}