{
  "type": "Feature",
  "properties": {
    "gn:admin1_code":"05",
    "gn:asciiname":"Mboula",
    "gn:country_code":"GA",
    "gn:dem":165,
    "gn:feature_class":"P",
    "gn:feature_code":"PPL",
    "gn:name":"Mboula",
    "gn:population":0,
    "gn:timezone":"Africa/Libreville",
    "iso:country":"GA",
    "wof:name":"Mboula",
    "wof:placetype":"locality"
},
  "geometry": {"coordinates":[10.62741,-2.69432],"type":"Point"}
}