{
  "type": "Feature",
  "properties": {
    "gn:admin1_code":"05",
    "gn:asciiname":"Malaba",
    "gn:country_code":"GA",
    "gn:dem":358,
    "gn:feature_class":"P",
    "gn:feature_code":"PPL",
    "gn:name":"Malaba",
    "gn:population":0,
    "gn:timezone":"Africa/Libreville",
    "iso:country":"GA",
    "wof:name":"Malaba",
    "wof:placetype":"locality"
},
  "geometry": {"coordinates":[11.06667,-2.33333],"type":"Point"}
}