{
  "type": "Feature",
  "properties": {
    "gn:admin1_code":"04",
    "gn:asciiname":"Massana",
    "gn:country_code":"GA",
    "gn:dem":22,
    "gn:feature_class":"P",
    "gn:feature_code":"PPL",
    "gn:name":"Massana",
    "gn:population":0,
    "gn:timezone":"Africa/Libreville",
    "iso:country":"GA",
    "wof:name":"Massana",
    "wof:placetype":"locality"
},
  "geometry": {"coordinates":[10.14217,-1.59767],"type":"Point"}
}