{
  "type": "Feature",
  "properties": {
    "gn:admin1_code":"09",
    "gn:asciiname":"Akonadem",
    "gn:country_code":"GA",
    "gn:dem":636,
    "gn:feature_class":"P",
    "gn:feature_code":"PPL",
    "gn:name":"Akonadem",
    "gn:population":0,
    "gn:timezone":"Africa/Libreville",
    "iso:country":"GA",
    "wof:name":"Akonadem",
    "wof:placetype":"locality"
},
  "geometry": {"coordinates":[11.52138,1.67196],"type":"Point"}
}