{
  "type": "Feature",
  "properties": {
    "gn:admin1_code":"05",
    "gn:asciiname":"Mouetji",
    "gn:country_code":"GA",
    "gn:dem":323,
    "gn:feature_class":"P",
    "gn:feature_code":"PPL",
    "gn:name":"Mouetji",
    "gn:population":0,
    "gn:timezone":"Africa/Libreville",
    "iso:country":"GA",
    "wof:name":"Mouetji",
    "wof:placetype":"locality"
},
  "geometry": {"coordinates":[11.16667,-2.65],"type":"Point"}
}