{
  "type": "Feature",
  "properties": {
    "gn:admin1_code":"01",
    "gn:asciiname":"Nzang-Ayong",
    "gn:country_code":"GA",
    "gn:dem":23,
    "gn:feature_class":"P",
    "gn:feature_code":"PPL",
    "gn:name":"Nzang-Ayong",
    "gn:population":0,
    "gn:timezone":"Africa/Libreville",
    "iso:country":"GA",
    "wof:name":"Nzang-Ayong",
    "wof:placetype":"locality"
},
  "geometry": {"coordinates":[9.71667,0.53333],"type":"Point"}
}