{
  "type": "Feature",
  "properties": {
    "gn:admin1_code":"09",
    "gn:asciiname":"Ayeguening",
    "gn:country_code":"GA",
    "gn:dem":620,
    "gn:feature_class":"P",
    "gn:feature_code":"PPL",
    "gn:name":"Ayeguening",
    "gn:population":0,
    "gn:timezone":"Africa/Libreville",
    "iso:country":"GA",
    "wof:name":"Ayeguening",
    "wof:placetype":"locality"
},
  "geometry": {"coordinates":[11.94664,1.92918],"type":"Point"}
}