{
  "type": "Feature",
  "properties": {
    "gn:admin1_code":"04",
    "gn:asciiname":"Miongo",
    "gn:country_code":"GA",
    "gn:dem":440,
    "gn:feature_class":"P",
    "gn:feature_code":"PPL",
    "gn:name":"Miongo",
    "gn:population":0,
    "gn:timezone":"Africa/Libreville",
    "iso:country":"GA",
    "wof:name":"Miongo",
    "wof:placetype":"locality"
},
  "geometry": {"coordinates":[11.46667,-1.91667],"type":"Point"}
}