{
  "type": "Feature",
  "properties": {
    "gn:admin1_code":"05",
    "gn:asciiname":"Mougandza",
    "gn:country_code":"GA",
    "gn:dem":249,
    "gn:feature_class":"P",
    "gn:feature_code":"PPL",
    "gn:name":"Mougandza",
    "gn:population":0,
    "gn:timezone":"Africa/Libreville",
    "iso:country":"GA",
    "wof:name":"Mougandza",
    "wof:placetype":"locality"
},
  "geometry": {"coordinates":[10.99619,-2.7775],"type":"Point"}
}