{
  "type": "Feature",
  "properties": {
    "gn:admin1_code":"04",
    "gn:asciiname":"Moulamba",
    "gn:country_code":"GA",
    "gn:dem":71,
    "gn:feature_class":"P",
    "gn:feature_code":"PPL",
    "gn:name":"Moulamba",
    "gn:population":0,
    "gn:timezone":"Africa/Libreville",
    "iso:country":"GA",
    "wof:name":"Moulamba",
    "wof:placetype":"locality"
},
  "geometry": {"coordinates":[10.68333,-1.03333],"type":"Point"}
}