{
  "type": "Feature",
  "properties": {
    "gn:admin1_code":"03",
    "gn:asciiname":"Mapouti",
    "gn:country_code":"GA",
    "gn:dem":74,
    "gn:feature_class":"P",
    "gn:feature_code":"PPL",
    "gn:name":"Mapouti",
    "gn:population":0,
    "gn:timezone":"Africa/Libreville",
    "iso:country":"GA",
    "wof:name":"Mapouti",
    "wof:placetype":"locality"
},
  "geometry": {"coordinates":[10.46667,-0.46667],"type":"Point"}
}