{
  "type": "Feature",
  "properties": {
    "gn:admin1_code":"09",
    "gn:asciiname":"Mbomo II",
    "gn:country_code":"GA",
    "gn:dem":593,
    "gn:feature_class":"P",
    "gn:feature_code":"PPL",
    "gn:name":"Mbomo II",
    "gn:population":0,
    "gn:timezone":"Africa/Libreville",
    "iso:country":"GA",
    "wof:name":"Mbomo II",
    "wof:placetype":"locality"
},
  "geometry": {"coordinates":[11.95,2.06667],"type":"Point"}
}