{
  "type": "Feature",
  "properties": {
    "gn:admin1_code":"08",
    "gn:asciiname":"Ngola",
    "gn:country_code":"GA",
    "gn:dem":20,
    "gn:feature_class":"P",
    "gn:feature_code":"PPL",
    "gn:name":"Ngola",
    "gn:population":0,
    "gn:timezone":"Africa/Libreville",
    "iso:country":"GA",
    "name:ceb_x_preferred":[
        "Ngola"
    ],
    "name:deu_x_preferred":[
        "Ngola"
    ],
    "name:fra_x_preferred":[
        "Ngola"
    ],
    "name:swe_x_preferred":[
        "Ngola"
    ],
    "wof:name":"Ngola",
    "wof:placetype":"locality"
},
  "geometry": {"coordinates":[9.05408,-0.97558],"type":"Point"}
}