{
  "type": "Feature",
  "properties": {
    "gn:admin1_code":"09",
    "gn:asciiname":"Elarmilon",
    "gn:country_code":"GA",
    "gn:dem":326,
    "gn:feature_class":"P",
    "gn:feature_code":"PPL",
    "gn:name":"Elarmilon",
    "gn:population":0,
    "gn:timezone":"Africa/Libreville",
    "iso:country":"GA",
    "wof:name":"Elarmilon",
    "wof:placetype":"locality"
},
  "geometry": {"coordinates":[11.46235,0.48202],"type":"Point"}
}