{
  "type": "Feature",
  "properties": {
    "gn:admin1_code":"08",
    "gn:asciiname":"Issinga",
    "gn:country_code":"GA",
    "gn:dem":9,
    "gn:feature_class":"P",
    "gn:feature_code":"PPL",
    "gn:name":"Issinga",
    "gn:population":0,
    "gn:timezone":"Africa/Libreville",
    "iso:country":"GA",
    "wof:name":"Issinga",
    "wof:placetype":"locality"
},
  "geometry": {"coordinates":[9.52656,-1.15292],"type":"Point"}
}