{
  "type": "Feature",
  "properties": {
    "gn:admin1_code":"05",
    "gn:asciiname":"Iyantzi",
    "gn:country_code":"GA",
    "gn:dem":237,
    "gn:feature_class":"P",
    "gn:feature_code":"PPL",
    "gn:name":"Iyantzi",
    "gn:population":0,
    "gn:timezone":"Africa/Libreville",
    "iso:country":"GA",
    "wof:name":"Iyantzi",
    "wof:placetype":"locality"
},
  "geometry": {"coordinates":[11.11703,-3.00258],"type":"Point"}
}