{
  "type": "Feature",
  "properties": {
    "gn:admin1_code":"05",
    "gn:asciiname":"Mabili",
    "gn:country_code":"GA",
    "gn:dem":350,
    "gn:feature_class":"P",
    "gn:feature_code":"PPL",
    "gn:name":"Mabili",
    "gn:population":0,
    "gn:timezone":"Africa/Libreville",
    "iso:country":"GA",
    "wof:name":"Mabili",
    "wof:placetype":"locality"
},
  "geometry": {"coordinates":[11.56972,-3.27268],"type":"Point"}
}