{
  "type": "Feature",
  "properties": {
    "gn:admin1_code":"07",
    "gn:asciiname":"Mitoungou",
    "gn:country_code":"GA",
    "gn:dem":697,
    "gn:feature_class":"P",
    "gn:feature_code":"PPL",
    "gn:name":"Mitoungou",
    "gn:population":0,
    "gn:timezone":"Africa/Libreville",
    "iso:country":"GA",
    "name:und_x_variant":[
        "Mitounga",
        "Mitoungou"
    ],
    "wof:name":"Mitoungou",
    "wof:placetype":"locality"
},
  "geometry": {"coordinates":[12.78518,-1.72786],"type":"Point"}
}