{
  "type": "Feature",
  "properties": {
    "gn:admin1_code":"09",
    "gn:asciiname":"Mebaza",
    "gn:country_code":"GA",
    "gn:dem":598,
    "gn:feature_class":"P",
    "gn:feature_code":"PPL",
    "gn:name":"M\u00e9baza",
    "gn:population":0,
    "gn:timezone":"Africa/Libreville",
    "iso:country":"GA",
    "wof:name":"Mebaza",
    "wof:placetype":"locality"
},
  "geometry": {"coordinates":[11.42,2.03721],"type":"Point"}
}