{
  "type": "Feature",
  "properties": {
    "gn:admin1_code":"04",
    "gn:asciiname":"Idoumi",
    "gn:country_code":"GA",
    "gn:dem":115,
    "gn:feature_class":"P",
    "gn:feature_code":"PPL",
    "gn:name":"Idoumi",
    "gn:population":0,
    "gn:timezone":"Africa/Libreville",
    "iso:country":"GA",
    "wof:name":"Idoumi",
    "wof:placetype":"locality"
},
  "geometry": {"coordinates":[10.61667,-1.38333],"type":"Point"}
}