{
  "type": "Feature",
  "properties": {
    "gn:admin1_code":"05",
    "gn:asciiname":"Ilendo",
    "gn:country_code":"GA",
    "gn:dem":94,
    "gn:feature_class":"P",
    "gn:feature_code":"PPL",
    "gn:name":"Ilendo",
    "gn:population":0,
    "gn:timezone":"Africa/Libreville",
    "iso:country":"GA",
    "wof:name":"Ilendo",
    "wof:placetype":"locality"
},
  "geometry": {"coordinates":[11.52813,-3.26882],"type":"Point"}
}