{
  "type": "Feature",
  "properties": {
    "gn:admin1_code":"06",
    "gn:asciiname":"Balemba I",
    "gn:country_code":"GA",
    "gn:dem":400,
    "gn:feature_class":"P",
    "gn:feature_code":"PPL",
    "gn:name":"Balemba I",
    "gn:population":0,
    "gn:timezone":"Africa/Libreville",
    "iso:country":"GA",
    "wof:name":"Balemba I",
    "wof:placetype":"locality"
},
  "geometry": {"coordinates":[11.88999,0.12836],"type":"Point"}
}