{
  "type": "Feature",
  "properties": {
    "gn:admin1_code":"01",
    "gn:asciiname":"Essanang",
    "gn:cc2":"GA",
    "gn:country_code":"GA",
    "gn:dem":31,
    "gn:feature_class":"P",
    "gn:feature_code":"PPL",
    "gn:name":"Essanang",
    "gn:population":0,
    "gn:timezone":"Africa/Libreville",
    "iso:country":"GA",
    "name:und_x_variant":[
        "N\u2019Tchoua",
        "Essanang"
    ],
    "wof:name":"Essanang",
    "wof:placetype":"locality"
},
  "geometry": {"coordinates":[9.43333,0.05],"type":"Point"}
}