{
  "type": "Feature",
  "properties": {
    "gn:admin1_code":"02",
    "gn:asciiname":"Boma",
    "gn:country_code":"GA",
    "gn:dem":443,
    "gn:feature_class":"P",
    "gn:feature_code":"PPL",
    "gn:name":"Boma",
    "gn:population":0,
    "gn:timezone":"Africa/Libreville",
    "iso:country":"GA",
    "name:ceb_x_preferred":[
        "Boma"
    ],
    "name:deu_x_preferred":[
        "Boma"
    ],
    "name:fra_x_preferred":[
        "Boma"
    ],
    "name:ita_x_preferred":[
        "Boma"
    ],
    "name:lin_x_preferred":[
        "Boma"
    ],
    "name:nld_x_preferred":[
        "Boma"
    ],
    "name:pol_x_preferred":[
        "Boma"
    ],
    "name:por_x_preferred":[
        "Boma"
    ],
    "name:rus_x_preferred":[
        "\u0411\u043e\u043c\u0430"
    ],
    "name:srp_x_preferred":[
        "\u0411\u043e\u043c\u0430"
    ],
    "name:swe_x_preferred":[
        "Boma"
    ],
    "wof:name":"Boma",
    "wof:placetype":"locality"
},
  "geometry": {"coordinates":[13.34642,-1.67053],"type":"Point"}
}