{
  "type": "Feature",
  "properties": {
    "gn:admin1_code":"05",
    "gn:asciiname":"Milando",
    "gn:country_code":"GA",
    "gn:dem":76,
    "gn:feature_class":"P",
    "gn:feature_code":"PPL",
    "gn:name":"Milando",
    "gn:population":0,
    "gn:timezone":"Africa/Libreville",
    "iso:country":"GA",
    "wof:name":"Milando",
    "wof:placetype":"locality"
},
  "geometry": {"coordinates":[10.70565,-2.65234],"type":"Point"}
}