{
  "type": "Feature",
  "properties": {
    "gn:admin1_code":"05",
    "gn:asciiname":"Dougandou I",
    "gn:country_code":"GA",
    "gn:dem":242,
    "gn:feature_class":"P",
    "gn:feature_code":"PPL",
    "gn:name":"Dougandou I",
    "gn:population":0,
    "gn:timezone":"Africa/Libreville",
    "iso:country":"GA",
    "wof:name":"Dougandou I",
    "wof:placetype":"locality"
},
  "geometry": {"coordinates":[10.97053,-2.73269],"type":"Point"}
}