{
  "type": "Feature",
  "properties": {
    "gn:admin1_code":"09",
    "gn:asciiname":"Mengang II",
    "gn:country_code":"GA",
    "gn:dem":624,
    "gn:feature_class":"P",
    "gn:feature_code":"PPL",
    "gn:name":"Mengang II",
    "gn:population":0,
    "gn:timezone":"Africa/Libreville",
    "iso:country":"GA",
    "wof:name":"Mengang II",
    "wof:placetype":"locality"
},
  "geometry": {"coordinates":[11.75,1.85],"type":"Point"}
}