{
  "type": "Feature",
  "properties": {
    "gn:admin1_code":"06",
    "gn:asciiname":"Inze",
    "gn:country_code":"GA",
    "gn:dem":515,
    "gn:feature_class":"P",
    "gn:feature_code":"PPL",
    "gn:name":"Inz\u00e9",
    "gn:population":0,
    "gn:timezone":"Africa/Libreville",
    "iso:country":"GA",
    "wof:name":"Inze",
    "wof:placetype":"locality"
},
  "geometry": {"coordinates":[13.32635,0.76667],"type":"Point"}
}