{
  "type": "Feature",
  "properties": {
    "gn:admin1_code":"07",
    "gn:asciiname":"Lindeba-Combi",
    "gn:country_code":"GA",
    "gn:dem":382,
    "gn:feature_class":"P",
    "gn:feature_code":"PPL",
    "gn:name":"Lindeba-Combi",
    "gn:population":0,
    "gn:timezone":"Africa/Libreville",
    "iso:country":"GA",
    "wof:name":"Lindeba-Combi",
    "wof:placetype":"locality"
},
  "geometry": {"coordinates":[13.08333,-1.21667],"type":"Point"}
}