{
  "type": "Feature",
  "properties": {
    "gn:admin1_code":"09",
    "gn:asciiname":"Nkogomesseng",
    "gn:country_code":"GA",
    "gn:dem":623,
    "gn:feature_class":"P",
    "gn:feature_code":"PPL",
    "gn:name":"Nkogomesseng",
    "gn:population":0,
    "gn:timezone":"Africa/Libreville",
    "iso:country":"GA",
    "wof:name":"Nkogomesseng",
    "wof:placetype":"locality"
},
  "geometry": {"coordinates":[11.92829,1.91195],"type":"Point"}
}