{
  "type": "Feature",
  "properties": {
    "gn:admin1_code":"04",
    "gn:asciiname":"Ebando",
    "gn:country_code":"GA",
    "gn:dem":575,
    "gn:feature_class":"P",
    "gn:feature_code":"PPL",
    "gn:name":"Ebando",
    "gn:population":0,
    "gn:timezone":"Africa/Libreville",
    "iso:country":"GA",
    "wof:name":"Ebando",
    "wof:placetype":"locality"
},
  "geometry": {"coordinates":[11.58333,-1.58333],"type":"Point"}
}