{
  "type": "Feature",
  "properties": {
    "gn:admin1_code":"06",
    "gn:asciiname":"Ikie",
    "gn:country_code":"GA",
    "gn:dem":551,
    "gn:feature_class":"P",
    "gn:feature_code":"PPL",
    "gn:name":"Iki\u00e9",
    "gn:population":0,
    "gn:timezone":"Africa/Libreville",
    "iso:country":"GA",
    "wof:name":"Ikie",
    "wof:placetype":"locality"
},
  "geometry": {"coordinates":[13.68333,0.91667],"type":"Point"}
}