{
  "type": "Feature",
  "properties": {
    "gn:admin1_code":"09",
    "gn:asciiname":"Nkomelene",
    "gn:country_code":"GA",
    "gn:dem":688,
    "gn:feature_class":"P",
    "gn:feature_code":"PPL",
    "gn:name":"Nkomelene",
    "gn:population":0,
    "gn:timezone":"Africa/Libreville",
    "iso:country":"GA",
    "wof:name":"Nkomelene",
    "wof:placetype":"locality"
},
  "geometry": {"coordinates":[11.75698,1.56118],"type":"Point"}
}