{
  "type": "Feature",
  "properties": {
    "gn:admin1_code":"03",
    "gn:asciiname":"Akok",
    "gn:country_code":"GA",
    "gn:dem":64,
    "gn:feature_class":"P",
    "gn:feature_code":"PPL",
    "gn:name":"Akok",
    "gn:population":0,
    "gn:timezone":"Africa/Libreville",
    "iso:country":"GA",
    "name:und_x_variant":[
        "Nkok"
    ],
    "wof:name":"Akok",
    "wof:placetype":"locality"
},
  "geometry": {"coordinates":[10.4367,-0.27381],"type":"Point"}
}