{
  "type": "Feature",
  "properties": {
    "gn:admin1_code":"04",
    "gn:asciiname":"Mboukou",
    "gn:country_code":"GA",
    "gn:dem":113,
    "gn:feature_class":"P",
    "gn:feature_code":"PPL",
    "gn:name":"Mboukou",
    "gn:population":0,
    "gn:timezone":"Africa/Libreville",
    "iso:country":"GA",
    "wof:name":"Mboukou",
    "wof:placetype":"locality"
},
  "geometry": {"coordinates":[10.81231,-1.7157],"type":"Point"}
}