{
  "type": "Feature",
  "properties": {
    "gn:admin1_code":"07",
    "gn:asciiname":"Midouma et Ngouassa",
    "gn:country_code":"GA",
    "gn:dem":378,
    "gn:feature_class":"P",
    "gn:feature_code":"PPL",
    "gn:name":"Midouma et Ngouassa",
    "gn:population":0,
    "gn:timezone":"Africa/Libreville",
    "iso:country":"GA",
    "wof:name":"Midouma et Ngouassa",
    "wof:placetype":"locality"
},
  "geometry": {"coordinates":[12.36172,-1.44748],"type":"Point"}
}