{
  "type": "Feature",
  "properties": {
    "gn:admin1_code":"01",
    "gn:asciiname":"Mikolongo",
    "gn:country_code":"GA",
    "gn:dem":36,
    "gn:feature_class":"P",
    "gn:feature_code":"PPL",
    "gn:name":"Mikolongo",
    "gn:population":0,
    "gn:timezone":"Africa/Libreville",
    "iso:country":"GA",
    "wof:name":"Mikolongo",
    "wof:placetype":"locality"
},
  "geometry": {"coordinates":[9.64466,0.72863],"type":"Point"}
}