{
  "type": "Feature",
  "properties": {
    "gn:admin1_code":"01",
    "gn:asciiname":"Ndouaniang",
    "gn:country_code":"GA",
    "gn:dem":26,
    "gn:feature_class":"P",
    "gn:feature_code":"PPL",
    "gn:name":"Ndouaniang",
    "gn:population":0,
    "gn:timezone":"Africa/Libreville",
    "iso:country":"GA",
    "name:und_x_variant":[
        "Ndouanieng",
        "Douaniang"
    ],
    "wof:name":"Ndouaniang",
    "wof:placetype":"locality"
},
  "geometry": {"coordinates":[10.02516,0.30228],"type":"Point"}
}