{
  "type": "Feature",
  "properties": {
    "gn:admin1_code":"05",
    "gn:asciiname":"Soukila",
    "gn:country_code":"GA",
    "gn:dem":304,
    "gn:feature_class":"P",
    "gn:feature_code":"PPL",
    "gn:name":"Soukila",
    "gn:population":0,
    "gn:timezone":"Africa/Libreville",
    "iso:country":"GA",
    "wof:name":"Soukila",
    "wof:placetype":"locality"
},
  "geometry": {"coordinates":[11.01667,-2.36667],"type":"Point"}
}