{
  "type": "Feature",
  "properties": {
    "gn:admin1_code":"06",
    "gn:asciiname":"Mbebengui",
    "gn:country_code":"GA",
    "gn:dem":515,
    "gn:feature_class":"P",
    "gn:feature_code":"PPL",
    "gn:name":"Mbebengui",
    "gn:population":0,
    "gn:timezone":"Africa/Libreville",
    "iso:country":"GA",
    "wof:name":"Mbebengui",
    "wof:placetype":"locality"
},
  "geometry": {"coordinates":[12.75,0.58333],"type":"Point"}
}