{
  "type": "Feature",
  "properties": {
    "gn:admin1_code":"03",
    "gn:asciiname":"Bordeaux",
    "gn:country_code":"GA",
    "gn:dem":26,
    "gn:feature_class":"P",
    "gn:feature_code":"PPL",
    "gn:name":"Bordeaux",
    "gn:population":0,
    "gn:timezone":"Africa/Libreville",
    "iso:country":"GA",
    "wof:name":"Bordeaux",
    "wof:placetype":"locality"
},
  "geometry": {"coordinates":[10.18358,-0.82841],"type":"Point"}
}