{
  "type": "Feature",
  "properties": {
    "gn:admin1_code":"09",
    "gn:asciiname":"Andok",
    "gn:country_code":"GA",
    "gn:dem":647,
    "gn:feature_class":"P",
    "gn:feature_code":"PPL",
    "gn:name":"Andok",
    "gn:population":0,
    "gn:timezone":"Africa/Libreville",
    "iso:country":"GA",
    "wof:name":"Andok",
    "wof:placetype":"locality"
},
  "geometry": {"coordinates":[11.68866,1.69643],"type":"Point"}
}