{
  "type": "Feature",
  "properties": {
    "gn:admin1_code":"06",
    "gn:asciiname":"Eyameyong",
    "gn:country_code":"GA",
    "gn:dem":533,
    "gn:feature_class":"P",
    "gn:feature_code":"PPL",
    "gn:name":"Eyameyong",
    "gn:population":0,
    "gn:timezone":"Africa/Libreville",
    "iso:country":"GA",
    "name:und_x_variant":[
        "Eyamayong",
        "Eyameyon",
        "Eyameyong"
    ],
    "wof:name":"Eyameyong",
    "wof:placetype":"locality"
},
  "geometry": {"coordinates":[12.62097,0.5642],"type":"Point"}
}