{
  "type": "Feature",
  "properties": {
    "gn:admin1_code":"09",
    "gn:asciiname":"Edoung Alangha",
    "gn:country_code":"GA",
    "gn:dem":580,
    "gn:feature_class":"P",
    "gn:feature_code":"PPL",
    "gn:name":"Edoung Alangha",
    "gn:population":0,
    "gn:timezone":"Africa/Libreville",
    "iso:country":"GA",
    "wof:name":"Edoung Alangha",
    "wof:placetype":"locality"
},
  "geometry": {"coordinates":[11.50679,0.80546],"type":"Point"}
}