{
  "type": "Feature",
  "properties": {
    "gn:admin1_code":"04",
    "gn:asciiname":"Camba Mongo",
    "gn:country_code":"GA",
    "gn:dem":727,
    "gn:feature_class":"P",
    "gn:feature_code":"PPL",
    "gn:name":"Camba Mongo",
    "gn:population":0,
    "gn:timezone":"Africa/Libreville",
    "iso:country":"GA",
    "wof:name":"Camba Mongo",
    "wof:placetype":"locality"
},
  "geometry": {"coordinates":[12.11105,-1.90918],"type":"Point"}
}