{
  "type": "Feature",
  "properties": {
    "gn:admin1_code":"09",
    "gn:asciiname":"Assengasi",
    "gn:country_code":"GA",
    "gn:dem":612,
    "gn:feature_class":"P",
    "gn:feature_code":"PPL",
    "gn:name":"Assengasi",
    "gn:population":0,
    "gn:timezone":"Africa/Libreville",
    "iso:country":"GA",
    "wof:name":"Assengasi",
    "wof:placetype":"locality"
},
  "geometry": {"coordinates":[11.98333,2.08333],"type":"Point"}
}