{
  "type": "Feature",
  "properties": {
    "gn:admin1_code":"06",
    "gn:asciiname":"Ndengoue",
    "gn:country_code":"GA",
    "gn:dem":524,
    "gn:feature_class":"P",
    "gn:feature_code":"PPL",
    "gn:name":"Ndengou\u00e9",
    "gn:population":0,
    "gn:timezone":"Africa/Libreville",
    "iso:country":"GA",
    "wof:name":"Ndengoue",
    "wof:placetype":"locality"
},
  "geometry": {"coordinates":[12.96667,0.61667],"type":"Point"}
}