{
  "type": "Feature",
  "properties": {
    "gn:admin1_code":"01",
    "gn:asciiname":"Nzogobeyork",
    "gn:country_code":"GA",
    "gn:dem":19,
    "gn:feature_class":"P",
    "gn:feature_code":"PPL",
    "gn:name":"Nzogobeyork",
    "gn:population":0,
    "gn:timezone":"Africa/Libreville",
    "iso:country":"GA",
    "wof:name":"Nzogobeyork",
    "wof:placetype":"locality"
},
  "geometry": {"coordinates":[9.38333,0.51667],"type":"Point"}
}