{
  "type": "Feature",
  "properties": {
    "gn:admin1_code":"04",
    "gn:asciiname":"Lelende",
    "gn:country_code":"GA",
    "gn:dem":761,
    "gn:feature_class":"P",
    "gn:feature_code":"PPL",
    "gn:name":"Lelend\u00e9",
    "gn:population":0,
    "gn:timezone":"Africa/Libreville",
    "iso:country":"GA",
    "wof:name":"Lelende",
    "wof:placetype":"locality"
},
  "geometry": {"coordinates":[12.15,-2.05],"type":"Point"}
}