{
  "type": "Feature",
  "properties": {
    "gn:admin1_code":"04",
    "gn:asciiname":"Doussala",
    "gn:country_code":"GA",
    "gn:dem":157,
    "gn:feature_class":"P",
    "gn:feature_code":"PPL",
    "gn:name":"Doussala",
    "gn:population":0,
    "gn:timezone":"Africa/Libreville",
    "iso:country":"GA",
    "wof:name":"Doussala",
    "wof:placetype":"locality"
},
  "geometry": {"coordinates":[11.62766,-2.64402],"type":"Point"}
}