{
  "type": "Feature",
  "properties": {
    "gn:admin1_code":"04",
    "gn:asciiname":"Ngouassa Mabounda",
    "gn:cc2":"GA",
    "gn:country_code":"GA",
    "gn:dem":729,
    "gn:feature_class":"P",
    "gn:feature_code":"PPL",
    "gn:name":"Ngouassa Mabounda",
    "gn:population":0,
    "gn:timezone":"Africa/Libreville",
    "iso:country":"GA",
    "name:und_x_variant":[
        "Ngwassa Mabouuza",
        "Ngwassa Mab",
        "Ngwassa Mabounza",
        "Ngouaza Mabounza",
        "Ngouassa Mabounda"
    ],
    "wof:name":"Ngouassa Mabounda",
    "wof:placetype":"locality"
},
  "geometry": {"coordinates":[11.51667,-1.45],"type":"Point"}
}