{
  "type": "Feature",
  "properties": {
    "gn:admin1_code":"05",
    "gn:asciiname":"Irendou",
    "gn:country_code":"GA",
    "gn:dem":303,
    "gn:feature_class":"P",
    "gn:feature_code":"PPL",
    "gn:name":"Irendou",
    "gn:population":0,
    "gn:timezone":"Africa/Libreville",
    "iso:country":"GA",
    "wof:name":"Irendou",
    "wof:placetype":"locality"
},
  "geometry": {"coordinates":[11.08333,-2.71667],"type":"Point"}
}