{
  "type": "Feature",
  "properties": {
    "gn:admin1_code":"02",
    "gn:asciiname":"Empoussa",
    "gn:country_code":"GA",
    "gn:dem":453,
    "gn:feature_class":"P",
    "gn:feature_code":"PPL",
    "gn:name":"Empoussa",
    "gn:population":0,
    "gn:timezone":"Africa/Libreville",
    "iso:country":"GA",
    "wof:name":"Empoussa",
    "wof:placetype":"locality"
},
  "geometry": {"coordinates":[13.79279,-1.24053],"type":"Point"}
}