{
  "type": "Feature",
  "properties": {
    "gn:admin1_code":"09",
    "gn:asciiname":"Ebei",
    "gn:country_code":"GA",
    "gn:dem":573,
    "gn:feature_class":"P",
    "gn:feature_code":"PPL",
    "gn:name":"Ebe\u00ef",
    "gn:population":0,
    "gn:timezone":"Africa/Libreville",
    "iso:country":"GA",
    "wof:name":"Ebei",
    "wof:placetype":"locality"
},
  "geometry": {"coordinates":[11.48413,1.16203],"type":"Point"}
}