{
  "type": "Feature",
  "properties": {
    "gn:admin1_code":"09",
    "gn:asciiname":"Aloune",
    "gn:country_code":"GA",
    "gn:dem":622,
    "gn:feature_class":"P",
    "gn:feature_code":"PPL",
    "gn:name":"Aloun\u00e9",
    "gn:population":0,
    "gn:timezone":"Africa/Libreville",
    "iso:country":"GA",
    "wof:name":"Aloune",
    "wof:placetype":"locality"
},
  "geometry": {"coordinates":[11.66667,2.08333],"type":"Point"}
}