{
  "type": "Feature",
  "properties": {
    "gn:admin1_code":"01",
    "gn:asciiname":"Boutica",
    "gn:country_code":"GA",
    "gn:dem":18,
    "gn:feature_class":"P",
    "gn:feature_code":"PPL",
    "gn:name":"Boutica",
    "gn:population":0,
    "gn:timezone":"Africa/Libreville",
    "iso:country":"GA",
    "name:und_x_variant":[
        "Butica Uvinia",
        "Butika",
        "Butica",
        "Boutica"
    ],
    "wof:name":"Boutica",
    "wof:placetype":"locality"
},
  "geometry": {"coordinates":[9.66303,1.05657],"type":"Point"}
}