{
  "type": "Feature",
  "properties": {
    "gn:admin1_code":"04",
    "gn:asciiname":"Levama",
    "gn:country_code":"GA",
    "gn:dem":249,
    "gn:feature_class":"P",
    "gn:feature_code":"PPL",
    "gn:name":"Levama",
    "gn:population":0,
    "gn:timezone":"Africa/Libreville",
    "iso:country":"GA",
    "wof:name":"Levama",
    "wof:placetype":"locality"
},
  "geometry": {"coordinates":[11.65,-2.33333],"type":"Point"}
}