{
  "type": "Feature",
  "properties": {
    "gn:admin1_code":"04",
    "gn:asciiname":"Soangui",
    "gn:country_code":"GA",
    "gn:dem":150,
    "gn:feature_class":"P",
    "gn:feature_code":"PPL",
    "gn:name":"Soangui",
    "gn:population":0,
    "gn:timezone":"Africa/Libreville",
    "iso:country":"GA",
    "wof:name":"Soangui",
    "wof:placetype":"locality"
},
  "geometry": {"coordinates":[11.46667,-2.28333],"type":"Point"}
}