{
  "type": "Feature",
  "properties": {
    "gn:admin1_code":"09",
    "gn:asciiname":"Kong",
    "gn:country_code":"GA",
    "gn:dem":598,
    "gn:feature_class":"P",
    "gn:feature_code":"PPL",
    "gn:name":"Kong",
    "gn:population":0,
    "gn:timezone":"Africa/Libreville",
    "iso:country":"GA",
    "name:aka_x_preferred":[
        "Kong"
    ],
    "name:ceb_x_preferred":[
        "Kong"
    ],
    "name:dan_x_preferred":[
        "Kong"
    ],
    "name:deu_x_preferred":[
        "Kong"
    ],
    "name:fra_x_preferred":[
        "Kong"
    ],
    "name:ita_x_preferred":[
        "Kong"
    ],
    "name:jpn_x_preferred":[
        "\u30b3\u30f3\u30b0"
    ],
    "name:kor_x_preferred":[
        "\ucf69"
    ],
    "name:nld_x_preferred":[
        "Kong"
    ],
    "name:nor_x_preferred":[
        "Kong"
    ],
    "name:pol_x_preferred":[
        "Kong"
    ],
    "name:por_x_preferred":[
        "Kong"
    ],
    "name:rus_x_preferred":[
        "\u041a\u043e\u043d\u0433"
    ],
    "name:swe_x_preferred":[
        "Kong"
    ],
    "wof:name":"Kong",
    "wof:placetype":"locality"
},
  "geometry": {"coordinates":[11.73333,2.23333],"type":"Point"}
}