{
  "type": "Feature",
  "properties": {
    "gn:admin1_code":"01",
    "gn:asciiname":"Akana-Bour",
    "gn:country_code":"GA",
    "gn:dem":39,
    "gn:feature_class":"P",
    "gn:feature_code":"PPL",
    "gn:name":"Akana-Bour",
    "gn:population":0,
    "gn:timezone":"Africa/Libreville",
    "iso:country":"GA",
    "wof:name":"Akana-Bour",
    "wof:placetype":"locality"
},
  "geometry": {"coordinates":[9.93333,0.35],"type":"Point"}
}