{
  "type": "Feature",
  "properties": {
    "gn:admin1_code":"09",
    "gn:asciiname":"Aniane",
    "gn:country_code":"GA",
    "gn:dem":475,
    "gn:feature_class":"P",
    "gn:feature_code":"PPL",
    "gn:name":"Aniane",
    "gn:population":0,
    "gn:timezone":"Africa/Libreville",
    "iso:country":"GA",
    "name:bel_x_preferred":[
        "\u0410\u043d\u044c\u044f\u043d"
    ],
    "name:cat_x_preferred":[
        "Aniana"
    ],
    "name:ceb_x_preferred":[
        "Aniane"
    ],
    "name:ces_x_preferred":[
        "Aniane"
    ],
    "name:deu_x_preferred":[
        "Aniane"
    ],
    "name:eus_x_preferred":[
        "Aniane"
    ],
    "name:fra_x_preferred":[
        "Aniane"
    ],
    "name:heb_x_preferred":[
        "\u05d0\u05e0\u05d9\u05d0\u05df"
    ],
    "name:hun_x_preferred":[
        "Aniane"
    ],
    "name:ita_x_preferred":[
        "Aniane"
    ],
    "name:kaz_x_preferred":[
        "\u0410\u043d\u044c\u044f\u043d"
    ],
    "name:lat_x_preferred":[
        "Aniana"
    ],
    "name:lmo_x_preferred":[
        "Aniane"
    ],
    "name:msa_x_preferred":[
        "Aniane"
    ],
    "name:nld_x_preferred":[
        "Aniane"
    ],
    "name:oci_x_preferred":[
        "Aniana"
    ],
    "name:pms_x_preferred":[
        "Aniane"
    ],
    "name:pol_x_preferred":[
        "Aniane"
    ],
    "name:por_x_preferred":[
        "Aniane"
    ],
    "name:ron_x_preferred":[
        "Aniane"
    ],
    "name:slk_x_preferred":[
        "Aniane"
    ],
    "name:slv_x_preferred":[
        "Aniane"
    ],
    "name:spa_x_preferred":[
        "Aniane"
    ],
    "name:srp_x_preferred":[
        "\u0410\u043d\u0438\u0458\u0430\u043d"
    ],
    "name:swe_x_preferred":[
        "Aniane"
    ],
    "name:ukr_x_preferred":[
        "\u0410\u043d\u044c\u044f\u043d"
    ],
    "name:vie_x_preferred":[
        "Aniane"
    ],
    "name:vol_x_preferred":[
        "Aniane"
    ],
    "name:war_x_preferred":[
        "Aniane"
    ],
    "name:zho_x_preferred":[
        "\u963f\u5c3c\u6602"
    ],
    "wof:name":"Aniane",
    "wof:placetype":"locality"
},
  "geometry": {"coordinates":[11.66667,0.66667],"type":"Point"}
}