{
  "type": "Feature",
  "properties": {
    "gn:admin1_code":"09",
    "gn:asciiname":"Aniane",
    "gn:country_code":"GA",
    "gn:dem":475,
    "gn:feature_class":"P",
    "gn:feature_code":"PPL",
    "gn:name":"Aniane",
    "gn:population":0,
    "gn:timezone":"Africa/Libreville",
    "iso:country":"GA",
    "wof:name":"Aniane",
    "wof:placetype":"locality"
},
  "geometry": {"coordinates":[11.66667,0.66667],"type":"Point"}
}