{
  "type": "Feature",
  "properties": {
    "gn:admin1_code":"09",
    "gn:asciiname":"Akane",
    "gn:country_code":"GA",
    "gn:dem":633,
    "gn:feature_class":"P",
    "gn:feature_code":"PPL",
    "gn:name":"Akane",
    "gn:population":0,
    "gn:timezone":"Africa/Libreville",
    "iso:country":"GA",
    "wof:name":"Akane",
    "wof:placetype":"locality"
},
  "geometry": {"coordinates":[11.45135,1.75577],"type":"Point"}
}