{
  "type": "Feature",
  "properties": {
    "gn:admin1_code":"04",
    "gn:asciiname":"Vouta",
    "gn:country_code":"GA",
    "gn:dem":478,
    "gn:feature_class":"P",
    "gn:feature_code":"PPL",
    "gn:name":"Vouta",
    "gn:population":0,
    "gn:timezone":"Africa/Libreville",
    "iso:country":"GA",
    "name:und_x_variant":[
        "Ivouti",
        "Ivouta",
        "Vouta"
    ],
    "wof:name":"Vouta",
    "wof:placetype":"locality"
},
  "geometry": {"coordinates":[11.11602,-1.28281],"type":"Point"}
}