{
  "type": "Feature",
  "properties": {
    "gn:admin1_code":"09",
    "gn:asciiname":"Nkouara",
    "gn:country_code":"GA",
    "gn:dem":568,
    "gn:feature_class":"P",
    "gn:feature_code":"PPL",
    "gn:name":"Nkouara",
    "gn:population":0,
    "gn:timezone":"Africa/Libreville",
    "iso:country":"GA",
    "wof:name":"Nkouara",
    "wof:placetype":"locality"
},
  "geometry": {"coordinates":[11.50123,1.19884],"type":"Point"}
}