{
  "type": "Feature",
  "properties": {
    "gn:admin1_code":"06",
    "gn:asciiname":"Mbomo",
    "gn:country_code":"GA",
    "gn:dem":354,
    "gn:feature_class":"P",
    "gn:feature_code":"PPL",
    "gn:name":"Mbomo",
    "gn:population":0,
    "gn:timezone":"Africa/Libreville",
    "iso:country":"GA",
    "wof:name":"Mbomo",
    "wof:placetype":"locality"
},
  "geometry": {"coordinates":[11.55,0.31667],"type":"Point"}
}