{
  "type": "Feature",
  "properties": {
    "gn:admin1_code":"07",
    "gn:asciiname":"Massiya",
    "gn:country_code":"GA",
    "gn:dem":343,
    "gn:feature_class":"P",
    "gn:feature_code":"PPL",
    "gn:name":"Massiya",
    "gn:population":0,
    "gn:timezone":"Africa/Libreville",
    "iso:country":"GA",
    "wof:name":"Massiya",
    "wof:placetype":"locality"
},
  "geometry": {"coordinates":[11.95,-1.01667],"type":"Point"}
}