{
  "type": "Feature",
  "properties": {
    "gn:admin1_code":"04",
    "gn:asciiname":"Iniounga",
    "gn:country_code":"GA",
    "gn:dem":136,
    "gn:feature_class":"P",
    "gn:feature_code":"PPL",
    "gn:name":"Iniounga",
    "gn:population":0,
    "gn:timezone":"Africa/Libreville",
    "iso:country":"GA",
    "wof:name":"Iniounga",
    "wof:placetype":"locality"
},
  "geometry": {"coordinates":[10.38926,-1.72902],"type":"Point"}
}