{
  "type": "Feature",
  "properties": {
    "gn:admin1_code":"09",
    "gn:asciiname":"Feng",
    "gn:country_code":"GA",
    "gn:dem":603,
    "gn:feature_class":"P",
    "gn:feature_code":"PPL",
    "gn:name":"Feng",
    "gn:population":0,
    "gn:timezone":"Africa/Libreville",
    "iso:country":"GA",
    "name:ces_x_preferred":[
        "Feng"
    ],
    "name:deu_x_preferred":[
        "Feng"
    ],
    "name:fra_x_preferred":[
        "Feng"
    ],
    "name:nor_x_preferred":[
        "Feng"
    ],
    "name:por_x_preferred":[
        "Feng"
    ],
    "name:swe_x_preferred":[
        "Feng"
    ],
    "wof:name":"Feng",
    "wof:placetype":"locality"
},
  "geometry": {"coordinates":[11.34895,1.95005],"type":"Point"}
}