{
  "type": "Feature",
  "properties": {
    "gn:admin1_code":"01",
    "gn:asciiname":"Abenelang",
    "gn:country_code":"GA",
    "gn:dem":41,
    "gn:feature_class":"P",
    "gn:feature_code":"PPL",
    "gn:name":"Ab\u00e9n\u00e9lang",
    "gn:population":0,
    "gn:timezone":"Africa/Libreville",
    "iso:country":"GA",
    "wof:name":"Abenelang",
    "wof:placetype":"locality"
},
  "geometry": {"coordinates":[9.83333,0.25],"type":"Point"}
}