{
  "type": "Feature",
  "properties": {
    "gn:admin1_code":"07",
    "gn:asciiname":"Lissoka-Mabeka",
    "gn:country_code":"GA",
    "gn:dem":523,
    "gn:feature_class":"P",
    "gn:feature_code":"PPL",
    "gn:name":"Lissoka-Mabeka",
    "gn:population":0,
    "gn:timezone":"Africa/Libreville",
    "iso:country":"GA",
    "wof:name":"Lissoka-Mabeka",
    "wof:placetype":"locality"
},
  "geometry": {"coordinates":[12.88333,-1.41667],"type":"Point"}
}