{
  "type": "Feature",
  "properties": {
    "gn:admin1_code":"02",
    "gn:asciiname":"Mikouagni",
    "gn:country_code":"GA",
    "gn:dem":425,
    "gn:feature_class":"P",
    "gn:feature_code":"PPL",
    "gn:name":"Mikouagni",
    "gn:population":0,
    "gn:timezone":"Africa/Libreville",
    "iso:country":"GA",
    "wof:name":"Mikouagni",
    "wof:placetype":"locality"
},
  "geometry": {"coordinates":[13.14892,-1.6094],"type":"Point"}
}