{
  "type": "Feature",
  "properties": {
    "gn:admin1_code":"08",
    "gn:asciiname":"Nabigou",
    "gn:country_code":"GA",
    "gn:dem":5,
    "gn:feature_class":"P",
    "gn:feature_code":"PPL",
    "gn:name":"Nabigou",
    "gn:population":0,
    "gn:timezone":"Africa/Libreville",
    "iso:country":"GA",
    "wof:name":"Nabigou",
    "wof:placetype":"locality"
},
  "geometry": {"coordinates":[9.51667,-1.18333],"type":"Point"}
}