{
  "type": "Feature",
  "properties": {
    "gn:admin1_code":"01",
    "gn:asciiname":"Abouna",
    "gn:cc2":"GA",
    "gn:country_code":"GA",
    "gn:dem":-9999,
    "gn:feature_class":"P",
    "gn:feature_code":"PPL",
    "gn:name":"Abouna",
    "gn:population":0,
    "gn:timezone":"Africa/Libreville",
    "iso:country":"GA",
    "name:ara_x_preferred":[
        "\u0623\u0628\u0648\u0646\u0627"
    ],
    "name:dan_x_preferred":[
        "Abouna"
    ],
    "name:fas_x_preferred":[
        "\u0622\u0628\u0648\u0646\u0627"
    ],
    "name:fra_x_preferred":[
        "Abouna"
    ],
    "name:ita_x_preferred":[
        "Abouna"
    ],
    "name:pol_x_preferred":[
        "Nasz ojciec"
    ],
    "name:por_x_preferred":[
        "Abouna"
    ],
    "name:spa_x_preferred":[
        "Abouna"
    ],
    "name:und_x_variant":[
        "Abuna",
        "Abouna"
    ],
    "wof:name":"Abouna",
    "wof:placetype":"locality"
},
  "geometry": {"coordinates":[9.61667,0.25],"type":"Point"}
}