{
  "type": "Feature",
  "properties": {
    "gn:admin1_code":"01",
    "gn:asciiname":"Abouna",
    "gn:cc2":"GA",
    "gn:country_code":"GA",
    "gn:dem":-9999,
    "gn:feature_class":"P",
    "gn:feature_code":"PPL",
    "gn:name":"Abouna",
    "gn:population":0,
    "gn:timezone":"Africa/Libreville",
    "iso:country":"GA",
    "name:und_x_variant":[
        "Abuna",
        "Abouna"
    ],
    "wof:name":"Abouna",
    "wof:placetype":"locality"
},
  "geometry": {"coordinates":[9.61667,0.25],"type":"Point"}
}