{
  "type": "Feature",
  "properties": {
    "gn:admin1_code":"04",
    "gn:asciiname":"Idembe",
    "gn:country_code":"GA",
    "gn:dem":404,
    "gn:feature_class":"P",
    "gn:feature_code":"PPL",
    "gn:name":"Idemb\u00e9",
    "gn:population":0,
    "gn:timezone":"Africa/Libreville",
    "iso:country":"GA",
    "wof:name":"Idembe",
    "wof:placetype":"locality"
},
  "geometry": {"coordinates":[11.68333,-2.21667],"type":"Point"}
}