{
  "type": "Feature",
  "properties": {
    "gn:admin1_code":"06",
    "gn:asciiname":"Malembe",
    "gn:country_code":"GA",
    "gn:dem":537,
    "gn:feature_class":"P",
    "gn:feature_code":"PPL",
    "gn:name":"Malemb\u00e9",
    "gn:population":0,
    "gn:timezone":"Africa/Libreville",
    "iso:country":"GA",
    "wof:name":"Malembe",
    "wof:placetype":"locality"
},
  "geometry": {"coordinates":[13.33333,0.76667],"type":"Point"}
}