{
  "type": "Feature",
  "properties": {
    "gn:admin1_code":"09",
    "gn:asciiname":"Ngola I",
    "gn:country_code":"GA",
    "gn:dem":499,
    "gn:feature_class":"P",
    "gn:feature_code":"PPL",
    "gn:name":"Ngola I",
    "gn:population":0,
    "gn:timezone":"Africa/Libreville",
    "iso:country":"GA",
    "wof:name":"Ngola I",
    "wof:placetype":"locality"
},
  "geometry": {"coordinates":[11.58312,0.86173],"type":"Point"}
}