{
  "type": "Feature",
  "properties": {
    "gn:admin1_code":"09",
    "gn:asciiname":"Mboma",
    "gn:country_code":"GA",
    "gn:dem":671,
    "gn:feature_class":"P",
    "gn:feature_code":"PPL",
    "gn:name":"Mboma",
    "gn:population":0,
    "gn:timezone":"Africa/Libreville",
    "iso:country":"GA",
    "wof:name":"Mboma",
    "wof:placetype":"locality"
},
  "geometry": {"coordinates":[11.59102,1.37517],"type":"Point"}
}