{
  "type": "Feature",
  "properties": {
    "gn:admin1_code":"08",
    "gn:asciiname":"Ikengue",
    "gn:country_code":"GA",
    "gn:dem":5,
    "gn:feature_class":"P",
    "gn:feature_code":"PPL",
    "gn:name":"Ikengu\u00e9",
    "gn:population":0,
    "gn:timezone":"Africa/Libreville",
    "iso:country":"GA",
    "wof:name":"Ikengue",
    "wof:placetype":"locality"
},
  "geometry": {"coordinates":[9.47663,-1.51361],"type":"Point"}
}