{
  "type": "Feature",
  "properties": {
    "gn:admin1_code":"09",
    "gn:asciiname":"Abang I",
    "gn:country_code":"GA",
    "gn:dem":639,
    "gn:feature_class":"P",
    "gn:feature_code":"PPL",
    "gn:name":"Abang I",
    "gn:population":0,
    "gn:timezone":"Africa/Libreville",
    "iso:country":"GA",
    "wof:name":"Abang I",
    "wof:placetype":"locality"
},
  "geometry": {"coordinates":[11.61956,1.77386],"type":"Point"}
}