{
  "type": "Feature",
  "properties": {
    "gn:admin1_code":"09",
    "gn:asciiname":"Viafe",
    "gn:country_code":"GA",
    "gn:dem":328,
    "gn:feature_class":"P",
    "gn:feature_code":"PPL",
    "gn:name":"Viaf\u00e9",
    "gn:population":0,
    "gn:timezone":"Africa/Libreville",
    "iso:country":"GA",
    "wof:name":"Viafe",
    "wof:placetype":"locality"
},
  "geometry": {"coordinates":[11.42623,0.3352],"type":"Point"}
}