{
  "type": "Feature",
  "properties": {
    "gn:admin1_code":"04",
    "gn:asciiname":"Mazinga",
    "gn:country_code":"GA",
    "gn:dem":584,
    "gn:feature_class":"P",
    "gn:feature_code":"PPL",
    "gn:name":"Mazinga",
    "gn:population":0,
    "gn:timezone":"Africa/Libreville",
    "iso:country":"GA",
    "wof:name":"Mazinga",
    "wof:placetype":"locality"
},
  "geometry": {"coordinates":[12.22568,-2.40163],"type":"Point"}
}