{
  "type": "Feature",
  "properties": {
    "gn:admin1_code":"01",
    "gn:asciiname":"Nianam I",
    "gn:country_code":"GA",
    "gn:dem":20,
    "gn:feature_class":"P",
    "gn:feature_code":"PPL",
    "gn:name":"Nianam I",
    "gn:population":0,
    "gn:timezone":"Africa/Libreville",
    "iso:country":"GA",
    "wof:name":"Nianam I",
    "wof:placetype":"locality"
},
  "geometry": {"coordinates":[9.57547,0.9294],"type":"Point"}
}