{
  "type": "Feature",
  "properties": {
    "gn:admin1_code":"09",
    "gn:asciiname":"Mfoul",
    "gn:country_code":"GA",
    "gn:dem":615,
    "gn:feature_class":"P",
    "gn:feature_code":"PPL",
    "gn:name":"Mfoul",
    "gn:population":0,
    "gn:timezone":"Africa/Libreville",
    "iso:country":"GA",
    "wof:name":"Mfoul",
    "wof:placetype":"locality"
},
  "geometry": {"coordinates":[11.85347,1.85256],"type":"Point"}
}