{
  "type": "Feature",
  "properties": {
    "gn:admin1_code":"09",
    "gn:asciiname":"Akineyon",
    "gn:country_code":"GA",
    "gn:dem":561,
    "gn:feature_class":"P",
    "gn:feature_code":"PPL",
    "gn:name":"Akineyon",
    "gn:population":0,
    "gn:timezone":"Africa/Libreville",
    "iso:country":"GA",
    "wof:name":"Akineyon",
    "wof:placetype":"locality"
},
  "geometry": {"coordinates":[11.23333,0.61667],"type":"Point"}
}