{
  "type": "Feature",
  "properties": {
    "gn:admin1_code":"02",
    "gn:asciiname":"Engoumou",
    "gn:country_code":"GA",
    "gn:dem":411,
    "gn:feature_class":"P",
    "gn:feature_code":"PPL",
    "gn:name":"Engoumou",
    "gn:population":0,
    "gn:timezone":"Africa/Libreville",
    "iso:country":"GA",
    "wof:name":"Engoumou",
    "wof:placetype":"locality"
},
  "geometry": {"coordinates":[13.7312,-0.6883],"type":"Point"}
}