{
  "type": "Feature",
  "properties": {
    "gn:admin1_code":"07",
    "gn:asciiname":"Mandji",
    "gn:country_code":"GA",
    "gn:dem":330,
    "gn:feature_class":"P",
    "gn:feature_code":"PPL",
    "gn:name":"Mandji",
    "gn:population":0,
    "gn:timezone":"Africa/Libreville",
    "iso:country":"GA",
    "wof:name":"Mandji",
    "wof:placetype":"locality"
},
  "geometry": {"coordinates":[11.89022,-0.9898],"type":"Point"}
}