{
  "type": "Feature",
  "properties": {
    "gn:admin1_code":"03",
    "gn:asciiname":"Grand Village",
    "gn:country_code":"GA",
    "gn:dem":167,
    "gn:feature_class":"P",
    "gn:feature_code":"PPL",
    "gn:name":"Grand Village",
    "gn:population":0,
    "gn:timezone":"Africa/Libreville",
    "iso:country":"GA",
    "wof:name":"Grand Village",
    "wof:placetype":"locality"
},
  "geometry": {"coordinates":[10.75,-0.16667],"type":"Point"}
}