{
  "type": "Feature",
  "properties": {
    "gn:admin1_code":"08",
    "gn:asciiname":"Akoumounou",
    "gn:country_code":"GA",
    "gn:dem":25,
    "gn:feature_class":"P",
    "gn:feature_code":"PPL",
    "gn:name":"Akoumounou",
    "gn:population":0,
    "gn:timezone":"Africa/Libreville",
    "iso:country":"GA",
    "wof:name":"Akoumounou",
    "wof:placetype":"locality"
},
  "geometry": {"coordinates":[9.35,-1.66667],"type":"Point"}
}