{
  "type": "Feature",
  "properties": {
    "gn:admin1_code":"02",
    "gn:asciiname":"Oyouma",
    "gn:country_code":"GA",
    "gn:dem":294,
    "gn:feature_class":"P",
    "gn:feature_code":"PPL",
    "gn:name":"Oyouma",
    "gn:population":0,
    "gn:timezone":"Africa/Libreville",
    "iso:country":"GA",
    "name:und_x_variant":[
        "Oyoma",
        "Oyouma"
    ],
    "wof:name":"Oyouma",
    "wof:placetype":"locality"
},
  "geometry": {"coordinates":[13.61146,-1.62766],"type":"Point"}
}