{
  "type": "Feature",
  "properties": {
    "gn:admin1_code":"07",
    "gn:asciiname":"Bivinde",
    "gn:country_code":"GA",
    "gn:dem":480,
    "gn:feature_class":"P",
    "gn:feature_code":"PPL",
    "gn:name":"Bivind\u00e9",
    "gn:population":0,
    "gn:timezone":"Africa/Libreville",
    "iso:country":"GA",
    "wof:name":"Bivinde",
    "wof:placetype":"locality"
},
  "geometry": {"coordinates":[12.18333,-1.16667],"type":"Point"}
}