{
  "type": "Feature",
  "properties": {
    "gn:admin1_code":"07",
    "gn:asciiname":"Idiba",
    "gn:country_code":"GA",
    "gn:dem":528,
    "gn:feature_class":"P",
    "gn:feature_code":"PPL",
    "gn:name":"Idiba",
    "gn:population":0,
    "gn:timezone":"Africa/Libreville",
    "iso:country":"GA",
    "wof:name":"Idiba",
    "wof:placetype":"locality"
},
  "geometry": {"coordinates":[12.96905,-1.1854],"type":"Point"}
}