{
  "type": "Feature",
  "properties": {
    "gn:admin1_code":"06",
    "gn:asciiname":"Mbomao",
    "gn:country_code":"GA",
    "gn:dem":310,
    "gn:feature_class":"P",
    "gn:feature_code":"PPL",
    "gn:name":"Mbomao",
    "gn:population":0,
    "gn:timezone":"Africa/Libreville",
    "iso:country":"GA",
    "wof:name":"Mbomao",
    "wof:placetype":"locality"
},
  "geometry": {"coordinates":[11.4901,0.33425],"type":"Point"}
}