{
  "type": "Feature",
  "properties": {
    "gn:admin1_code":"08",
    "gn:asciiname":"Allego",
    "gn:country_code":"GA",
    "gn:dem":5,
    "gn:feature_class":"P",
    "gn:feature_code":"PPL",
    "gn:name":"Allego",
    "gn:population":0,
    "gn:timezone":"Africa/Libreville",
    "iso:country":"GA",
    "wof:name":"Allego",
    "wof:placetype":"locality"
},
  "geometry": {"coordinates":[9.6506,-0.81378],"type":"Point"}
}