{
  "type": "Feature",
  "properties": {
    "gn:admin1_code":"09",
    "gn:asciiname":"Messang",
    "gn:country_code":"GA",
    "gn:dem":585,
    "gn:feature_class":"P",
    "gn:feature_code":"PPL",
    "gn:name":"Messang",
    "gn:population":0,
    "gn:timezone":"Africa/Libreville",
    "iso:country":"GA",
    "wof:name":"Messang",
    "wof:placetype":"locality"
},
  "geometry": {"coordinates":[11.41008,2.06815],"type":"Point"}
}