{
  "type": "Feature",
  "properties": {
    "gn:admin1_code":"07",
    "gn:asciiname":"Mbigou",
    "gn:country_code":"GA",
    "gn:dem":342,
    "gn:feature_class":"P",
    "gn:feature_code":"PPL",
    "gn:name":"Mbigou",
    "gn:population":0,
    "gn:timezone":"Africa/Libreville",
    "iso:country":"GA",
    "name:und_x_variant":[
        "Mbighou",
        "Mbigou"
    ],
    "wof:name":"Mbigou",
    "wof:placetype":"locality"
},
  "geometry": {"coordinates":[12.37886,-1.41351],"type":"Point"}
}