{
  "type": "Feature",
  "properties": {
    "gn:admin1_code":"06",
    "gn:asciiname":"Yeng",
    "gn:country_code":"GA",
    "gn:dem":332,
    "gn:feature_class":"P",
    "gn:feature_code":"PPL",
    "gn:name":"Yeng",
    "gn:population":0,
    "gn:timezone":"Africa/Libreville",
    "iso:country":"GA",
    "wof:name":"Yeng",
    "wof:placetype":"locality"
},
  "geometry": {"coordinates":[11.60618,0.3252],"type":"Point"}
}