{
  "type": "Feature",
  "properties": {
    "gn:admin1_code":"09",
    "gn:asciiname":"Ouol",
    "gn:country_code":"GA",
    "gn:dem":562,
    "gn:feature_class":"P",
    "gn:feature_code":"PPL",
    "gn:name":"Ouol",
    "gn:population":0,
    "gn:timezone":"Africa/Libreville",
    "iso:country":"GA",
    "wof:name":"Ouol",
    "wof:placetype":"locality"
},
  "geometry": {"coordinates":[11.21163,0.96539],"type":"Point"}
}