{
  "type": "Feature",
  "properties": {
    "gn:admin1_code":"06",
    "gn:asciiname":"Mbeza",
    "gn:country_code":"GA",
    "gn:dem":514,
    "gn:feature_class":"P",
    "gn:feature_code":"PPL",
    "gn:name":"Mb\u00e9za",
    "gn:population":0,
    "gn:timezone":"Africa/Libreville",
    "iso:country":"GA",
    "wof:name":"Mbeza",
    "wof:placetype":"locality"
},
  "geometry": {"coordinates":[12.91047,0.58801],"type":"Point"}
}