{
  "type": "Feature",
  "properties": {
    "gn:admin1_code":"05",
    "gn:asciiname":"Tchitende",
    "gn:country_code":"GA",
    "gn:dem":66,
    "gn:feature_class":"P",
    "gn:feature_code":"PPL",
    "gn:name":"Tchitend\u00e9",
    "gn:population":0,
    "gn:timezone":"Africa/Libreville",
    "iso:country":"GA",
    "name:und_x_variant":[
        "Tchibenda",
        "Tchitend\u00e9"
    ],
    "wof:name":"Tchitende",
    "wof:placetype":"locality"
},
  "geometry": {"coordinates":[11.13824,-3.89774],"type":"Point"}
}