{
  "type": "Feature",
  "properties": {
    "gn:admin1_code":"02",
    "gn:asciiname":"Ekoungou",
    "gn:country_code":"GA",
    "gn:dem":476,
    "gn:feature_class":"P",
    "gn:feature_code":"PPL",
    "gn:name":"Ekoungou",
    "gn:population":0,
    "gn:timezone":"Africa/Libreville",
    "iso:country":"GA",
    "name:und_x_variant":[
        "Okoungou",
        "Ekoungou"
    ],
    "wof:name":"Ekoungou",
    "wof:placetype":"locality"
},
  "geometry": {"coordinates":[13.69621,-1.30954],"type":"Point"}
}