{
  "type": "Feature",
  "properties": {
    "gn:admin1_code":"04",
    "gn:asciiname":"Ilelo",
    "gn:country_code":"GA",
    "gn:dem":143,
    "gn:feature_class":"P",
    "gn:feature_code":"PPL",
    "gn:name":"Ilelo",
    "gn:population":0,
    "gn:timezone":"Africa/Libreville",
    "iso:country":"GA",
    "wof:name":"Ilelo",
    "wof:placetype":"locality"
},
  "geometry": {"coordinates":[11.33333,-2.45],"type":"Point"}
}