{
  "type": "Feature",
  "properties": {
    "gn:admin1_code":"03",
    "gn:asciiname":"Nkenga-Mbya",
    "gn:country_code":"GA",
    "gn:dem":16,
    "gn:feature_class":"P",
    "gn:feature_code":"PPL",
    "gn:name":"Nkenga-Mbya",
    "gn:population":0,
    "gn:timezone":"Africa/Libreville",
    "iso:country":"GA",
    "wof:name":"Nkenga-Mbya",
    "wof:placetype":"locality"
},
  "geometry": {"coordinates":[10.03333,-0.98333],"type":"Point"}
}