{
  "type": "Feature",
  "properties": {
    "gn:admin1_code":"09",
    "gn:asciiname":"Minkebe",
    "gn:country_code":"GA",
    "gn:dem":656,
    "gn:feature_class":"P",
    "gn:feature_code":"PPL",
    "gn:name":"Mink\u00e9b\u00e9",
    "gn:population":0,
    "gn:timezone":"Africa/Libreville",
    "iso:country":"GA",
    "wof:name":"Minkebe",
    "wof:placetype":"locality"
},
  "geometry": {"coordinates":[12.85007,1.74525],"type":"Point"}
}