{
  "type": "Feature",
  "properties": {
    "gn:admin1_code":"09",
    "gn:asciiname":"Doumanzo",
    "gn:country_code":"GA",
    "gn:dem":492,
    "gn:feature_class":"P",
    "gn:feature_code":"PPL",
    "gn:name":"Doumanzo",
    "gn:population":0,
    "gn:timezone":"Africa/Libreville",
    "iso:country":"GA",
    "wof:name":"Doumanzo",
    "wof:placetype":"locality"
},
  "geometry": {"coordinates":[11.08333,0.63333],"type":"Point"}
}