{
  "type": "Feature",
  "properties": {
    "gn:admin1_code":"04",
    "gn:asciiname":"Fouelou",
    "gn:country_code":"GA",
    "gn:dem":124,
    "gn:feature_class":"P",
    "gn:feature_code":"PPL",
    "gn:name":"Fouelou",
    "gn:population":0,
    "gn:timezone":"Africa/Libreville",
    "iso:country":"GA",
    "wof:name":"Fouelou",
    "wof:placetype":"locality"
},
  "geometry": {"coordinates":[11.11667,-2.18333],"type":"Point"}
}