{
  "type": "Feature",
  "properties": {
    "gn:admin1_code":"07",
    "gn:asciiname":"Koubala",
    "gn:country_code":"GA",
    "gn:dem":489,
    "gn:feature_class":"P",
    "gn:feature_code":"PPL",
    "gn:name":"Koubala",
    "gn:population":0,
    "gn:timezone":"Africa/Libreville",
    "iso:country":"GA",
    "wof:name":"Koubala",
    "wof:placetype":"locality"
},
  "geometry": {"coordinates":[12.23333,-1.36667],"type":"Point"}
}