{
  "type": "Feature",
  "properties": {
    "gn:admin1_code":"04",
    "gn:asciiname":"Tchengue",
    "gn:country_code":"GA",
    "gn:dem":734,
    "gn:feature_class":"P",
    "gn:feature_code":"PPL",
    "gn:name":"Tchengu\u00e9",
    "gn:population":0,
    "gn:timezone":"Africa/Libreville",
    "iso:country":"GA",
    "wof:name":"Tchengue",
    "wof:placetype":"locality"
},
  "geometry": {"coordinates":[11.98333,-1.65],"type":"Point"}
}