{
  "type": "Feature",
  "properties": {
    "gn:admin1_code":"04",
    "gn:asciiname":"Mandji-Kili",
    "gn:country_code":"GA",
    "gn:dem":134,
    "gn:feature_class":"P",
    "gn:feature_code":"PPL",
    "gn:name":"Mandji-Kili",
    "gn:population":0,
    "gn:timezone":"Africa/Libreville",
    "iso:country":"GA",
    "wof:name":"Mandji-Kili",
    "wof:placetype":"locality"
},
  "geometry": {"coordinates":[10.34956,-1.57981],"type":"Point"}
}