{
  "type": "Feature",
  "properties": {
    "gn:admin1_code":"05",
    "gn:asciiname":"Tsogni",
    "gn:country_code":"GA",
    "gn:dem":40,
    "gn:feature_class":"P",
    "gn:feature_code":"PPL",
    "gn:name":"Tsogni",
    "gn:population":0,
    "gn:timezone":"Africa/Libreville",
    "iso:country":"GA",
    "name:ceb_x_preferred":[
        "Tsogni"
    ],
    "name:deu_x_preferred":[
        "Tsogni"
    ],
    "name:fra_x_preferred":[
        "Tsogni"
    ],
    "name:ita_x_preferred":[
        "Tsogni"
    ],
    "name:pol_x_preferred":[
        "Tsogni"
    ],
    "name:rus_x_preferred":[
        "\u0422\u0441\u043e\u0433\u043d\u0438"
    ],
    "name:swe_x_preferred":[
        "Tsogni"
    ],
    "name:und_x_variant":[
        "Isogni"
    ],
    "wof:name":"Tsogni",
    "wof:placetype":"locality"
},
  "geometry": {"coordinates":[10.16058,-2.80365],"type":"Point"}
}