{
  "type": "Feature",
  "properties": {
    "gn:admin1_code":"05",
    "gn:asciiname":"Tsogni",
    "gn:country_code":"GA",
    "gn:dem":40,
    "gn:feature_class":"P",
    "gn:feature_code":"PPL",
    "gn:name":"Tsogni",
    "gn:population":0,
    "gn:timezone":"Africa/Libreville",
    "iso:country":"GA",
    "name:und_x_variant":[
        "Isogni",
        "Tsogni"
    ],
    "wof:name":"Tsogni",
    "wof:placetype":"locality"
},
  "geometry": {"coordinates":[10.16058,-2.80365],"type":"Point"}
}