{
  "type": "Feature",
  "properties": {
    "gn:admin1_code":"07",
    "gn:asciiname":"Doume",
    "gn:country_code":"GA",
    "gn:dem":261,
    "gn:feature_class":"P",
    "gn:feature_code":"PPL",
    "gn:name":"Doum\u00e9",
    "gn:population":0,
    "gn:timezone":"Africa/Libreville",
    "iso:country":"GA",
    "wof:name":"Doume",
    "wof:placetype":"locality"
},
  "geometry": {"coordinates":[12.96298,-0.84642],"type":"Point"}
}