{
  "type": "Feature",
  "properties": {
    "gn:admin1_code":"09",
    "gn:asciiname":"Febezok",
    "gn:country_code":"GA",
    "gn:dem":725,
    "gn:feature_class":"P",
    "gn:feature_code":"PPL",
    "gn:name":"F\u00e9bezok",
    "gn:population":0,
    "gn:timezone":"Africa/Libreville",
    "iso:country":"GA",
    "wof:name":"Febezok",
    "wof:placetype":"locality"
},
  "geometry": {"coordinates":[11.82942,1.5424],"type":"Point"}
}