{
  "type": "Feature",
  "properties": {
    "gn:admin1_code":"04",
    "gn:asciiname":"Mamboungou",
    "gn:country_code":"GA",
    "gn:dem":740,
    "gn:feature_class":"P",
    "gn:feature_code":"PPL",
    "gn:name":"Mamboungou",
    "gn:population":0,
    "gn:timezone":"Africa/Libreville",
    "iso:country":"GA",
    "wof:name":"Mamboungou",
    "wof:placetype":"locality"
},
  "geometry": {"coordinates":[11.93333,-1.93333],"type":"Point"}
}