{
  "type": "Feature",
  "properties": {
    "gn:admin1_code":"04",
    "gn:asciiname":"Dibotinefata",
    "gn:country_code":"GA",
    "gn:dem":46,
    "gn:feature_class":"P",
    "gn:feature_code":"PPL",
    "gn:name":"Dibotin\u00e9fata",
    "gn:population":0,
    "gn:timezone":"Africa/Libreville",
    "iso:country":"GA",
    "wof:name":"Dibotinefata",
    "wof:placetype":"locality"
},
  "geometry": {"coordinates":[9.96461,-1.61049],"type":"Point"}
}