{
  "type": "Feature",
  "properties": {
    "gn:admin1_code":"01",
    "gn:asciiname":"Akounilen",
    "gn:country_code":"GA",
    "gn:dem":15,
    "gn:feature_class":"P",
    "gn:feature_code":"PPL",
    "gn:name":"Akounilen",
    "gn:population":0,
    "gn:timezone":"Africa/Libreville",
    "iso:country":"GA",
    "name:und_x_variant":[
        "Akolinem",
        "Akoulinem",
        "Akonilen",
        "Akounilem",
        "Akounilen"
    ],
    "wof:name":"Akounilen",
    "wof:placetype":"locality"
},
  "geometry": {"coordinates":[9.92433,0.79275],"type":"Point"}
}