{
  "type": "Feature",
  "properties": {
    "gn:admin1_code":"04",
    "gn:asciiname":"Ngondzi",
    "gn:country_code":"GA",
    "gn:dem":117,
    "gn:feature_class":"P",
    "gn:feature_code":"PPL",
    "gn:name":"Ngondzi",
    "gn:population":0,
    "gn:timezone":"Africa/Libreville",
    "iso:country":"GA",
    "wof:name":"Ngondzi",
    "wof:placetype":"locality"
},
  "geometry": {"coordinates":[11.45,-2.26667],"type":"Point"}
}