{
  "type": "Feature",
  "properties": {
    "gn:admin1_code":"05",
    "gn:asciiname":"Djema",
    "gn:country_code":"GA",
    "gn:dem":21,
    "gn:feature_class":"P",
    "gn:feature_code":"PPL",
    "gn:name":"Djema",
    "gn:population":0,
    "gn:timezone":"Africa/Libreville",
    "iso:country":"GA",
    "name:und_x_variant":[
        "Dj\u00e9mba",
        "Djema"
    ],
    "wof:name":"Djema",
    "wof:placetype":"locality"
},
  "geometry": {"coordinates":[10.35536,-2.93706],"type":"Point"}
}