{
  "type": "Feature",
  "properties": {
    "gn:admin1_code":"01",
    "gn:asciiname":"Kougouleu",
    "gn:country_code":"GA",
    "gn:dem":38,
    "gn:feature_class":"P",
    "gn:feature_code":"PPL",
    "gn:name":"Kougouleu",
    "gn:population":0,
    "gn:timezone":"Africa/Libreville",
    "iso:country":"GA",
    "name:fra_x_preferred":[
        "Kougouleu"
    ],
    "name:und_x_variant":[
        "Kougoul\u00e9"
    ],
    "wof:name":"Kougouleu",
    "wof:placetype":"locality"
},
  "geometry": {"coordinates":[9.89032,0.40364],"type":"Point"}
}