{
  "type": "Feature",
  "properties": {
    "gn:admin1_code":"01",
    "gn:asciiname":"Idokogo",
    "gn:country_code":"GA",
    "gn:dem":-9999,
    "gn:feature_class":"P",
    "gn:feature_code":"PPL",
    "gn:name":"Idokogo",
    "gn:population":0,
    "gn:timezone":"Africa/Libreville",
    "iso:country":"GA",
    "wof:name":"Idokogo",
    "wof:placetype":"locality"
},
  "geometry": {"coordinates":[9.30846,0.58141],"type":"Point"}
}