{
  "type": "Feature",
  "properties": {
    "gn:admin1_code":"09",
    "gn:asciiname":"Ekong",
    "gn:country_code":"GA",
    "gn:dem":680,
    "gn:feature_class":"P",
    "gn:feature_code":"PPL",
    "gn:name":"Ekong",
    "gn:population":0,
    "gn:timezone":"Africa/Libreville",
    "iso:country":"GA",
    "wof:name":"Ekong",
    "wof:placetype":"locality"
},
  "geometry": {"coordinates":[11.45231,1.74193],"type":"Point"}
}