{
  "type": "Feature",
  "properties": {
    "gn:admin1_code":"01",
    "gn:asciiname":"Afakma",
    "gn:country_code":"GA",
    "gn:dem":28,
    "gn:feature_class":"P",
    "gn:feature_code":"PPL",
    "gn:name":"Afakma",
    "gn:population":0,
    "gn:timezone":"Africa/Libreville",
    "iso:country":"GA",
    "wof:name":"Afakma",
    "wof:placetype":"locality"
},
  "geometry": {"coordinates":[9.96667,-0.01667],"type":"Point"}
}