{
  "type": "Feature",
  "properties": {
    "iso:country":"GA",
    "name:ceb_x_preferred":[
        "Ndend\u00e9"
    ],
    "name:eng_x_preferred":[
        "Ndend\u00e9"
    ],
    "name:fra_x_preferred":[
        "Ndend\u00e9"
    ],
    "name:ita_x_preferred":[
        "Ndend\u00e9"
    ],
    "name:jpn_x_preferred":[
        "\u30c9\u30f3\u30c7"
    ],
    "name:lit_x_preferred":[
        "Ndend\u0117"
    ],
    "name:nld_x_preferred":[
        "Ndend\u00e9"
    ],
    "name:pol_x_preferred":[
        "Ndend\u00e9"
    ],
    "name:rus_x_preferred":[
        "\u041d\u0434\u0435\u043d\u0434\u0435"
    ],
    "name:spa_x_preferred":[
        "Ndend\u00e9"
    ],
    "name:swe_x_preferred":[
        "Ndend\u00e9"
    ],
    "name:zho_x_preferred":[
        "\u6069\u4ee3\u6069\u4ee3"
    ],
    "ne:ADM0CAP":0.0,
    "ne:ADM0NAME":"Gabon",
    "ne:ADM0_A3":"GAB",
    "ne:ADM1NAME":"Ngouni\u00e9",
    "ne:ADMIN1_COD":4,
    "ne:CAPALT":0,
    "ne:CHANGED":0,
    "ne:CHECKME":0,
    "ne:COMPARE":0,
    "ne:DIFFASCII":0,
    "ne:ELEVATION":0.0,
    "ne:FEATURECLA":"Populated place",
    "ne:FEATURE_CL":"P",
    "ne:FEATURE_CO":"PPL",
    "ne:GEONAMEID":2397614,
    "ne:GEONAMESNO":"Geonames ascii name + lat.d + long.d matching.",
    "ne:GN_ASCII":"Ndende",
    "ne:GN_POP":6200,
    "ne:GTOPO30":540.0,
    "ne:ISO_A2":"GA",
    "ne:LABELRANK":7,
    "ne:LATITUDE":-2.382918,
    "ne:LONGITUDE":11.383274,
    "ne:LS_MATCH":1,
    "ne:LS_NAME":"Ndende",
    "ne:MAX_AREAKM":3.0,
    "ne:MAX_AREAMI":1.0,
    "ne:MAX_BBXMAX":11.391667,
    "ne:MAX_BBXMIN":11.375,
    "ne:MAX_BBYMAX":-2.366667,
    "ne:MAX_BBYMIN":-2.383333,
    "ne:MAX_NATSCA":20.0,
    "ne:MAX_PERKM":7.0,
    "ne:MAX_PERMI":5.0,
    "ne:MAX_POP10":2002,
    "ne:MAX_POP20":2002,
    "ne:MAX_POP300":0,
    "ne:MAX_POP310":0,
    "ne:MAX_POP50":0,
    "ne:MEAN_BBXC":11.384722,
    "ne:MEAN_BBYC":-2.376389,
    "ne:MEGACITY":0,
    "ne:MIN_AREAKM":3.0,
    "ne:MIN_AREAMI":1.0,
    "ne:MIN_BBXMAX":11.391667,
    "ne:MIN_BBXMIN":11.375,
    "ne:MIN_BBYMAX":-2.366667,
    "ne:MIN_BBYMIN":-2.383333,
    "ne:MIN_PERKM":7.0,
    "ne:MIN_PERMI":5.0,
    "ne:NAME":"Ndende",
    "ne:NAMEASCII":"Ndende",
    "ne:NAMEDIFF":0,
    "ne:NATSCALE":20,
    "ne:POP1950":0,
    "ne:POP1955":0,
    "ne:POP1960":0,
    "ne:POP1965":0,
    "ne:POP1970":0,
    "ne:POP1975":0,
    "ne:POP1980":0,
    "ne:POP1985":0,
    "ne:POP1990":0,
    "ne:POP1995":0,
    "ne:POP2000":0,
    "ne:POP2005":0,
    "ne:POP2010":0,
    "ne:POP2015":0,
    "ne:POP2020":0,
    "ne:POP2025":0,
    "ne:POP2050":0,
    "ne:POP_MAX":6200,
    "ne:POP_MIN":2002,
    "ne:POP_OTHER":2002,
    "ne:RANK_MAX":5,
    "ne:RANK_MIN":4,
    "ne:SCALERANK":7,
    "ne:SOV0NAME":"Gabon",
    "ne:SOV_A3":"GAB",
    "ne:TIMEZONE":"Africa/Libreville",
    "ne:UN_FID":0,
    "ne:UN_LAT":0.0,
    "ne:UN_LONG":0.0,
    "ne:WORLDCITY":0,
    "ne:min_zoom":6.7,
    "wof:name":"Ndende",
    "wof:placetype":"locality"
},
  "geometry": {"coordinates":[11.38327388372204,-2.38291786815717],"type":"Point"}
}