{
  "type": "Feature",
  "properties": {
    "gn:admin1_code":"04",
    "gn:asciiname":"Bouali",
    "gn:country_code":"GA",
    "gn:dem":660,
    "gn:feature_class":"P",
    "gn:feature_code":"PPL",
    "gn:name":"Bouali",
    "gn:population":0,
    "gn:timezone":"Africa/Libreville",
    "iso:country":"GA",
    "wof:name":"Bouali",
    "wof:placetype":"locality"
},
  "geometry": {"coordinates":[11.81667,-1.51667],"type":"Point"}
}