{
  "type": "Feature",
  "properties": {
    "gn:admin1_code":"09",
    "gn:asciiname":"Eyane",
    "gn:country_code":"GA",
    "gn:dem":525,
    "gn:feature_class":"P",
    "gn:feature_code":"PPL",
    "gn:name":"Eyan\u00e9",
    "gn:population":0,
    "gn:timezone":"Africa/Libreville",
    "iso:country":"GA",
    "wof:name":"Eyane",
    "wof:placetype":"locality"
},
  "geometry": {"coordinates":[11.56361,0.85007],"type":"Point"}
}