{
  "type": "Feature",
  "properties": {
    "gn:admin1_code":"02",
    "gn:asciiname":"Mboua",
    "gn:country_code":"GA",
    "gn:dem":524,
    "gn:feature_class":"P",
    "gn:feature_code":"PPL",
    "gn:name":"Mboua",
    "gn:population":0,
    "gn:timezone":"Africa/Libreville",
    "iso:country":"GA",
    "wof:name":"Mboua",
    "wof:placetype":"locality"
},
  "geometry": {"coordinates":[13.72818,-2.13566],"type":"Point"}
}