{
  "type": "Feature",
  "properties": {
    "gn:admin1_code":"01",
    "gn:asciiname":"Massai",
    "gn:country_code":"GA",
    "gn:dem":22,
    "gn:feature_class":"P",
    "gn:feature_code":"PPL",
    "gn:name":"Massa\u00ef",
    "gn:population":0,
    "gn:timezone":"Africa/Libreville",
    "iso:country":"GA",
    "name:deu_x_preferred":[
        "Massai"
    ],
    "wof:name":"Massai",
    "wof:placetype":"locality"
},
  "geometry": {"coordinates":[9.77826,0.97593],"type":"Point"}
}