{
  "type": "Feature",
  "properties": {
    "gn:admin1_code":"07",
    "gn:asciiname":"Mouvangue",
    "gn:country_code":"GA",
    "gn:dem":579,
    "gn:feature_class":"P",
    "gn:feature_code":"PPL",
    "gn:name":"Mouvangu\u00e9",
    "gn:population":0,
    "gn:timezone":"Africa/Libreville",
    "iso:country":"GA",
    "name:und_x_variant":[
        "Mouvengu\u00e9",
        "Mouvangu\u00e9"
    ],
    "wof:name":"Mouvangue",
    "wof:placetype":"locality"
},
  "geometry": {"coordinates":[12.61911,-1.61847],"type":"Point"}
}