{
  "type": "Feature",
  "properties": {
    "gn:admin1_code":"06",
    "gn:asciiname":"Achouka",
    "gn:country_code":"GA",
    "gn:dem":150,
    "gn:feature_class":"P",
    "gn:feature_code":"PPL",
    "gn:name":"Achouka",
    "gn:population":0,
    "gn:timezone":"Africa/Libreville",
    "iso:country":"GA",
    "name:und_x_variant":[
        "Aschouka",
        "Achouka"
    ],
    "wof:name":"Achouka",
    "wof:placetype":"locality"
},
  "geometry": {"coordinates":[11.77921,-0.09595],"type":"Point"}
}