{
  "type": "Feature",
  "properties": {
    "gn:admin1_code":"09",
    "gn:asciiname":"Avo",
    "gn:country_code":"GA",
    "gn:dem":573,
    "gn:feature_class":"P",
    "gn:feature_code":"PPL",
    "gn:name":"Avo",
    "gn:population":0,
    "gn:timezone":"Africa/Libreville",
    "iso:country":"GA",
    "wof:name":"Avo",
    "wof:placetype":"locality"
},
  "geometry": {"coordinates":[11.4621,1.10806],"type":"Point"}
}