{
  "type": "Feature",
  "properties": {
    "gn:admin1_code":"09",
    "gn:asciiname":"Ossas",
    "gn:country_code":"GA",
    "gn:dem":693,
    "gn:feature_class":"P",
    "gn:feature_code":"PPL",
    "gn:name":"Ossas",
    "gn:population":0,
    "gn:timezone":"Africa/Libreville",
    "iso:country":"GA",
    "wof:name":"Ossas",
    "wof:placetype":"locality"
},
  "geometry": {"coordinates":[11.41667,1.33333],"type":"Point"}
}