{
  "type": "Feature",
  "properties": {
    "gn:admin1_code":"04",
    "gn:asciiname":"Dianza",
    "gn:country_code":"GA",
    "gn:dem":684,
    "gn:feature_class":"P",
    "gn:feature_code":"PPL",
    "gn:name":"Dianza",
    "gn:population":0,
    "gn:timezone":"Africa/Libreville",
    "iso:country":"GA",
    "name:und_x_variant":[
        "Dyanza",
        "Dianza"
    ],
    "wof:name":"Dianza",
    "wof:placetype":"locality"
},
  "geometry": {"coordinates":[12.45445,-2.3082],"type":"Point"}
}