{
  "type": "Feature",
  "properties": {
    "gn:admin1_code":"06",
    "gn:asciiname":"Bengiyoe",
    "gn:country_code":"GA",
    "gn:dem":509,
    "gn:feature_class":"P",
    "gn:feature_code":"PPL",
    "gn:name":"Bengiyoe",
    "gn:population":0,
    "gn:timezone":"Africa/Libreville",
    "iso:country":"GA",
    "wof:name":"Bengiyoe",
    "wof:placetype":"locality"
},
  "geometry": {"coordinates":[12.68333,0.65],"type":"Point"}
}