{
  "type": "Feature",
  "properties": {
    "gn:admin1_code":"04",
    "gn:asciiname":"Pegny-Sampana",
    "gn:country_code":"GA",
    "gn:dem":359,
    "gn:feature_class":"P",
    "gn:feature_code":"PPL",
    "gn:name":"Pegny-Sampana",
    "gn:population":0,
    "gn:timezone":"Africa/Libreville",
    "iso:country":"GA",
    "wof:name":"Pegny-Sampana",
    "wof:placetype":"locality"
},
  "geometry": {"coordinates":[10.81936,-2.04202],"type":"Point"}
}