{
  "type": "Feature",
  "properties": {
    "gn:admin1_code":"03",
    "gn:asciiname":"Mfoume",
    "gn:country_code":"GA",
    "gn:dem":97,
    "gn:feature_class":"P",
    "gn:feature_code":"PPL",
    "gn:name":"Mfoum\u00e9",
    "gn:population":0,
    "gn:timezone":"Africa/Libreville",
    "iso:country":"GA",
    "wof:name":"Mfoume",
    "wof:placetype":"locality"
},
  "geometry": {"coordinates":[10.71667,-0.18333],"type":"Point"}
}