{
  "type": "Feature",
  "properties": {
    "gn:admin1_code":"04",
    "gn:asciiname":"Mahounga",
    "gn:country_code":"GA",
    "gn:dem":131,
    "gn:feature_class":"P",
    "gn:feature_code":"PPL",
    "gn:name":"Mahounga",
    "gn:population":0,
    "gn:timezone":"Africa/Libreville",
    "iso:country":"GA",
    "wof:name":"Mahounga",
    "wof:placetype":"locality"
},
  "geometry": {"coordinates":[11.33333,-2.33333],"type":"Point"}
}