{
  "type": "Feature",
  "properties": {
    "gn:admin1_code":"03",
    "gn:asciiname":"Fernan Vaz",
    "gn:country_code":"GA",
    "gn:dem":42,
    "gn:feature_class":"P",
    "gn:feature_code":"PPL",
    "gn:name":"Fernan Vaz",
    "gn:population":0,
    "gn:timezone":"Africa/Libreville",
    "iso:country":"GA",
    "wof:name":"Fernan Vaz",
    "wof:placetype":"locality"
},
  "geometry": {"coordinates":[10.46241,-0.41835],"type":"Point"}
}