{
  "type": "Feature",
  "properties": {
    "gn:admin1_code":"03",
    "gn:asciiname":"Matoulou",
    "gn:country_code":"GA",
    "gn:dem":58,
    "gn:feature_class":"P",
    "gn:feature_code":"PPL",
    "gn:name":"Matoulou",
    "gn:population":0,
    "gn:timezone":"Africa/Libreville",
    "iso:country":"GA",
    "wof:name":"Matoulou",
    "wof:placetype":"locality"
},
  "geometry": {"coordinates":[10.53333,-0.25],"type":"Point"}
}