{
  "type": "Feature",
  "properties": {
    "gn:admin1_code":"09",
    "gn:asciiname":"Ngo",
    "gn:country_code":"GA",
    "gn:dem":627,
    "gn:feature_class":"P",
    "gn:feature_code":"PPL",
    "gn:name":"Ngo",
    "gn:population":0,
    "gn:timezone":"Africa/Libreville",
    "iso:country":"GA",
    "wof:name":"Ngo",
    "wof:placetype":"locality"
},
  "geometry": {"coordinates":[11.85,1.88333],"type":"Point"}
}