{
  "type": "Feature",
  "properties": {
    "gn:admin1_code":"04",
    "gn:asciiname":"Ikoya",
    "gn:country_code":"GA",
    "gn:dem":320,
    "gn:feature_class":"P",
    "gn:feature_code":"PPL",
    "gn:name":"Ikoya",
    "gn:population":0,
    "gn:timezone":"Africa/Libreville",
    "iso:country":"GA",
    "wof:name":"Ikoya",
    "wof:placetype":"locality"
},
  "geometry": {"coordinates":[11.58333,-2.21667],"type":"Point"}
}