{
  "type": "Feature",
  "properties": {
    "gn:admin1_code":"02",
    "gn:asciiname":"Messami I",
    "gn:country_code":"GA",
    "gn:dem":527,
    "gn:feature_class":"P",
    "gn:feature_code":"PPL",
    "gn:name":"Messami I",
    "gn:population":0,
    "gn:timezone":"Africa/Libreville",
    "iso:country":"GA",
    "wof:name":"Messami I",
    "wof:placetype":"locality"
},
  "geometry": {"coordinates":[13.6947,-2.15953],"type":"Point"}
}