{
  "type": "Feature",
  "properties": {
    "gn:admin1_code":"03",
    "gn:asciiname":"Ayambi",
    "gn:country_code":"GA",
    "gn:dem":59,
    "gn:feature_class":"P",
    "gn:feature_code":"PPL",
    "gn:name":"Ayambi",
    "gn:population":0,
    "gn:timezone":"Africa/Libreville",
    "iso:country":"GA",
    "wof:name":"Ayambi",
    "wof:placetype":"locality"
},
  "geometry": {"coordinates":[10.51667,-0.26667],"type":"Point"}
}