{
  "type": "Feature",
  "properties": {
    "gn:admin1_code":"01",
    "gn:asciiname":"Andem",
    "gn:country_code":"GA",
    "gn:dem":27,
    "gn:feature_class":"P",
    "gn:feature_code":"PPL",
    "gn:name":"Andem",
    "gn:population":0,
    "gn:timezone":"Africa/Libreville",
    "iso:country":"GA",
    "name:fas_x_preferred":[
        "\u0627\u0646\u062f\u06cc\u0645"
    ],
    "wof:name":"Andem",
    "wof:placetype":"locality"
},
  "geometry": {"coordinates":[9.96536,0.32291],"type":"Point"}
}