{
  "type": "Feature",
  "properties": {
    "gn:admin1_code":"04",
    "gn:asciiname":"Boungoumana",
    "gn:country_code":"GA",
    "gn:dem":506,
    "gn:feature_class":"P",
    "gn:feature_code":"PPL",
    "gn:name":"Boungoumana",
    "gn:population":0,
    "gn:timezone":"Africa/Libreville",
    "iso:country":"GA",
    "wof:name":"Boungoumana",
    "wof:placetype":"locality"
},
  "geometry": {"coordinates":[11.73333,-2.16667],"type":"Point"}
}