{
  "type": "Feature",
  "properties": {
    "gn:admin1_code":"09",
    "gn:asciiname":"Nyamegong",
    "gn:country_code":"GA",
    "gn:dem":603,
    "gn:feature_class":"P",
    "gn:feature_code":"PPL",
    "gn:name":"Nyamegong",
    "gn:population":0,
    "gn:timezone":"Africa/Libreville",
    "iso:country":"GA",
    "wof:name":"Nyamegong",
    "wof:placetype":"locality"
},
  "geometry": {"coordinates":[11.56667,1.75],"type":"Point"}
}