{
  "type": "Feature",
  "properties": {
    "gn:admin1_code":"01",
    "gn:asciiname":"Medegue",
    "gn:country_code":"GA",
    "gn:dem":79,
    "gn:feature_class":"P",
    "gn:feature_code":"PPL",
    "gn:name":"M\u00e9d\u00e9gu\u00e9",
    "gn:population":0,
    "gn:timezone":"Africa/Libreville",
    "iso:country":"GA",
    "wof:name":"Medegue",
    "wof:placetype":"locality"
},
  "geometry": {"coordinates":[10.12621,0.61429],"type":"Point"}
}