{
  "type": "Feature",
  "properties": {
    "gn:admin1_code":"05",
    "gn:asciiname":"Louango",
    "gn:country_code":"GA",
    "gn:dem":248,
    "gn:feature_class":"P",
    "gn:feature_code":"PPL",
    "gn:name":"Louango",
    "gn:population":0,
    "gn:timezone":"Africa/Libreville",
    "iso:country":"GA",
    "wof:name":"Louango",
    "wof:placetype":"locality"
},
  "geometry": {"coordinates":[10.91935,-2.64767],"type":"Point"}
}