{
  "type": "Feature",
  "properties": {
    "gn:country":"GA",
    "gn:fcode":"PPL",
    "gn:population":8569,
    "iso:country":"GA",
    "name:ces_x_preferred":[
        "Ntoum"
    ],
    "name:eng_x_preferred":[
        "Ntoum"
    ],
    "name:fra_x_preferred":[
        "Ntoum"
    ],
    "name:ita_x_preferred":[
        "Ntoum"
    ],
    "name:jpn_x_preferred":[
        "\u30f3\u30c8\u30a5\u30e0"
    ],
    "name:nld_x_preferred":[
        "Ntoum"
    ],
    "name:pol_x_preferred":[
        "Ntoum"
    ],
    "name:por_x_preferred":[
        "Ntoum"
    ],
    "name:ron_x_preferred":[
        "Ntoum"
    ],
    "name:rus_x_preferred":[
        "\u041d\u0442\u0443\u043c"
    ],
    "qs:name":"Ntoum",
    "qs:photos_9r":0,
    "qs:photos_sr":0,
    "qs:pop_sr":"5",
    "wd:wordcount":153,
    "wof:name":"Ntoum",
    "wof:placetype":"locality",
    "wof:population":8569
},
  "geometry": {"coordinates":[9.78333,0.38333],"type":"Point"}
}