{
  "type": "Feature",
  "properties": {
    "gn:country":"GA",
    "gn:fcode":"PPL",
    "gn:pop":8569,
    "iso:country":"GA",
    "qs:name":"Ntoum",
    "qs:photos_9r":0,
    "qs:photos_sr":0,
    "qs:pop_sr":"5",
    "wd:wordcount":153,
    "wof:name":"Ntoum",
    "wof:placetype":"locality",
    "wof:population":8569
},
  "geometry": {"coordinates":[9.78333,0.38333],"type":"Point"}
}