{
  "type": "Feature",
  "properties": {
    "gn:admin1_code":"03",
    "gn:asciiname":"Diboussou",
    "gn:country_code":"GA",
    "gn:dem":28,
    "gn:feature_class":"P",
    "gn:feature_code":"PPL",
    "gn:name":"Diboussou",
    "gn:population":0,
    "gn:timezone":"Africa/Libreville",
    "iso:country":"GA",
    "wof:name":"Diboussou",
    "wof:placetype":"locality"
},
  "geometry": {"coordinates":[10.2431,-0.99275],"type":"Point"}
}