{
  "type": "Feature",
  "properties": {
    "gn:admin1_code":"04",
    "gn:asciiname":"Meli",
    "gn:country_code":"GA",
    "gn:dem":136,
    "gn:feature_class":"P",
    "gn:feature_code":"PPL",
    "gn:name":"M\u00e8li",
    "gn:population":0,
    "gn:timezone":"Africa/Libreville",
    "iso:country":"GA",
    "wof:name":"Meli",
    "wof:placetype":"locality"
},
  "geometry": {"coordinates":[10.39064,-1.67836],"type":"Point"}
}