{
  "type": "Feature",
  "properties": {
    "gn:admin1_code":"04",
    "gn:asciiname":"Moukouagna",
    "gn:country_code":"GA",
    "gn:dem":745,
    "gn:feature_class":"P",
    "gn:feature_code":"PPL",
    "gn:name":"Moukouagna",
    "gn:population":0,
    "gn:timezone":"Africa/Libreville",
    "iso:country":"GA",
    "wof:name":"Moukouagna",
    "wof:placetype":"locality"
},
  "geometry": {"coordinates":[12.18333,-1.91667],"type":"Point"}
}