{
  "type": "Feature",
  "properties": {
    "gn:admin1_code":"07",
    "gn:asciiname":"Moukouagna",
    "gn:country_code":"GA",
    "gn:dem":356,
    "gn:feature_class":"P",
    "gn:feature_code":"PPL",
    "gn:name":"Moukouagna",
    "gn:population":0,
    "gn:timezone":"Africa/Libreville",
    "iso:country":"GA",
    "wof:name":"Moukouagna",
    "wof:placetype":"locality"
},
  "geometry": {"coordinates":[12.55314,-1.36246],"type":"Point"}
}