{
  "type": "Feature",
  "properties": {
    "gn:admin1_code":"09",
    "gn:asciiname":"Melene",
    "gn:country_code":"GA",
    "gn:dem":658,
    "gn:feature_class":"P",
    "gn:feature_code":"PPL",
    "gn:name":"Mel\u00e8ne",
    "gn:population":0,
    "gn:timezone":"Africa/Libreville",
    "iso:country":"GA",
    "wof:name":"Melene",
    "wof:placetype":"locality"
},
  "geometry": {"coordinates":[11.51323,1.55261],"type":"Point"}
}