{
  "type": "Feature",
  "properties": {
    "gn:admin1_code":"03",
    "gn:asciiname":"Nzeck",
    "gn:country_code":"GA",
    "gn:dem":60,
    "gn:feature_class":"P",
    "gn:feature_code":"PPL",
    "gn:name":"Nzeck",
    "gn:population":0,
    "gn:timezone":"Africa/Libreville",
    "iso:country":"GA",
    "wof:name":"Nzeck",
    "wof:placetype":"locality"
},
  "geometry": {"coordinates":[10.61667,-0.23333],"type":"Point"}
}