{
  "type": "Feature",
  "properties": {
    "gn:admin1_code":"01",
    "gn:asciiname":"Mvanayong",
    "gn:country_code":"GA",
    "gn:dem":51,
    "gn:feature_class":"P",
    "gn:feature_code":"PPL",
    "gn:name":"Mvanayong",
    "gn:population":0,
    "gn:timezone":"Africa/Libreville",
    "iso:country":"GA",
    "wof:name":"Mvanayong",
    "wof:placetype":"locality"
},
  "geometry": {"coordinates":[10.14794,0.49264],"type":"Point"}
}