{
  "type": "Feature",
  "properties": {
    "gn:admin1_code":"04",
    "gn:asciiname":"Baposo",
    "gn:country_code":"GA",
    "gn:dem":720,
    "gn:feature_class":"P",
    "gn:feature_code":"PPL",
    "gn:name":"Baposo",
    "gn:population":0,
    "gn:timezone":"Africa/Libreville",
    "iso:country":"GA",
    "name:und_x_variant":[
        "Baposso",
        "Baposso le Petit",
        "Baposso le Pointe",
        "Baposo"
    ],
    "wof:name":"Baposo",
    "wof:placetype":"locality"
},
  "geometry": {"coordinates":[12.18525,-2.10218],"type":"Point"}
}