{
  "type": "Feature",
  "properties": {
    "gn:admin1_code":"05",
    "gn:asciiname":"Nyanga-Vembe",
    "gn:country_code":"GA",
    "gn:dem":68,
    "gn:feature_class":"P",
    "gn:feature_code":"PPL",
    "gn:name":"Nyanga-Vembe",
    "gn:population":0,
    "gn:timezone":"Africa/Libreville",
    "iso:country":"GA",
    "name:und_x_variant":[
        "Nyanga",
        "Nyanga-Vembe"
    ],
    "wof:name":"Nyanga-Vembe",
    "wof:placetype":"locality"
},
  "geometry": {"coordinates":[10.69966,-2.62852],"type":"Point"}
}