{
  "type": "Feature",
  "properties": {
    "gn:admin1_code":"08",
    "gn:asciiname":"Vandarene Echira",
    "gn:country_code":"GA",
    "gn:dem":29,
    "gn:feature_class":"P",
    "gn:feature_code":"PPL",
    "gn:name":"Vandar\u00e9ne Echira",
    "gn:population":0,
    "gn:timezone":"Africa/Libreville",
    "iso:country":"GA",
    "name:und_x_variant":[
        "Vandar\u00e9n\u00e9",
        "Vandar\u00e9ne Echira"
    ],
    "wof:name":"Vandarene Echira",
    "wof:placetype":"locality"
},
  "geometry": {"coordinates":[9.5783,-1.66176],"type":"Point"}
}