{
  "type": "Feature",
  "properties": {
    "gn:admin1_code":"04",
    "gn:asciiname":"Digambo",
    "gn:country_code":"GA",
    "gn:dem":681,
    "gn:feature_class":"P",
    "gn:feature_code":"PPL",
    "gn:name":"Digambo",
    "gn:population":0,
    "gn:timezone":"Africa/Libreville",
    "iso:country":"GA",
    "wof:name":"Digambo",
    "wof:placetype":"locality"
},
  "geometry": {"coordinates":[11.78333,-1.86667],"type":"Point"}
}