{
  "type": "Feature",
  "properties": {
    "gn:admin1_code":"01",
    "gn:asciiname":"Obelo",
    "gn:cc2":"GA",
    "gn:country_code":"GA",
    "gn:dem":4,
    "gn:feature_class":"P",
    "gn:feature_code":"PPL",
    "gn:name":"Obelo",
    "gn:population":0,
    "gn:timezone":"Africa/Libreville",
    "iso:country":"GA",
    "name:und_x_variant":[
        "Ob\u00e9o",
        "Obelo"
    ],
    "wof:name":"Obelo",
    "wof:placetype":"locality"
},
  "geometry": {"coordinates":[9.41667,0.11667],"type":"Point"}
}