{
  "type": "Feature",
  "properties": {
    "gn:admin1_code":"09",
    "gn:asciiname":"Keng-Akok",
    "gn:country_code":"GA",
    "gn:dem":666,
    "gn:feature_class":"P",
    "gn:feature_code":"PPL",
    "gn:name":"Keng-Akok",
    "gn:population":0,
    "gn:timezone":"Africa/Libreville",
    "iso:country":"GA",
    "wof:name":"Keng-Akok",
    "wof:placetype":"locality"
},
  "geometry": {"coordinates":[11.58069,1.5847],"type":"Point"}
}