{
  "type": "Feature",
  "properties": {
    "gn:admin1_code":"02",
    "gn:asciiname":"Mabinga",
    "gn:country_code":"GA",
    "gn:dem":407,
    "gn:feature_class":"P",
    "gn:feature_code":"PPL",
    "gn:name":"Mabinga",
    "gn:population":0,
    "gn:timezone":"Africa/Libreville",
    "iso:country":"GA",
    "wof:name":"Mabinga",
    "wof:placetype":"locality"
},
  "geometry": {"coordinates":[13.20114,-1.51289],"type":"Point"}
}