{
  "type": "Feature",
  "properties": {
    "gn:admin1_code":"04",
    "gn:asciiname":"Nzila-Kala",
    "gn:country_code":"GA",
    "gn:dem":615,
    "gn:feature_class":"P",
    "gn:feature_code":"PPL",
    "gn:name":"Nzila-Kala",
    "gn:population":0,
    "gn:timezone":"Africa/Libreville",
    "iso:country":"GA",
    "wof:name":"Nzila-Kala",
    "wof:placetype":"locality"
},
  "geometry": {"coordinates":[11.81667,-2.08333],"type":"Point"}
}