{
  "type": "Feature",
  "properties": {
    "gn:admin1_code":"02",
    "gn:asciiname":"Ossouele",
    "gn:country_code":"GA",
    "gn:dem":535,
    "gn:feature_class":"P",
    "gn:feature_code":"PPL",
    "gn:name":"Ossou\u00e9l\u00e9",
    "gn:population":0,
    "gn:timezone":"Africa/Libreville",
    "iso:country":"GA",
    "wof:name":"Ossouele",
    "wof:placetype":"locality"
},
  "geometry": {"coordinates":[14.3704,-1.08865],"type":"Point"}
}