{
  "type": "Feature",
  "properties": {
    "gn:admin1_code":"09",
    "gn:asciiname":"Essong Abam III",
    "gn:country_code":"GA",
    "gn:dem":691,
    "gn:feature_class":"P",
    "gn:feature_code":"PPL",
    "gn:name":"Essong Abam III",
    "gn:population":0,
    "gn:timezone":"Africa/Libreville",
    "iso:country":"GA",
    "wof:name":"Essong Abam III",
    "wof:placetype":"locality"
},
  "geometry": {"coordinates":[11.41842,1.32358],"type":"Point"}
}