{
  "type": "Feature",
  "properties": {
    "gn:admin1_code":"07",
    "gn:asciiname":"Bounzoukou",
    "gn:country_code":"GA",
    "gn:dem":524,
    "gn:feature_class":"P",
    "gn:feature_code":"PPL",
    "gn:name":"Bounzoukou",
    "gn:population":0,
    "gn:timezone":"Africa/Libreville",
    "iso:country":"GA",
    "wof:name":"Bounzoukou",
    "wof:placetype":"locality"
},
  "geometry": {"coordinates":[12.91901,-1.12373],"type":"Point"}
}